Workbook

Sheet 规范整合泌尿系统医疗服务价格映射表12.11
A1: 附件1
A2: 泌尿系统类立项指南项目价格拟定情况
A3: 泌尿系统类立项指南项目 | V3: 现行价格项目
A4: 序号 | B4: 项目代码 | C4: 项目名称 | D4: 归集口径 | E4: 服务产出 | F4: 价格构成 | G4: 计价单位 | H4: 计价说明 | I4: 省三甲价格 | J4: 省三甲以下价格 | K4: 平移价格 (市级) | L4: 平移价格 (县级) | M4: 平移价格 (基层) | N4: 拟定价格 (市级) | O4: 拟定价格 (县级) | P4: 拟定价格 (基层) | Q4: 医保属性 | R4: 医保限定支付范围 | S4: 个人先行自付比例 | T4: 调整情况 | U4: 备注 | V4: 国家结算编码 | W4: 项目编码 | X4: 项目名称 | Y4: 项目内涵 | Z4: 除外内容 | AA4: 计价单位 | AB4: 说明 | AC4: 三甲 | AD4: 三甲以下 | AE4: 价格 (市级) | AF4: 价格 (县级) | AG4: 价格 (基层)
A5: 1 | B5: 012411000010000 | C5: 肾盂内压检查费 | D5: 检查费 | E5: 通过各种方式测定肾盂内压，辅助判断肾盂输尿管连接部是否存在梗阻。 | F5: 所定价格涵盖放置导管、注射、观察记录、出具报告、处理用物等步骤所需的人力资源和基本物质资源消耗。 | G5: 次 | H5: “次”指双侧，单侧按50%收取。 | I5: 240 | J5: 216 | N5: 220 | O5: 200 | P5: 170 | Q5: 非医保 | T5: 新增价格 | U5: 新增价格，按比价关系拟定 | V5: 003110000140000-311000014 | W5: 311000014 | X5: 肾盂测压 | AA5: 单侧
A6: 2 | B6: 012411000020000 | C6: 尿流动力学检查费 | D6: 检查费 | E6: 通过各种方式对尿路功能状态进行评估，辅助诊断尿路功能障碍性疾病。 | F6: 所定价格涵盖检测尿流率与动力学、出具报告、处理用物等步骤所需的人力资源和基本物质资源消耗。 | G6: 次 | H6: 尿流率检测市级医院收取66元/次，县级医院收取59元/次，基层收取51元/次。 | I6: 165 | J6: 150 | K6: 165 | L6: 150 | M6: 127.5 | N6: 165 | O6: 150 | P6: 128 | Q6: 医保 | T6: 平移 | U6: 平移后，县级按不高于省级拟定，基层取整。同质化高的项目持平省级定价。 | V6: 003110000390000-311000039 | W6: 311000039 | X6: 尿流动力学检测 | Y6: 不含摄片 | AA6: 次 | AC6: 165 | AD6: 150 | AE6: 165 | AF6: 150 | AG6: 127.5
C7: 尿流动力学检查费（尿流率检测） | K7: 66 | L7: 60 | M7: 51 | N7: 66 | O7: 59 | P7: 51 | V7: 003110000380000-311000038 | W7: 311000038 | X7: 尿流率检测 | AA7: 次 | AC7: 66 | AD7: 59 | AE7: 66 | AF7: 60 | AG7: 51
A8: 3 | B8: 012411000030000 | C8: 泌尿系镜检查费（肾镜） | D8: 检查费 | E8: 通过肾镜观察和诊断泌尿系统疾病。 | F8: 所定价格涵盖消毒、插管、扩张通道、观察、出具报告、处理用物、必要时穿刺等步骤所需的人力资源和基本物质资源消耗。 | G8: 单侧 | I8: 660 | J8: 595 | K8: 660 | L8: 600 | M8: 510 | N8: 660 | O8: 595 | P8: 510 | Q8: 医保 | T8: 理顺 | U8: 平移后，县级按不高于省级拟定 | V8: 003110000180000-311000018 | W8: 311000018 | X8: 经皮肾盂镜检查 | Y8: 含活检 | AA8: 单侧 | AC8: 660 | AD8: 595 | AE8: 660 | AF8: 600 | AG8: 510
A9: 4 | B9: 012411000040000 | C9: 泌尿系镜检查费（输尿管镜） | D9: 检查费 | E9: 通过输尿管镜观察和诊断泌尿系统疾病。 | F9: 所定价格涵盖消毒、插管、扩张通道、观察、出具报告、处理用物等步骤所需的人力资源和基本物质资源消耗。 | G9: 单侧 | I9: 499 | J9: 449 | K9: 495 | L9: 450 | M9: 382.5 | N9: 495 | O9: 445 | P9: 380 | Q9: 医保 | T9: 理顺，降低 | U9: 平移后，县级按不高于省级拟定，基层对应调整 | V9: 003110000200000-311000020 | W9: 311000020 | X9: 经尿道输尿管镜检查 | Y9: 含活检；包括取异物 | AA9: 单侧 | AC9: 495 | AD9: 445 | AE9: 495 | AF9: 450 | AG9: 382.5
A10: 分项 | B10: 012411000040100 | C10: 泌尿系镜检查费（输尿管镜）-精囊镜检查（扩展） | D10: 检查费 | G10: 单侧 | I10: 499 | J10: 449 | K10: 720 | L10: 648 | M10: 550.8 | N10: 495 | O10: 445 | P10: 380 | Q10: 医保 | U10: 扩展项按主项价格执行 | V10: 353111000290000-311100020 | W10: 311100020 | X10: 经尿道精囊镜检查 | Y10: 消毒，取Wolf4.5/6.5精囊镜连接电视成像系统，以生理盐水为灌注液，直视下将精囊镜经尿道置入膀胱，观察尿道、膀胱，将镜体退至精阜处，仔细观察射精管口，发现射精管口后稍加大灌注液速度，将镜体置入一侧射精管内，将镜体逐渐推进精囊内，观察射精管及精囊内情况，如有无结石、肿物及精囊液情况。含活检、斑马导丝。 | AA10: 侧 | AC10: 800 | AE10: 720 | AF10: 648 | AG10: 550.8
A11: 5 | B11: 012411000050000 | C11: 泌尿系镜检查费（膀胱镜尿道镜） | D11: 检查费 | E11: 通过膀胱镜尿道镜观察和诊断泌尿系统疾病。 | F11: 所定价格涵盖消毒、插管、扩张通道、观察、出具报告、处理用物等步骤所需的人力资源和基本物质资源消耗。 | G11: 次 | I11: 132 | J11: 120 | K11: 132 | L11: 120 | M11: 102 | N11: 132 | O11: 120 | P11: 102 | Q11: 医保 | T11: 平移 | U11: 平移 | V11: 003110000340000-311000034 | W11: 311000034 | X11: 膀胱镜尿道镜检查 | Y11: 含活检，包括取异物 | AA11: 次 | AC11: 132 | AD11: 120 | AE11: 132 | AF11: 120 | AG11: 102
A12: 6 | B12: 012412000010000 | C12: 性刺激勃起检查费 | D12: 检查费 | E12: 通过各种方式对患者在各类性刺激环境下勃起次数、持续时间、硬度分级等情况进行监测。 | F12: 所定价格涵盖消毒、设备准备、刺激、监测、读取结果、出具报告、处理用物等步骤所需的人力资源和基本物质资源消耗。 | G12: 次 | I12: 63 | J12: 57 | N12: 60 | O12: 54 | P12: 46 | Q12: 非医保 | T12: 新增项目 | U12: 新增项目，按比价关系拟定，同质化高的检查项目缩小价差
A13: 7 | B13: 012412000020000 | C13: 阴茎勃起检查费 | D13: 检查费 | E13: 对患者夜间或模拟夜间环境下勃起次数、持续时间、硬度分级等情况进行监测。 | F13: 所定价格涵盖消毒、设备准备、监测、读取结果、出具报告、处理用物等步骤所需的人力资源和基本物质资源消耗。 | G13: 次 | I13: 100 | J13: 90 | K13: 99 | L13: 89 | M13: 77 | N13: 99 | O13: 89 | P13: 77 | Q13: 非医保 | T13: 平移 | U13: 平移 | V13: 003111000030000-311100003 | W13: 311100003 | X13: 夜间阴茎胀大试验 | Y13: 含硬度计法 | AA13: 次 | AC13: 100 | AD13: 90 | AE13: 99 | AF13: 89 | AG13: 77
A14: 8 | B14: 012412000030000 | C14: 阴茎超声血流图检查费 | D14: 检查费 | E14: 对患者阴茎海绵体内血流情况进行检测。 | F14: 所定价格涵盖消毒、设备准备、检测、诊断、出具报告、处理用物等步骤所需的人力资源和基本物质资源消耗。 | G14: 次 | I14: 77 | J14: 69 | L14: 80 | N14: 77 | O14: 69 | P14: 60 | Q14: 非医保 | T14: 理顺，降低 | U14: 仅县级有工作量，平移后按不超过省级拟定，同质化高的项目持平省级定价。 | V14: 003111000040000-311100004 | W14: 311100004 | X14: 阴茎超声血流图检查 | AA14: 次 | AC14: 80 | AD14: 72 | AE14: 88 | AF14: 80 | AG14: 68
V15: 003111000110000-311100011 | W15: 311100011 | X15: 阴茎动脉测压术 | AA15: 次 | AC15: 44 | AD15: 40 | AE15: 44 | AF15: 40 | AG15: 34
A16: 9 | B16: 012412000040000 | C16: 阴茎勃起神经检查费 | D16: 检查费 | E16: 通过各种方式对患者勃起相关神经进行检测。 | F16: 所定价格涵盖消毒、设备准备、检测、读取结果、出具报告、处理用物等步骤所需的人力资源和基本物质资源消耗。 | G16: 次 | I16: 110 | J16: 99 | K16: 110 | L16: 100 | M16: 85 | N16: 110 | O16: 99 | P16: 85 | Q16: 非医保 | T16: 理顺 | U16: 平移后，县级按不高于省级拟定，同质化高的项目持平省级定价。 | V16: 003111000050000-311100005 | W16: 311100005 | X16: 阴茎勃起神经检查 | Y16: 含肌电图检查 | AA16: 次 | AC16: 110 | AD16: 99 | AE16: 110 | AF16: 100 | AG16: 85
A17: 10 | B17: 013110000010000 | C17: 血液透析费 | D17: 治疗费 | E17: 通过弥散和对流原理清除血液中过多水分和有害物质。 | F17: 所定价格涵盖消毒、穿刺、安装设定、连接管路、监测、血液回输、加压止血、封管、处理用物等步骤所需的人力资源和基本物质资源消耗。 | G17: 次 | H17: 本项目中的“监测”指：血温、血压、在线清除率、血容量监测，医院未完成全部四项监测事项的，每少完成一项监测减收5元。 | I17: 398 | J17: 398 | K17: 385 | L17: 370 | M17: 340 | N17: 385 | O17: 370 | P17: 340 | Q17: 医保 | T17: 已落地，直接平移 | U17: 2025年7月15日已落地执行 | V17: 013110000010000 | W17: 013110000010000 | X17: 血液透析费 | Y17: 通过弥散和对流原理清除血液中过多水分和有害物质。 | AA17: 次 | AB17: 本项目中的“监测”指：血温、血压、在线清除率、血容量监测，医院未完成全部四项监测事项的，每少完成一项监测减收5元。 | AC17: 398 | AD17: 398 | AE17: 385 | AF17: 370 | AG17: 340
A18: 11 | B18: 013110000020000 | C18: 血液滤过费 | D18: 治疗费 | E18: 通过对流原理清除血液中过多水分和有害物质。 | F18: 所定价格涵盖消毒、穿刺、建立通路、抗凝处理、连接管路、补充置换液、清除毒素及水分、监测、封管、处理用物等步骤所需的人力资源和基本物质资源消耗。 | G18: 次 | H18: 本项目中的“监测”指：血温、血压、在线清除率、血容量监测，医院未完成全部四项监测事项的，每少完成一项监测减收5元。 | I18: 398 | J18: 398 | K18: 395 | L18: 390 | M18: 355 | N18: 395 | O18: 390 | P18: 355 | Q18: 医保 | T18: 已落地，直接平移 | U18: 2025年7月15日已落地执行 | V18: 013110000020000 | W18: 013110000020000 | X18: 血液滤过费 | Y18: 通过对流原理清除血液中过多水分和有害物质。 | AA18: 次 | AB18: 本项目中的“监测”指：血温、血压、在线清除率、血容量监测，医院未完成全部四项监测事项的，每少完成一项监测减收5元。 | AC18: 398 | AD18: 398 | AE18: 395 | AF18: 390 | AG18: 355
A19: 12 | B19: 013110000030000 | C19: 血液透析滤过费 | D19: 治疗费 | E19: 通过同时进行血液透析和血液滤过清除血液中过多水分和有害物质。 | F19: 所定价格涵盖消毒、穿刺、建立通路、连接管路、参数设置、清除毒素及水分滤过、监测、封管、处理用物等步骤所需的人力资源和基本物质资源消耗。 | G19: 次 | H19: 本项目中的“监测”指：血温、血压、在线清除率、血容量监测，医院未完成全部四项监测事项的，每少完成一项监测减收5元。 | I19: 598 | J19: 598 | K19: 590 | L19: 575 | M19: 510 | N19: 590 | O19: 575 | P19: 510 | Q19: 医保 | T19: 已落地，直接平移 | U19: 2025年7月15日已落地执行 | V19: 013110000030000 | W19: 013110000030000 | X19: 血液透析滤过费 | Y19: 通过同时进行血液透析和血液滤过清除血液中过多水分和有害物质。 | AA19: 次 | AB19: 本项目中的“监测”指：血温、血压、在线清除率、血容量监测，医院未完成全部四项监测事项的，每少完成一项监测减收5元。 | AC19: 598 | AD19: 598 | AE19: 590 | AF19: 575 | AG19: 510
A20: 13 | B20: 013110000040000 | C20: 血液灌流费 | D20: 治疗费 | E20: 通过吸附原理‌直接结合血液中的中大分子及蛋白结合毒素。 | F20: 所定价格涵盖消毒、穿刺、建立通路、连接管路、参数设置、血液灌流、回输、封管、处理用物等步骤所需的人力资源和基本物质资源消耗。 | G20: 次 | I20: 300 | J20: 300 | K20: 275 | L20: 260 | M20: 250 | N20: 275 | O20: 260 | P20: 250 | T20: 已落地，直接平移 | U20: 2025年7月15日已落地执行 | V20: 013110000040000 | W20: 013110000040000 | X20: 血液灌流费 | Y20: 通过吸附原理‌直接结合血液中的中大分子及蛋白结合毒素。 | AA20: 次 | AC20: 300 | AD20: 300 | AE20: 275 | AF20: 260 | AG20: 250
A21: 14 | B21: 013110000050000 | C21: 血液透析灌流费 | D21: 治疗费 | E21: 通过同时进行血液透析和血液灌流清除血液中过多水分和有害物质。 | F21: 所定价格涵盖消毒、穿刺、建立通路、连接管路、参数设置、透析灌流、监测、封管、处理用物等步骤所需的人力资源和基本物质资源消耗。 | G21: 次 | H21: 本项目中的“监测”指：血温、血压、在线清除率、血容量监测，医院未完成全部四项监测事项的，每少完成一项监测减收5元。 | I21: 620 | J21: 620 | K21: 520 | L21: 520 | M21: 440 | N21: 520 | O21: 520 | P21: 440 | Q21: 医保 | S21: 0.05 | T21: 已落地，直接平移 | U21: 2025年7月15日已落地执行 | V21: 013110000050000 | W21: 013110000050000 | X21: 血液透析灌流费 | Y21: 通过同时进行血液透析和血液灌流清除血液中过多水分和有害物质。 | AA21: 次 | AB21: 本项目中的“监测”指：血温、血压、在线清除率、血容量监测，医院未完成全部四项监测事项的，每少完成一项监测减收5元。 | AC21: 620 | AD21: 620 | AE21: 520 | AF21: 520 | AG21: =420+20 -> 440
A22: 15 | B22: 013110000060000 | C22: 血浆置换费 | D22: 治疗费 | E22: 分离血浆、用置换液置换含有有害物质的血浆。 | F22: 所定价格涵盖消毒、穿刺、连接管路、血浆分离置换、回输、去除装置、处理用物等步骤所需的人力资源和基本物质资源消耗。 | G22: 次 | H22: 血浆置换费使用的滤器、血浆分离器、管路按零差率销售价格另行收取相应费用。 | I22: 800 | J22: 720 | N22: 750 | O22: 700 | P22: 595 | Q22: 医保 | S22: 0.2 | T22: 理顺 | U22: 2025年7月15日已落地执行，现将耗材剥离，重新制定价格。 血浆分离器、分离管路全市采购均价分别为2178元、1425元，耗材成本超过项目本身价格。 | V22: 003109050230000-310905023 | W22: 310905023 | X22: 人工肝治疗 | Z22: 一次性导管 | AA22: 次 | AC22: 1600 | AD22: 1440 | AE22: 1500 | AF22: 1350 | AG22: 1145
V23: 013110000060000 | W23: 013110000060000 | X23: 血浆置换费 | Y23: 分离血浆、用置换液置换含有有害物质的血浆。 | AC23: 2600 | AD23: 2340 | AE23: 2450 | AF23: 2325 | AG23: 2000
A24: 分项 | B24: 013110000060001 | C24: 血浆置换费-双重血浆置换（加收） | D24: 治疗费 | G24: 次 | I24: 340 | J24: 306 | N24: 320 | O24: 300 | P24: 255 | Q24: 医保 | S24: 0.2 | U24: 新增项目，按项目间比价关系拟定
A25: 16 | B25: 013110000070000 | C25: 血浆吸附费 | D25: 治疗费 | E25: 分离血浆，利用吸附原理清除血浆中特定有害物质。 | F25: 所定价格涵盖消毒、穿刺、连接管路、分离血浆、吸附清除致病物质、血细胞混合、回输、去除装置、处理用物等步骤所需的人力资源和基本物质资源消耗。 | G25: 次 | I25: 1200 | J25: 1080 | N25: 1100 | O25: 1000 | P25: 850 | Q25: 医保 | S25: 0.05 | T25: 新增价格 | U25: 新增价格，按比价关系拟定
A26: 17 | B26: 013110000080000 | C26: 连续性肾脏替代治疗费 | D26: 治疗费 | E26: 通过血液净化实现连续肾脏替代治疗和多脏器功能衰竭的生命支持治疗。 | F26: 所定价格涵盖消毒、穿刺、连接管路、上机、血液净化、体外抗凝、回输、去除装置、处理用物等步骤所需的人力资源和基本物质资源消耗。 | G26: 小时 | H26: 连续性肾脏替代治疗使用的滤器、管路按零差率销售价格另行收取相应费用。 | I26: 96 | J26: 96 | K26: 95 | L26: 95 | M26: 86 | N26: 95 | O26: 95 | P26: 86 | Q26: 医保 | T26: 已落地，直接平移 | U26: 新家 | V26: 013110000080000 | W26: 013110000080000 | X26: 连续性肾脏替代治疗费 | AA26: 小时 | AC26: 96 | AD26: 96 | AE26: 95 | AF26: 95 | AG26: 86
A27: 分项 | B27: 013110000080001 | C27: 连续性肾脏替代治疗费-连续性血浆吸附滤过治疗（加收） | D27: 治疗费 | G27: 小时 | I27: 30 | J27: 30 | K27: 28 | L27: 28 | M27: 25 | N27: 28 | O27: 28 | P27: 25 | Q27: 医保 | U27: 2025年7月15日已落地执行 | V27: 013110000080001 | W27: 013110000080001 | X27: 连续性肾脏替代治疗费-连续性血浆吸附滤过治疗（加收） | AA27: 小时 | AC27: 30 | AD27: 30 | AE27: 28 | AF27: 28 | AG27: 25
A28: 18 | B28: 013110000090000 | C28: 腹膜透析费（人工） | D28: 治疗费 | E28: 通过人工进行肾脏替代治疗，清除毒素和/或水分。 | F28: 所定价格涵盖操作前准备、透析管连接、注入透析液、引流液收集、记录等步骤所需的人力资源和基本物质资源消耗。 | G28: 次 | I28: 17 | J28: 15 | K28: 15 | L28: 15 | M28: 12.8 | N28: 15 | O28: 15 | P28: 12.8 | Q28: 医保 | T28: 已落地，直接平移 | U28: 2025年7月15日已落地执行 | W28: 013110000090000 | X28: 腹膜透析费（人工） | Y28: 通过人工进行肾脏替代治疗，清除毒素和/或水分。 | AA28: 次 | AC28: 17 | AD28: 15 | AE28: 15 | AF28: 15 | AG28: 12.8
A29: 19 | B29: 013110000100000 | C29: 腹膜透析费（自动） | D29: 治疗费 | E29: 通过设备进行肾脏替代治疗，清除毒素和/或水分。 | F29: 所定价格涵盖设备准备、透析管连接、设备运行、引流液收集、记录等步骤所需的人力资源和基本物质资源消耗。 | G29: 小时 | I29: 17 | J29: 15 | K29: 15 | L29: 15 | M29: 12.8 | N29: 15 | O29: 15 | P29: 12.8 | Q29: 医保 | S29: 0.05 | T29: 已落地，直接平移 | U29: 2025年7月15日已落地执行 | W29: 013110000100000 | X29: 腹膜透析费（自动） | Y29: 通过设备进行肾脏替代治疗，清除毒素和/或水分。 | AA29: 小时 | AC29: 17 | AD29: 15 | AE29: 15 | AF29: 15 | AG29: 12.8
A30: 20 | B30: 013110000110000 | C30: 腹膜透析操作训练费 | D30: 治疗费 | E30: 由医疗机构提供腹膜透析治疗的相关操作训练和指导，使患者具备自我操作腹膜透析和疾病自我管理的能力。 | F30: 所定价格涵盖医务人员对患者及照顾者进行培训，使其掌握家庭腹膜透析技能所需的人力资源和基本物质资源消耗。 | G30: 小时 | H30: 超过4小时按4小时收取。 | I30: 50 | J30: 45 | N30: 45 | O30: 41 | P30: 35 | Q30: 医保 | S30: 0.2 | T30: 新增项目 | U30: 新增项目，按比价关系拟定
A31: 21 | B31: 013110000120000 | C31: 腹膜透析延伸服务费 | D31: 治疗费 | E31: 通过各种方式向在院外进行腹膜透析治疗的患者提供沟通、评估及指导等医学服务。 | F31: 所定价格涵盖医务人员对患者进行沟通、评估及指导等所需的人力资源和基本物质资源消耗。 | G31: 月 | H31: 医疗机构收取该项费用应以每周最少完成一次延伸服务为前提。居家自动腹膜透析远程实时监测不得同时收取腹膜透析延伸服务费。 | I31: 150 | J31: 135 | N31: 135 | O31: 125 | P31: 110 | Q31: 医保 | S31: 0.2 | T31: 新增项目 | U31: 新增项目，按比价关系拟定
A32: 22 | B32: 013110000130000 | C32: 透析管路处理费 | D32: 治疗费 | E32: 溶解透析管路内栓塞物，恢复透析管路通畅。 | F32: 所定价格涵盖消毒、反复溶栓药物注射、留置、抽取、封管、处理用物等步骤所需的人力资源和基本物质资源消耗。 | G32: 次 | I32: 120 | J32: 108 | N32: 110 | O32: 100 | P32: 85 | Q32: 医保 | S32: 0.2 | T32: 新增项目 | U32: 新增项目，按比价关系拟定
A33: 23 | B33: 013110000140000 | C33: 腹膜透析外管更换费 | D33: 治疗费 | E33: 通过各种方式更换腹膜透析外接短管。 | F33: 所定价格涵盖消毒、更换管路、封管、处理用物等步骤所需的人力资源和基本物质资源消耗。 | G33: 次 | I33: 45 | J33: 41 | K33: 40 | L33: 40 | M33: 34 | N33: 42 | O33: 40 | P33: 34 | Q33: 医保 | T33: 理顺 | U33: 2025年7月15日已在“腹膜透析换管费”说明中落地执行，此次调整市级理顺比价 | V33: 013311000020000 | W33: 013311000020000 | X33: 腹膜透析换管费（更换外管） | AA33: 次
A34: 24 | B34: 013110000150000 | C34: 腹膜平衡试验费 | D34: 治疗费 | E34: 对腹膜功能进行检测，调整腹膜透析方案。 | F34: 所定价格涵盖腹透换液、留取标本、测量、计算、出具方案、处理用物等步骤所需的人力资源和基本物质资源消耗。 | G34: 次 | I34: 45 | J34: 41 | K34: 40 | L34: 40 | M34: 34 | N34: 42 | O34: 40 | P34: 34 | Q34: 医保 | T34: 理顺 | U34: 2025年7月15日已落地执行，此次调整市级理顺比价 | V34: 013110000150000 | W34: 013110000150000 | X34: 腹膜平衡试验费 | Y34: 对腹膜功能进行检测，调整腹膜透析方案。 | AA34: 次 | AC34: 45 | AD34: 41 | AE34: 40 | AF34: 40 | AG34: 34
A35: 25 | B35: 013311000010000 | C35: 腹膜透析置管费 | D35: 手术费 | E35: 通过各种方式放置腹膜透析导管。 | F35: 所定价格涵盖消毒、切开、穿刺或分离、置管、试水通畅、缝合、处理用物等步骤所需的人力资源和基本物质资源消耗。 | G35: 次 | I35: 440 | J35: 395 | K35: 400 | L35: 400 | M35: 340 | N35: 420 | O35: 395 | P35: 340 | Q35: 医保 | T35: 理顺 | U35: 2025年7月15日已落地执行，现微调市级、县级价格以理顺比价 | V35: 013311000010000 | W35: 013311000010000 | X35: 腹膜透析置管费 | Y35: 通过各种方式放置腹膜透析导管。 | AA35: 次 | AC35: 440 | AD35: 395 | AE35: 400 | AF35: 400 | AG35: 340
A36: 分项 | B36: 013311000010001 | C36: 腹膜透析置管费-儿童（加收） | D36: 手术费 | G36: 次 | I36: 0 | J36: 0 | N36: 0 | O36: 0 | P36: 0 | Q36: 医保 | U36: 新增儿童加收项目，福建省目前不予区分定价，因此定价为0
A37: 26 | B37: 013311000020000 | C37: 腹膜透析换管费 | D37: 手术费 | E37: 更换破损、堵塞、移位的腹膜透析导管。 | F37: 所定价格涵盖消毒、切开、拔除旧管、原位置入新管、试水通畅、缝合、处理用物等步骤所需的人力资源和基本物质资源消耗。 | G37: 次 | H37: 不与“腹膜透析置管费”“腹膜透析导管取出费”“腹膜透析导管感染清创费”同时收取。 | I37: 440 | J37: 395 | K37: 420 | L37: 420 | M37: 360 | N37: 420 | O37: 395 | P37: 340 | Q37: 医保 | T37: 理顺 | U37: 2025年7月15日已落地执行，现调整说明，更换外管独立设立项目 微调价格理顺比价 | V37: 013311000020000 | W37: 013311000020000 | X37: 腹膜透析换管费 | Y37: 更换破损、堵塞、移位的腹膜透析导管。 | AA37: 次 | AB37: 不与“腹膜透析置管费”“腹膜透析导管取出费”“腹膜透析导管感染清创费”同时收取。更换外管市、县级按40元收取，基层按34元收取。 | AC37: 440 | AD37: 395 | AE37: 420 | AF37: 420 | AG37: 360
A38: 分项 | B38: 013311000020001 | C38: 腹膜透析换管费-儿童（加收） | D38: 手术费 | G38: 次 | I38: 0 | J38: 0 | N38: 0 | O38: 0 | P38: 0 | Q38: 医保 | U38: 新增儿童加收项目，福建省目前不予区分定价，因此定价为0
A39: 27 | B39: 013110000160000 | C39: 腹膜透析导管复位费（导丝复位） | D39: 治疗费 | E39: 通过导丝调整复位移位的腹膜透析导管，恢复导管功能。 | F39: 所定价格涵盖消毒、修复、调整管路、试水通畅等步骤所需的人力资源和基本物质资源消耗。 | G39: 次 | H39: 不与“腹膜透析导管复位费（手术复位）”同时收取。 | I39: 300 | J39: 270 | N39: 270 | O39: 245 | P39: 210 | Q39: 医保 | S39: 0.2 | T39: 新增项目 | U39: 新增项目，按比价关系拟定
A40: 28 | B40: 013311000030000 | C40: 腹膜透析导管复位费（手术复位） | D40: 手术费 | E40: 通过手术调整复位移位的腹膜透析导管，恢复导管功能。 | F40: 所定价格涵盖消毒、修复、调整管路、试水通畅、缝合及必要时使用导丝调整、处理用物等步骤所需的人力资源和基本物质资源消耗。 | G40: 次 | H40: 不与“腹膜透析导管复位费（导丝复位）”同时收取。 | I40: 500 | J40: 450 | N40: 450 | O40: 410 | P40: 350 | Q40: 医保 | S40: 0.2 | T40: 新增项目 | U40: 新增项目，按比价关系拟定
A41: 分项 | B41: 013311000030001 | C41: 腹膜透析导管复位费（手术复位）-儿童（加收） | D41: 手术费 | G41: 次 | I41: 150 | J41: 135 | N41: 135 | O41: 125 | P41: 105 | Q41: 医保 | U41: 新增儿童加收项目，儿童按30%加收
A42: 29 | B42: 013110000170000 | C42: 腹膜透析导管取出费 | D42: 治疗费 | E42: 通过各种方式取出腹膜透析导管。 | F42: 所定价格涵盖消毒、切开、分离、拔管、缝合等步骤所需的人力资源和基本物质资源消耗。 | G42: 次 | I42: 440 | J42: 395 | K42: 400 | L42: 400 | M42: 340 | N42: 420 | O42: 395 | P42: 340 | Q42: 医保 | T42: 理顺 | U42: 2025年7月15日已落地执行，现微调市级、县级价格以理顺比价 | W42: 013110000170000 | X42: 腹膜透析导管取出费 | Y42: 通过各种方式取出腹膜透析导管。 | AA42: 次 | AC42: 440 | AD42: 395 | AE42: 400 | AF42: 400 | AG42: 340
A43: 30 | B43: 013110000180000 | C43: 腹膜透析导管感染清创费 | D43: 治疗费 | E43: 清除感染的腹膜透析导管外涤纶套。 | F43: 所定价格涵盖消毒、切开、游离、清除涤纶套、缝合及必要时更换管路、处理用物等步骤所需的人力资源和基本物质资源消耗。 | G43: 次 | H43: 不与“腹膜透析换管费”同时收取。 | I43: 300 | J43: 270 | N43: 270 | O43: 245 | P43: 210 | Q43: 医保 | S43: 0.2 | T43: 新增项目 | U43: 新增项目，按比价关系拟定
A44: 31 | B44: 013110000190000 | C44: 体外冲击波碎石费 | D44: 治疗费 | E44: 通过冲击波聚焦能量，裂解尿路结石，便于结石排出。 | F44: 所定价格涵盖体位摆放、机器校准、能量释放、结石裂解、排出体外等步骤所需的人力资源和基本物质资源消耗。 | G44: 次 | H44: 第二次碎石市级医院收取350元/次，县级医院收取315元/次，基层收取268元/次；第三次碎石市级医院收取175元/次，县级医院收取158元/次，基层收取134元/次；第四次起不收费。 | I44: 700 | J44: 630 | K44: 700 | L44: 630 | M44: 535.5 | N44: 700 | O44: 630 | P44: 535 | Q44: 医保 | S44: 0.2 | T44: 平移 | U44: 平移，取整 | V44: 003110000400000-311000040 | W44: 311000040 | X44: 体外冲击波碎石 | Y44: 含影像学监测,不含摄片 | AA44: 次 | AB44: 第二次碎石按全价50%计价，第三次按25%计价，第四次起不收费。 | AC44: 700 | AD44: 630 | AE44: 700 | AF44: 630 | AG44: 535.5
C45: 体外冲击波碎石费（第二次） | D45: 治疗费 | G45: 次 | I45: 350 | J45: 315 | K45: 350 | L45: 315 | M45: 267.75 | N45: 350 | O45: 315 | P45: 268 | U45: 平移，取整 | V45: 003110000400000-31100004003 | W45: 31100004003 | X45: 体外冲击波碎石（第二次） | AA45: 次 | AB45: 第二次 | AC45: 350 | AD45: 315 | AE45: 350 | AF45: 315 | AG45: 267.8
C46: 体外冲击波碎石费（第三次） | D46: 治疗费 | G46: 次 | I46: 175 | J46: 158 | K46: 175 | L46: 157.5 | M46: 133.875 | N46: 175 | O46: 158 | P46: 134 | U46: 平移，取整 | V46: 003110000400000-31100004006 | W46: 31100004006 | X46: 体外冲击波碎石（第三次） | AA46: 次 | AB46: 第三次 | AC46: 175 | AD46: 158 | AE46: 175 | AF46: 157.5 | AG46: 133.9
A47: 32 | B47: 013110000200000 | C47: 泌尿系镜下治疗费（常规） | D47: 治疗费 | E47: 通过置物、取物等方式对泌尿系统及男性生殖系统病灶进行治疗。 | F47: 所定价格涵盖消毒、下镜、治疗、撤镜等步骤所需的人力资源和基本物质资源消耗。（不含泌尿系镜下检查） | G47: 次 | H47: 同时行常规治疗和特殊治疗的，按照“泌尿系镜下治疗费（特殊）”收取。 | I47: 825 | J47: 743 | K47: 817.32836 | L47: 741.1044 | M47: 640.94595 | N47: 815 | O47: 740 | P47: 640 | Q47: 医保 | T47: 平移取整 | U47: 加权平移取整 | V47: 003110000190200-31100001901 | W47: 31100001901 | X47: 经皮肾盂镜取石术（取异物） | AA47: 次 | AB47: 取异物 | AC47: 880 | AD47: 790 | AE47: 880 | AF47: 800 | AG47: 680
V48: 003311030270000-331103027 | W48: 331103027 | X48: 经尿道膀胱碎石取石术 | Y48: 包括血块、异物取出 | AA48: 次 | AC48: 1250 | AD48: 1125 | AE48: 1250 | AF48: 1200 | AG48: 1020
V49: 003311030270000-33110302701 | W49: 33110302701 | X49: 小儿经尿道膀胱碎石取石术 | AA49: 次 | AC49: 1625 | AD49: 1465 | AE49: 1625 | AF49: 1560 | AG49: 1325
V50: 003110000200000-311000020 | W50: 311000020 | X50: 经尿道输尿管镜检查 | Y50: 含活检；包括取异物 | AA50: 单侧 | AC50: 495 | AD50: 445 | AE50: 495 | AF50: 450 | AG50: 382.5
V51: 003110000370000-311000037 | W51: 311000037 | X51: 经尿道治疗尿失禁 | Y51: 含硬化剂局部注射 | AA51: 次 | AC51: 220 | AD51: 200 | AE51: 220 | AF51: 200 | AG51: 170
V52: 003312010070000-331201007 | W52: 331201007 | X52: 经尿道前列腺气囊扩张术 | Z52: 气囊导管 | AA52: 次 | AC52: 250 | AD52: 225 | AE52: 250 | AF52: 240 | AG52: 204
V53: 003312010070000-33120100701 | W53: 33120100701 | X53: 小儿经尿道前列腺气囊扩张术 | AA53: 次 | AC53: 325 | AD53: 295 | AE53: 325 | AF53: 310 | AG53: 265
V54: 003312010070000-33120100702 | W54: 33120100702 | X54: 经膀胱镜经尿道前列腺气囊扩张术 | AA54: 次 | AC54: 500 | AD54: 450 | AE54: 500 | AF54: 465 | AG54: 394
V55: 003312010070000-33120100703 | W55: 33120100703 | X55: 小儿经膀胱镜经尿道前列腺气囊扩张术 | AA55: 次 | AC55: 575 | AD55: 520 | AE55: 575 | AF55: 535 | AG55: 455
V56: 353312030140000-331203014 | W56: 331203014 | X56: 经精囊镜射精管疏通冲洗术 | Y56: 消毒，取Wolf4.5/6.5精囊镜连接电视成像系统，以生理盐水为灌注液，直视下将精囊镜经尿道置入膀胱，观察尿道、膀胱，将镜体退至精阜处，仔细观察射精管口，发现射精管口后稍加大灌注液速度，置入斑马导丝，沿斑马导丝用镜体边扩张边将镜体置入一侧射精管内，并逐渐推进精囊内，用生理盐水或药物反复冲洗精囊直至冲洗液变清，并取精囊液送细菌培养。含射精管扩张术、斑马导丝。 | AA56: 侧 | AC56: 1000 | AE56: 900 | AF56: 810 | AG56: 688.5
A57: 33 | B57: 013110000210000 | C57: 泌尿系镜下治疗费（特殊） | D57: 治疗费 | E57: 通过电凝、冷冻、蒸汽、射频、微波等各种物理方式对泌尿系统及男性生殖系统病灶进行治疗。 | F57: 所定价格涵盖消毒、下镜、治疗、取出、撤镜等步骤所需的人力资源和基本物质资源消耗。（不含泌尿系镜下检查） | G57: 次 | H57: 1.同一治疗位置使用多种能量源只可收取一次。 2.同时行常规治疗和特殊治疗的，按照“泌尿系镜下治疗费（特殊）”收取。 | I57: 1900 | J57: 1710 | K57: 2248.5461 | L57: 1514.4078 | M57: 1109.2737 | N57: 1875 | O57: 1700 | P57: 1470 | Q57: 医保 | T57: 理顺 | U57: 扣除原项目中涉及的内镜使用费用后加权平均，根据项目间比价关系，为常规的2.3倍。 | V57: 003110000260000-311000026 | W57: 311000026 | X57: 经输尿管镜碎石取石术 | AA57: 次 | AB57: 弹道法基层850元，县级医院1000元，市级医院1100元；激光基层1360元，县级医院1600元，市级医院1760元。 | AC57: 990 | AD57: 890 | AE57: 990 | AF57: 900 | AG57: 765 | AH57: =K9 -> 495 | AI57: =L9 -> 450 | AJ57: =M9 -> 382.5 | AK57: 输尿管镜
V58: 003110000260000-31100002601 | W58: 31100002601 | X58: 经输尿管镜碎石取石术（弹道法） | AA58: 次 | AB58: 弹道法 | AC58: 1100 | AD58: 990 | AE58: 1100 | AF58: 1000 | AG58: 850
V59: 003110000260000-31100002602 | W59: 31100002602 | X59: 经输尿管镜碎石取石术（激光法） | AA59: 次 | AB59: 激光法 | AC59: 1760 | AD59: 1580 | AE59: 1760 | AF59: 1600 | AG59: 1360
V60: 003110000350000-311000035 | W60: 311000035 | X60: 经膀胱镜尿道镜特殊治疗 | AA60: 次 | AB60: 激光法基层178.5元，县级医院210元，市级医院231元 | AC60: 176 | AD60: 160 | AE60: 176 | AF60: 160 | AG60: 136
V61: 003110000350000-31100003501 | W61: 31100003501 | X61: 经膀胱镜尿道镜特殊治疗（激光法） | AA61: 次 | AB61: 激光法 | AC61: 230 | AD61: 210 | AE61: 231 | AF61: 210 | AG61: 178.5
V62: 003311030260000-331103026 | W62: 331103026 | X62: 经尿道膀胱肿瘤特殊治疗 | Y62: 指电灼、激光法 | AA62: 次 | AB62: 电切法市级医院2590元，县级医院2330元，基层1980元 | AC62: 2880 | AD62: 2590 | AE62: 2530 | AF62: 2280 | AG62: 1940
V63: 003311030260000-33110302601 | W63: 33110302601 | X63: 经尿道膀胱肿瘤特殊治疗（电切法） | AA63: 次 | AB63: 电切法 | AC63: 3360 | AD63: 3020 | AE63: 2590 | AF63: 2330 | AG63: 1980
V64: 003311030260000-33110302602 | W64: 33110302602 | X64: 小儿经尿道膀胱肿瘤特殊治疗 | AA64: 次 | AC64: 3745 | AD64: 3365 | AE64: 3290 | AF64: 2965 | AG64: 2520
V65: 003311030260000-33110302603 | W65: 33110302603 | X65: 小儿经尿道膀胱肿瘤特殊治疗（电切法） | AA65: 次 | AB65: 电切法 | AC65: 4370 | AD65: 3925 | AE65: 3365 | AF65: 3030 | AG65: 2575
V66: 003311030260000-33110302604 | W66: 33110302604 | X66: 经膀胱镜下经尿道膀胱肿瘤特殊治疗 | AA66: 次 | AC66: 3130 | AD66: 2815 | AE66: 2780 | AF66: 2505 | AG66: 2130 | AH66: 132 | AI66: 120 | AJ66: 102 | AK66: 膀胱镜
V67: 003311030260000-33110302605 | W67: 33110302605 | X67: 经膀胱镜下经尿道膀胱肿瘤特殊治疗（电切法） | AA67: 次 | AB67: 电切法 | AC67: 3610 | AD67: 3245 | AE67: 2840 | AF67: 2555 | AG67: 2170
V68: 003311030260000-33110302606 | W68: 33110302606 | X68: 小儿经膀胱镜下经尿道膀胱肿瘤特殊治疗 | AA68: 次 | AC68: 3995 | AD68: 3590 | AE68: 3540 | AF68: 3190 | AG68: 2710
V69: 003311030260000-33110302607 | W69: 33110302607 | X69: 小儿经膀胱镜下经尿道膀胱肿瘤特殊治疗（电切法） | AA69: 次 | AB69: 电切法 | AC69: 4620 | AD69: 4150 | AE69: 3615 | AF69: 3255 | AG69: 2765
V70: 003311030270000-33110302702 | W70: 33110302702 | X70: 膀胱镜下经尿道膀胱碎石取石术 | AA70: 次 | AC70: 1500 | AD70: 1350 | AE70: 1500 | AF70: 1425 | AG70: 1210
V71: 003311030270000-33110302703 | W71: 33110302703 | X71: 小儿膀胱镜下经尿道膀胱碎石取石术 | AA71: 次 | AC71: 1875 | AD71: 1690 | AE71: 1875 | AF71: 1785 | AG71: 1515
V72: 003312010060000-331201006 | W72: 331201006 | X72: 经尿道前列腺电切术 | AA72: 次 | AB72: 电切法市级医院3635元，县级医院3270元，基层2780元；等离子法市级医院3310元，县级医院2980元，基层2530元 | AC72: 3080 | AD72: 2770 | AE72: 2530 | AF72: 2280 | AG72: 1940
V73: 003312010060000-33120100601 | W73: 33120100601 | X73: 经尿道前列腺电切术（电切法） | AA73: 次 | AB73: 电切法 | AC73: 4040 | AD73: 3630 | AE73: 3635 | AF73: 3270 | AG73: 2780
V74: 003312010060000-33120100602 | W74: 33120100602 | X74: 经尿道前列腺电切术（等离子法） | AA74: 次 | AB74: 等离子法 | AC74: 4360 | AD74: 3920 | AE74: 3310 | AF74: 2980 | AG74: 2530
V75: 003312010060000-33120100603 | W75: 33120100603 | X75: 小儿经尿道前列腺电切术 | AA75: 次 | AC75: 4000 | AD75: 3600 | AE75: 3290 | AF75: 2965 | AG75: 2520
V76: 003312010060000-33120100604 | W76: 33120100604 | X76: 小儿经尿道前列腺电切术（电切法） | AA76: 次 | AB76: 电切法 | AC76: 5250 | AD76: 4720 | AE76: 4725 | AF76: 4250 | AG76: 3615
V77: 003312010060000-33120100605 | W77: 33120100605 | X77: 小儿经尿道前列腺电切术（等离子法） | AA77: 次 | AB77: 等离子法 | AC77: 5670 | AD77: 5090 | AE77: 4305 | AF77: 3875 | AG77: 3295
V78: 003312010060000-33120100606 | W78: 33120100606 | X78: 经膀胱镜经尿道前列腺电切术 | AA78: 次 | AC78: 3130 | AD78: 2815 | AE78: 2780 | AF78: 2505 | AG78: 2130
V79: 003312010060000-33120100607 | W79: 33120100607 | X79: 经膀胱镜经尿道前列腺电切术（电切法） | AA79: 次 | AB79: 电切法 | AC79: 4090 | AD79: 3675 | AE79: 3270 | AF79: 2945 | AG79: 2500
V80: 003312010060000-33120100608 | W80: 33120100608 | X80: 经膀胱镜经尿道前列腺电切术（等离子法） | AA80: 次 | AB80: 等离子法 | AC80: 4410 | AD80: 3965 | AE80: 3560 | AF80: 3205 | AG80: 2720
V81: 003312010060000-33120100609 | W81: 33120100609 | X81: 小儿经膀胱镜经尿道前列腺电切术 | AA81: 次 | AC81: 3995 | AD81: 3590 | AE81: 3540 | AF81: 3190 | AG81: 2710
V82: 003312010060000-33120100610 | W82: 33120100610 | X82: 小儿经膀胱镜经尿道前列腺电切术（电切法） | AA82: 次 | AB82: 电切法 | AC82: 5240 | AD82: 4710 | AE82: 4175 | AF82: 3760 | AG82: 3195
V83: 003312010060000-33120100611 | W83: 33120100611 | X83: 小儿经膀胱镜经尿道前列腺电切术（等离子法） | AA83: 次 | AB83: 等离子法 | AC83: 5660 | AD83: 5085 | AE83: 4555 | AF83: 4100 | AG83: 3485
V84: 003312010060000-331201010 | W84: 331201010 | X84: 经尿道前列腺激光切除术 | Y84: 会阴区消毒，尿道润滑，尿道膀胱镜检查，使用激光纤维，剜除前列腺组织，止血，膀胱冲洗，取出前列腺组织，留置尿管。 | AA84: 次 | AC84: 4500 | AD84: 4050 | AE84: 4500 | AF84: 4500 | AG84: 3825
V85: 353312030150100-331203015 | W85: 331203015 | X85: 经精囊镜碎石取石术（激光法） | Y85: 消毒，取Wolf4.5/6.5精囊镜连接电视成像系统，以生理盐水为灌注液，直视下将精囊镜经尿道置入膀胱，观察尿道、膀胱，将镜体退至精阜处，仔细观察射精管口，发现射精管口后稍加大灌注液速度，轻柔的将镜体置入一侧射精管内，将镜体逐渐推进精囊内，连接激光设备，用激光将结石逐一击碎并用取石钳夹出、套石篮取出或生理盐水冲出结石。含斑马导丝。 | AA85: 侧 | AB85: 激光法 | AC85: 2300 | AE85: 2070 | AF85: 1863 | AG85: 1583.6 | AH85: =N10 -> 495 | AI85: =O10 -> 445 | AJ85: =P10 -> 380 | AK85: 精囊镜
V86: 353312030150200-331203016 | W86: 331203016 | X86: 经精囊镜碎石取石术（弹道法） | Y86: 消毒，取Wolf4.5/6.5精囊镜连接电视成像系统，以生理盐水为灌注液，直视下将精囊镜经尿道置入膀胱，观察尿道、膀胱，将镜体退至精阜处，仔细观察射精管口，发现射精管口后稍加大灌注液速度，轻柔的将镜体置入一侧射精管内，将镜体逐渐推进精囊内，连接气压弹道碎石设备，用探针将结石逐一击碎并用取石钳夹出、套石篮取出或生理盐水冲出结石。含斑马导丝。 | AA86: 侧 | AB86: 弹道法 | AC86: 1600 | AE86: 1440 | AF86: 1296 | AG86: 1101.6
V87: 353312030150300-331203017 | W87: 331203017 | X87: 经精囊镜碎石取石术（直接法） | Y87: 消毒，取Wolf4.5/6.5精囊镜连接电视成像系统，以生理盐水为灌注液，直视下将精囊镜经尿道置入膀胱，观察尿道、膀胱，将镜体退至精阜处，仔细观察射精管口，发现射精管口后稍加大灌注液速度，轻柔的将镜体置入一侧射精管内，将镜体逐渐推进精囊内，将结石用取石钳夹出、套石篮取出或生理盐水冲出结石。含斑马导丝。 | AA87: 侧 | AB87: 直接法 | AC87: 1400 | AE87: 1260 | AF87: 1134 | AG87: 963.9
V88: 353312040150000-331204020 | W88: 331204020 | X88: 经精囊镜肿物切除术 | Y88: 消毒，取Wolf4.5/6.5精囊镜连接电视成像系统，以生理盐水为灌注液，直视下将精囊镜经尿道置入膀胱，观察尿道、膀胱，将镜体退至精阜处，仔细观察射精管口，发现射精管口后稍加大灌注液速度，轻柔的将镜体置入一侧射精管内，连接激光设备，激光下电灼或切除肿物、囊肿壁等。含斑马导丝。 | AA88: 侧 | AC88: 2300 | AE88: 2070 | AF88: 1863 | AG88: 1583.6
V89: 353312040150000-33120402001 | W89: 33120402001 | X89: 小儿经精囊镜肿物切除术 | AA89: 侧 | AC89: 2990 | AE89: 2690 | AF89: 2420 | AG89: 2055
V90: 353110000440000-A331203018 | W90: A331203018 | X90: 经皮肾镜碎石取石术 | Y90: 包括气压弹道法、超声碎石法、激光碎石法。 | Z90: 导管、导丝、支架 | AA90: 次 | AB90: 两种及以上方法加收20% | AE90: 自主 定价 | AF90: 自主 定价 | AG90: 自主 定价 | AH90: =N8 -> 660 | AI90: =O8 -> 595 | AJ90: =P8 -> 510 | AK90: 肾镜
V91: 353110000440000-A33120301801 | W91: A33120301801 | X91: 经皮肾镜碎石取石术（两种及以上方法加收20%） | AA91: 次 | AB91: 两种及以上方法加收20% | AE91: 自主 定价 | AF91: 自主 定价 | AG91: 自主 定价
A92: 34 | B92: 013311000040000 | C92: 泌尿系异物取出费 | D92: 手术费 | E92: 通过手术从下尿路取出异物。 | F92: 所定价格涵盖手术计划、术区准备、消毒、取出异物、缝合、处理用物等步骤所需的人力资源和基本物质资源消耗。 | G92: 次 | I92: 1220 | J92: 1100 | K92: 1125 | L92: 1080 | M92: 918 | N92: 1125 | O92: 1080 | P92: 918 | Q92: 医保 | T92: 平移 | U92: 平移 | V92: 003311040050000-331104005 | W92: 331104005 | X92: 尿道切开取石术 | Y92: 包括前后尿道及取异物术 | AA92: 次 | AC92: 1220 | AD92: 1090 | AE92: 1125 | AF92: 1080 | AG92: 918
A93: 分项 | B93: 013311000040001 | C93: 泌尿系异物取出费-上尿路（加收） | D93: 手术费 | G93: 次 | H93: 本项目中的“上尿路”指：肾脏及输尿管。 | I93: 378 | J93: 340 | N93: 350 | O93: 335 | P93: 285 | Q93: 医保 | U93: 新增项目，按主项比价关系拟定
A94: 分项 | B94: 013311000040011 | C94: 泌尿系异物取出费-儿童（加收） | D94: 手术费 | G94: 次 | I94: 366 | J94: 330 | N94: 340 | O94: 325 | P94: 275 | Q94: 医保 | U94: 新增项目，按主项比价关系拟定
A95: 35 | B95: 013311000050000 | C95: 泌尿系取石费 | D95: 手术费 | E95: 通过手术从下尿路取出结石。 | F95: 所定价格涵盖手术计划、术区准备、消毒、取石、缝合、处理用物等步骤所需的人力资源和基本物质资源消耗。 | G95: 次 | I95: 1350 | J95: 1215 | K95: 1000 | L95: 986.66667 | M95: 918 | N95: 1250 | O95: 1200 | P95: 1020 | Q95: 医保 | T95: 理顺，提高 | U95: 加权平均后，根据项目间比价关系，理顺项目价格（泌尿系异物取出费为该项目的90%） | V95: 003311030010000-331103001 | W95: 331103001 | X95: 膀胱切开取石术 | AA95: 次 | AC95: 1000 | AD95: 900 | AE95: 1000 | AF95: 960 | AG95: 816
V96: 003311030010000-33110300102 | W96: 33110300102 | X96: 经腹腔镜膀胱切开取石术 | AA96: 次 | AC96: 1800 | AD96: 1620 | AE96: 1625 | AF96: 1560 | AG96: 1326
V97: 003311040050000-331104005 | W97: 331104005 | X97: 尿道切开取石术 | Y97: 包括前后尿道及取异物术 | AA97: 次 | AC97: 1220 | AD97: 1090 | AE97: 1125 | AF97: 1080 | AG97: 918
V98: 003311040050000-33110400502 | W98: 33110400502 | X98: 经膀胱镜尿道切开取石术 | AA98: 次 | AC98: 1470 | AD98: 1315 | AE98: 1375 | AF98: 1305 | AG98: 1108
A99: 分项 | B99: 013311000050001 | C99: 泌尿系取石费-上尿路（加收） | D99: 手术费 | G99: 次 | H99: 本项目中的“上尿路”指：肾脏及输尿管。 | I99: 1265 | J99: 1139 | K99: 1224.3925 | L99: 962.92683 | M99: 280 | N99: 1170 | O99: 1120 | P99: 950 | Q99: 医保 | U99: 加权平均后扣除主项拟定价格得到平移价格，根据项目间比价理顺项目价格。 | V99: 003311010160000-331101016 | W99: 331101016 | X99: 肾切开取石术 | Y99: 包括肾盂切开、肾实质切开 | AA99: 次 | AC99: 2880 | AD99: 2590 | AE99: 2530 | AF99: 2280 | AG99: 1940
V100: 003311010160000-33110101601 | W100: 33110101601 | X100: 小儿肾切开取石术 | AA100: 次 | AC100: 3745 | AD100: 3365 | AE100: 3290 | AF100: 2965 | AG100: 2520
...

Sheet 规范整合泌尿系统医疗服务价格映射表12.11 (2)
A1: 附件1
A2: 泌尿系统类立项指南项目价格拟定情况 | B2: 泌尿系统类立项指南项目价格拟定情况 | C2: 泌尿系统类立项指南项目价格拟定情况 | D2: 泌尿系统类立项指南项目价格拟定情况 | E2: 泌尿系统类立项指南项目价格拟定情况 | F2: 泌尿系统类立项指南项目价格拟定情况 | G2: 泌尿系统类立项指南项目价格拟定情况 | H2: 泌尿系统类立项指南项目价格拟定情况 | I2: 泌尿系统类立项指南项目价格拟定情况 | J2: 泌尿系统类立项指南项目价格拟定情况 | K2: 泌尿系统类立项指南项目价格拟定情况 | L2: 泌尿系统类立项指南项目价格拟定情况 | M2: 泌尿系统类立项指南项目价格拟定情况 | N2: 泌尿系统类立项指南项目价格拟定情况 | O2: 泌尿系统类立项指南项目价格拟定情况 | P2: 泌尿系统类立项指南项目价格拟定情况 | Q2: 泌尿系统类立项指南项目价格拟定情况 | R2: 泌尿系统类立项指南项目价格拟定情况 | S2: 泌尿系统类立项指南项目价格拟定情况 | T2: 泌尿系统类立项指南项目价格拟定情况 | U2: 泌尿系统类立项指南项目价格拟定情况 | V2: 泌尿系统类立项指南项目价格拟定情况 | W2: 泌尿系统类立项指南项目价格拟定情况 | X2: 泌尿系统类立项指南项目价格拟定情况 | Y2: 泌尿系统类立项指南项目价格拟定情况 | Z2: 泌尿系统类立项指南项目价格拟定情况 | AA2: 泌尿系统类立项指南项目价格拟定情况 | AB2: 泌尿系统类立项指南项目价格拟定情况 | AC2: 泌尿系统类立项指南项目价格拟定情况 | AD2: 泌尿系统类立项指南项目价格拟定情况 | AE2: 泌尿系统类立项指南项目价格拟定情况
A3: 泌尿系统类立项指南项目 | B3: 泌尿系统类立项指南项目 | C3: 泌尿系统类立项指南项目 | D3: 泌尿系统类立项指南项目 | E3: 泌尿系统类立项指南项目 | F3: 泌尿系统类立项指南项目 | G3: 泌尿系统类立项指南项目 | H3: 泌尿系统类立项指南项目 | I3: 泌尿系统类立项指南项目 | J3: 泌尿系统类立项指南项目 | K3: 泌尿系统类立项指南项目 | L3: 泌尿系统类立项指南项目 | M3: 泌尿系统类立项指南项目 | N3: 泌尿系统类立项指南项目 | O3: 泌尿系统类立项指南项目 | P3: 泌尿系统类立项指南项目 | Q3: 泌尿系统类立项指南项目 | R3: 泌尿系统类立项指南项目 | S3: 泌尿系统类立项指南项目 | T3: 现行价格项目 | U3: 现行价格项目 | V3: 现行价格项目 | W3: 现行价格项目 | X3: 现行价格项目 | Y3: 现行价格项目 | Z3: 现行价格项目 | AA3: 现行价格项目 | AB3: 现行价格项目 | AC3: 现行价格项目 | AD3: 现行价格项目 | AE3: 现行价格项目
A4: 序号 | B4: 项目代码 | C4: 项目名称 | D4: 归集口径 | E4: 服务产出 | F4: 价格构成 | G4: 计价单位 | H4: 计价说明 | I4: 省三甲价格 | J4: 省三甲以下价格 | K4: 平移价格 (市级) | L4: 平移价格 (县级) | M4: 平移价格 (基层) | N4: 拟定价格 (市级) | O4: 拟定价格 (县级) | P4: 拟定价格 (基层) | Q4: 医保属性 | R4: 调整情况 | S4: 备注 | T4: 国家结算编码 | U4: 项目编码 | V4: 项目名称 | W4: 项目内涵 | X4: 除外内容 | Y4: 计价单位 | Z4: 说明 | AA4: 三甲 | AB4: 三甲以下 | AC4: 价格 (市级) | AD4: 价格 (县级) | AE4: 价格 (基层)
A5: 1 | B5: 012411000010000 | C5: 肾盂内压检查费 | D5: 检查费 | E5: 通过各种方式测定肾盂内压，辅助判断肾盂输尿管连接部是否存在梗阻。 | F5: 所定价格涵盖放置导管、注射、观察记录、出具报告、处理用物等步骤所需的人力资源和基本物质资源消耗。 | G5: 次 | H5: “次”指双侧，单侧按50%收取。 | I5: 240 | J5: 216 | N5: 220 | O5: 200 | P5: 170 | Q5: 非医保 | R5: 新增价格 | S5: 新增价格，按比价关系拟定 | T5: 003110000140000-311000014 | U5: 311000014 | V5: 肾盂测压 | Y5: 单侧 | AF5: =IFERROR(FIND("（加收）",C5,1),0) -> 0 | AG5: =IF(AF5>0,LEFT(C5,IFERROR(FIND("-",C5,1),1)-1),C5) -> 肾盂内压检查费 | AH5: =IF(AF5>0,_xlfn.MAXIFS(N:N,C:C,AG5),0)+N5 -> 220 | AI5: =IF(AF5>0,_xlfn.MAXIFS(O:O,C:C,AG5),0)+O5 -> 200 | AJ5: =IF(AF5>0,_xlfn.MAXIFS(P:P,C:C,AG5),0)+P5 -> 170
A6: 2 | B6: 012411000020000 | C6: 尿流动力学检查费 | D6: 检查费 | E6: 通过各种方式对尿路功能状态进行评估，辅助诊断尿路功能障碍性疾病。 | F6: 所定价格涵盖检测尿流率与动力学、出具报告、处理用物等步骤所需的人力资源和基本物质资源消耗。 | G6: 次 | H6: 尿流率检测市级医院收取66元/次，县级医院收取59元/次，基层收取51元/次。 | I6: 165 | J6: 150 | K6: 165 | L6: 150 | M6: 127.5 | N6: 165 | O6: 150 | P6: 128 | Q6: 医保 | R6: 平移 | S6: 平移后，县级按不高于省级拟定，基层取整。同质化高的项目持平省级定价。 | T6: 003110000390000-311000039 | U6: 311000039 | V6: 尿流动力学检测 | W6: 不含摄片 | Y6: 次 | AA6: 165 | AB6: 150 | AC6: 165 | AD6: 150 | AE6: 127.5 | AF6: =IFERROR(FIND("（加收）",C6,1),0) -> 0 | AG6: =IF(AF6>0,LEFT(C6,IFERROR(FIND("-",C6,1),1)-1),C6) -> 尿流动力学检查费 | AH6: =IF(AF6>0,_xlfn.MAXIFS(N:N,C:C,AG6),0)+N6 -> 165 | AI6: =IF(AF6>0,_xlfn.MAXIFS(O:O,C:C,AG6),0)+O6 -> 150 | AJ6: =IF(AF6>0,_xlfn.MAXIFS(P:P,C:C,AG6),0)+P6 -> 128
A7: 2 | B7: 012411000020000 | C7: 尿流动力学检查费（尿流率检测） | K7: 66 | L7: 60 | M7: 51 | N7: 66 | O7: 59 | P7: 51 | Q7: 医保 | S7: 平移后，县级按不高于省级拟定，基层取整。同质化高的项目持平省级定价。 | T7: 003110000380000-311000038 | U7: 311000038 | V7: 尿流率检测 | Y7: 次 | AA7: 66 | AB7: 59 | AC7: 66 | AD7: 60 | AE7: 51 | AF7: =IFERROR(FIND("（加收）",C7,1),0) -> 0 | AG7: =IF(AF7>0,LEFT(C7,IFERROR(FIND("-",C7,1),1)-1),C7) -> 尿流动力学检查费（尿流率检测） | AH7: =IF(AF7>0,_xlfn.MAXIFS(N:N,C:C,AG7),0)+N7 -> 66 | AI7: =IF(AF7>0,_xlfn.MAXIFS(O:O,C:C,AG7),0)+O7 -> 59 | AJ7: =IF(AF7>0,_xlfn.MAXIFS(P:P,C:C,AG7),0)+P7 -> 51
A8: 3 | B8: 012411000030000 | C8: 泌尿系镜检查费（肾镜） | D8: 检查费 | E8: 通过肾镜观察和诊断泌尿系统疾病。 | F8: 所定价格涵盖消毒、插管、扩张通道、观察、出具报告、处理用物、必要时穿刺等步骤所需的人力资源和基本物质资源消耗。 | G8: 单侧 | I8: 660 | J8: 595 | K8: 660 | L8: 600 | M8: 510 | N8: 660 | O8: 595 | P8: 510 | Q8: 医保 | R8: 理顺 | S8: 平移后，县级按不高于省级拟定 | T8: 003110000180000-311000018 | U8: 311000018 | V8: 经皮肾盂镜检查 | W8: 含活检 | Y8: 单侧 | AA8: 660 | AB8: 595 | AC8: 660 | AD8: 600 | AE8: 510 | AF8: =IFERROR(FIND("（加收）",C8,1),0) -> 0 | AG8: =IF(AF8>0,LEFT(C8,IFERROR(FIND("-",C8,1),1)-1),C8) -> 泌尿系镜检查费（肾镜） | AH8: =IF(AF8>0,_xlfn.MAXIFS(N:N,C:C,AG8),0)+N8 -> 660 | AI8: =IF(AF8>0,_xlfn.MAXIFS(O:O,C:C,AG8),0)+O8 -> 595 | AJ8: =IF(AF8>0,_xlfn.MAXIFS(P:P,C:C,AG8),0)+P8 -> 510
A9: 4 | B9: 012411000040000 | C9: 泌尿系镜检查费（输尿管镜） | D9: 检查费 | E9: 通过输尿管镜观察和诊断泌尿系统疾病。 | F9: 所定价格涵盖消毒、插管、扩张通道、观察、出具报告、处理用物等步骤所需的人力资源和基本物质资源消耗。 | G9: 单侧 | I9: 499 | J9: 449 | K9: 495 | L9: 450 | M9: 382.5 | N9: 495 | O9: 445 | P9: 380 | Q9: 医保 | R9: 理顺，降低 | S9: 平移后，县级按不高于省级拟定，基层对应调整 | T9: 003110000200000-311000020 | U9: 311000020 | V9: 经尿道输尿管镜检查 | W9: 含活检；包括取异物 | Y9: 单侧 | AA9: 495 | AB9: 445 | AC9: 495 | AD9: 450 | AE9: 382.5 | AF9: =IFERROR(FIND("（加收）",C9,1),0) -> 0 | AG9: =IF(AF9>0,LEFT(C9,IFERROR(FIND("-",C9,1),1)-1),C9) -> 泌尿系镜检查费（输尿管镜） | AH9: =IF(AF9>0,_xlfn.MAXIFS(N:N,C:C,AG9),0)+N9 -> 495 | AI9: =IF(AF9>0,_xlfn.MAXIFS(O:O,C:C,AG9),0)+O9 -> 445 | AJ9: =IF(AF9>0,_xlfn.MAXIFS(P:P,C:C,AG9),0)+P9 -> 380
A10: 分项 | B10: 012411000040100 | C10: 泌尿系镜检查费（输尿管镜）-精囊镜检查（扩展） | D10: 检查费 | G10: 单侧 | I10: 499 | J10: 449 | K10: 720 | L10: 648 | M10: 550.8 | N10: 495 | O10: 445 | P10: 380 | Q10: 医保 | S10: 扩展项按主项价格执行 | T10: 353111000290000-311100020 | U10: 311100020 | V10: 经尿道精囊镜检查 | W10: 消毒，取Wolf4.5/6.5精囊镜连接电视成像系统，以生理盐水为灌注液，直视下将精囊镜经尿道置入膀胱，观察尿道、膀胱，将镜体退至精阜处，仔细观察射精管口，发现射精管口后稍加大灌注液速度，将镜体置入一侧射精管内，将镜体逐渐推进精囊内，观察射精管及精囊内情况，如有无结石、肿物及精囊液情况。含活检、斑马导丝。 | Y10: 侧 | AA10: 800 | AC10: 720 | AD10: 648 | AE10: 550.8 | AF10: =IFERROR(FIND("（加收）",C10,1),0) -> 0 | AG10: =IF(AF10>0,LEFT(C10,IFERROR(FIND("-",C10,1),1)-1),C10) -> 泌尿系镜检查费（输尿管镜）-精囊镜检查（扩展） | AH10: =IF(AF10>0,_xlfn.MAXIFS(N:N,C:C,AG10),0)+N10 -> 495 | AI10: =IF(AF10>0,_xlfn.MAXIFS(O:O,C:C,AG10),0)+O10 -> 445 | AJ10: =IF(AF10>0,_xlfn.MAXIFS(P:P,C:C,AG10),0)+P10 -> 380
A11: 5 | B11: 012411000050000 | C11: 泌尿系镜检查费（膀胱镜尿道镜） | D11: 检查费 | E11: 通过膀胱镜尿道镜观察和诊断泌尿系统疾病。 | F11: 所定价格涵盖消毒、插管、扩张通道、观察、出具报告、处理用物等步骤所需的人力资源和基本物质资源消耗。 | G11: 次 | I11: 132 | J11: 120 | K11: 132 | L11: 120 | M11: 102 | N11: 132 | O11: 120 | P11: 102 | Q11: 医保 | R11: 平移 | S11: 平移 | T11: 003110000340000-311000034 | U11: 311000034 | V11: 膀胱镜尿道镜检查 | W11: 含活检，包括取异物 | Y11: 次 | AA11: 132 | AB11: 120 | AC11: 132 | AD11: 120 | AE11: 102 | AF11: =IFERROR(FIND("（加收）",C11,1),0) -> 0 | AG11: =IF(AF11>0,LEFT(C11,IFERROR(FIND("-",C11,1),1)-1),C11) -> 泌尿系镜检查费（膀胱镜尿道镜） | AH11: =IF(AF11>0,_xlfn.MAXIFS(N:N,C:C,AG11),0)+N11 -> 132 | AI11: =IF(AF11>0,_xlfn.MAXIFS(O:O,C:C,AG11),0)+O11 -> 120 | AJ11: =IF(AF11>0,_xlfn.MAXIFS(P:P,C:C,AG11),0)+P11 -> 102
A12: 7 | B12: 012412000020000 | C12: 阴茎勃起检查费 | D12: 检查费 | E12: 对患者夜间或模拟夜间环境下勃起次数、持续时间、硬度分级等情况进行监测。 | F12: 所定价格涵盖消毒、设备准备、监测、读取结果、出具报告、处理用物等步骤所需的人力资源和基本物质资源消耗。 | G12: 次 | I12: 100 | J12: 90 | K12: 99 | L12: 89 | M12: 77 | N12: 99 | O12: 89 | P12: 77 | Q12: 非医保 | R12: 平移 | S12: 平移 | T12: 003111000030000-311100003 | U12: 311100003 | V12: 夜间阴茎胀大试验 | W12: 含硬度计法 | Y12: 次 | AA12: 100 | AB12: 90 | AC12: 99 | AD12: 89 | AE12: 77 | AF12: =IFERROR(FIND("（加收）",C12,1),0) -> 0 | AG12: =IF(AF12>0,LEFT(C12,IFERROR(FIND("-",C12,1),1)-1),C12) -> 阴茎勃起检查费 | AH12: =IF(AF12>0,_xlfn.MAXIFS(N:N,C:C,AG12),0)+N12 -> 99 | AI12: =IF(AF12>0,_xlfn.MAXIFS(O:O,C:C,AG12),0)+O12 -> 89 | AJ12: =IF(AF12>0,_xlfn.MAXIFS(P:P,C:C,AG12),0)+P12 -> 77
A13: 8 | B13: 012412000030000 | C13: 阴茎超声血流图检查费 | D13: 检查费 | E13: 对患者阴茎海绵体内血流情况进行检测。 | F13: 所定价格涵盖消毒、设备准备、检测、诊断、出具报告、处理用物等步骤所需的人力资源和基本物质资源消耗。 | G13: 次 | I13: 77 | J13: 69 | L13: 80 | N13: 77 | O13: 69 | P13: 60 | Q13: 非医保 | R13: 理顺，降低 | S13: 仅县级有工作量，平移后按不超过省级拟定，同质化高的项目持平省级定价。 | T13: 003111000040000-311100004 | U13: 311100004 | V13: 阴茎超声血流图检查 | Y13: 次 | AA13: 80 | AB13: 72 | AC13: 88 | AD13: 80 | AE13: 68 | AF13: =IFERROR(FIND("（加收）",C13,1),0) -> 0 | AG13: =IF(AF13>0,LEFT(C13,IFERROR(FIND("-",C13,1),1)-1),C13) -> 阴茎超声血流图检查费 | AH13: =IF(AF13>0,_xlfn.MAXIFS(N:N,C:C,AG13),0)+N13 -> 77 | AI13: =IF(AF13>0,_xlfn.MAXIFS(O:O,C:C,AG13),0)+O13 -> 69 | AJ13: =IF(AF13>0,_xlfn.MAXIFS(P:P,C:C,AG13),0)+P13 -> 60
A14: 8 | B14: 012412000030000 | C14: 阴茎超声血流图检查费 | D14: 检查费 | E14: 对患者阴茎海绵体内血流情况进行检测。 | F14: 所定价格涵盖消毒、设备准备、检测、诊断、出具报告、处理用物等步骤所需的人力资源和基本物质资源消耗。 | G14: 次 | I14: 77 | J14: 69 | L14: 80 | N14: 77 | O14: 69 | P14: 60 | Q14: 非医保 | R14: 理顺，降低 | S14: 仅县级有工作量，平移后按不超过省级拟定，同质化高的项目持平省级定价。 | T14: 003111000110000-311100011 | U14: 311100011 | V14: 阴茎动脉测压术 | Y14: 次 | AA14: 44 | AB14: 40 | AC14: 44 | AD14: 40 | AE14: 34 | AF14: =IFERROR(FIND("（加收）",C14,1),0) -> 0 | AG14: =IF(AF14>0,LEFT(C14,IFERROR(FIND("-",C14,1),1)-1),C14) -> 阴茎超声血流图检查费 | AH14: =IF(AF14>0,_xlfn.MAXIFS(N:N,C:C,AG14),0)+N14 -> 77 | AI14: =IF(AF14>0,_xlfn.MAXIFS(O:O,C:C,AG14),0)+O14 -> 69 | AJ14: =IF(AF14>0,_xlfn.MAXIFS(P:P,C:C,AG14),0)+P14 -> 60
A15: 9 | B15: 012412000040000 | C15: 阴茎勃起神经检查费 | D15: 检查费 | E15: 通过各种方式对患者勃起相关神经进行检测。 | F15: 所定价格涵盖消毒、设备准备、检测、读取结果、出具报告、处理用物等步骤所需的人力资源和基本物质资源消耗。 | G15: 次 | I15: 110 | J15: 99 | K15: 110 | L15: 100 | M15: 85 | N15: 110 | O15: 99 | P15: 85 | Q15: 非医保 | R15: 理顺 | S15: 平移后，县级按不高于省级拟定，同质化高的项目持平省级定价。 | T15: 003111000050000-311100005 | U15: 311100005 | V15: 阴茎勃起神经检查 | W15: 含肌电图检查 | Y15: 次 | AA15: 110 | AB15: 99 | AC15: 110 | AD15: 100 | AE15: 85 | AF15: =IFERROR(FIND("（加收）",C15,1),0) -> 0 | AG15: =IF(AF15>0,LEFT(C15,IFERROR(FIND("-",C15,1),1)-1),C15) -> 阴茎勃起神经检查费 | AH15: =IF(AF15>0,_xlfn.MAXIFS(N:N,C:C,AG15),0)+N15 -> 110 | AI15: =IF(AF15>0,_xlfn.MAXIFS(O:O,C:C,AG15),0)+O15 -> 99 | AJ15: =IF(AF15>0,_xlfn.MAXIFS(P:P,C:C,AG15),0)+P15 -> 85
A16: 10 | B16: 013110000010000 | C16: 血液透析费 | D16: 治疗费 | E16: 通过弥散和对流原理清除血液中过多水分和有害物质。 | F16: 所定价格涵盖消毒、穿刺、安装设定、连接管路、监测、血液回输、加压止血、封管、处理用物等步骤所需的人力资源和基本物质资源消耗。 | G16: 次 | H16: 本项目中的“监测”指：血温、血压、在线清除率、血容量监测，医院未完成全部四项监测事项的，每少完成一项监测减收5元。 | I16: 398 | J16: 398 | K16: 385 | L16: 370 | M16: 340 | N16: 385 | O16: 370 | P16: 340 | Q16: 医保 | R16: 已落地，直接平移 | S16: 2025年7月15日已落地执行 | T16: 013110000010000 | U16: 013110000010000 | V16: 血液透析费 | W16: 通过弥散和对流原理清除血液中过多水分和有害物质。 | Y16: 次 | Z16: 本项目中的“监测”指：血温、血压、在线清除率、血容量监测，医院未完成全部四项监测事项的，每少完成一项监测减收5元。 | AA16: 398 | AB16: 398 | AC16: 385 | AD16: 370 | AE16: 340 | AF16: =IFERROR(FIND("（加收）",C16,1),0) -> 0 | AG16: =IF(AF16>0,LEFT(C16,IFERROR(FIND("-",C16,1),1)-1),C16) -> 血液透析费 | AH16: =IF(AF16>0,_xlfn.MAXIFS(N:N,C:C,AG16),0)+N16 -> 385 | AI16: =IF(AF16>0,_xlfn.MAXIFS(O:O,C:C,AG16),0)+O16 -> 370 | AJ16: =IF(AF16>0,_xlfn.MAXIFS(P:P,C:C,AG16),0)+P16 -> 340
A17: 11 | B17: 013110000020000 | C17: 血液滤过费 | D17: 治疗费 | E17: 通过对流原理清除血液中过多水分和有害物质。 | F17: 所定价格涵盖消毒、穿刺、建立通路、抗凝处理、连接管路、补充置换液、清除毒素及水分、监测、封管、处理用物等步骤所需的人力资源和基本物质资源消耗。 | G17: 次 | H17: 本项目中的“监测”指：血温、血压、在线清除率、血容量监测，医院未完成全部四项监测事项的，每少完成一项监测减收5元。 | I17: 398 | J17: 398 | K17: 395 | L17: 390 | M17: 355 | N17: 395 | O17: 390 | P17: 355 | Q17: 医保 | R17: 已落地，直接平移 | S17: 2025年7月15日已落地执行 | T17: 013110000020000 | U17: 013110000020000 | V17: 血液滤过费 | W17: 通过对流原理清除血液中过多水分和有害物质。 | Y17: 次 | Z17: 本项目中的“监测”指：血温、血压、在线清除率、血容量监测，医院未完成全部四项监测事项的，每少完成一项监测减收5元。 | AA17: 398 | AB17: 398 | AC17: 395 | AD17: 390 | AE17: 355 | AF17: =IFERROR(FIND("（加收）",C17,1),0) -> 0 | AG17: =IF(AF17>0,LEFT(C17,IFERROR(FIND("-",C17,1),1)-1),C17) -> 血液滤过费 | AH17: =IF(AF17>0,_xlfn.MAXIFS(N:N,C:C,AG17),0)+N17 -> 395 | AI17: =IF(AF17>0,_xlfn.MAXIFS(O:O,C:C,AG17),0)+O17 -> 390 | AJ17: =IF(AF17>0,_xlfn.MAXIFS(P:P,C:C,AG17),0)+P17 -> 355
A18: 12 | B18: 013110000030000 | C18: 血液透析滤过费 | D18: 治疗费 | E18: 通过同时进行血液透析和血液滤过清除血液中过多水分和有害物质。 | F18: 所定价格涵盖消毒、穿刺、建立通路、连接管路、参数设置、清除毒素及水分滤过、监测、封管、处理用物等步骤所需的人力资源和基本物质资源消耗。 | G18: 次 | H18: 本项目中的“监测”指：血温、血压、在线清除率、血容量监测，医院未完成全部四项监测事项的，每少完成一项监测减收5元。 | I18: 598 | J18: 598 | K18: 590 | L18: 575 | M18: 510 | N18: 590 | O18: 575 | P18: 510 | Q18: 医保 | R18: 已落地，直接平移 | S18: 2025年7月15日已落地执行 | T18: 013110000030000 | U18: 013110000030000 | V18: 血液透析滤过费 | W18: 通过同时进行血液透析和血液滤过清除血液中过多水分和有害物质。 | Y18: 次 | Z18: 本项目中的“监测”指：血温、血压、在线清除率、血容量监测，医院未完成全部四项监测事项的，每少完成一项监测减收5元。 | AA18: 598 | AB18: 598 | AC18: 590 | AD18: 575 | AE18: 510 | AF18: =IFERROR(FIND("（加收）",C18,1),0) -> 0 | AG18: =IF(AF18>0,LEFT(C18,IFERROR(FIND("-",C18,1),1)-1),C18) -> 血液透析滤过费 | AH18: =IF(AF18>0,_xlfn.MAXIFS(N:N,C:C,AG18),0)+N18 -> 590 | AI18: =IF(AF18>0,_xlfn.MAXIFS(O:O,C:C,AG18),0)+O18 -> 575 | AJ18: =IF(AF18>0,_xlfn.MAXIFS(P:P,C:C,AG18),0)+P18 -> 510
A19: 13 | B19: 013110000040000 | C19: 血液灌流费 | D19: 治疗费 | E19: 通过吸附原理‌直接结合血液中的中大分子及蛋白结合毒素。 | F19: 所定价格涵盖消毒、穿刺、建立通路、连接管路、参数设置、血液灌流、回输、封管、处理用物等步骤所需的人力资源和基本物质资源消耗。 | G19: 次 | I19: 300 | J19: 300 | K19: 275 | L19: 260 | M19: 250 | N19: 275 | O19: 260 | P19: 250 | R19: 已落地，直接平移 | S19: 2025年7月15日已落地执行 | T19: 013110000040000 | U19: 013110000040000 | V19: 血液灌流费 | W19: 通过吸附原理‌直接结合血液中的中大分子及蛋白结合毒素。 | Y19: 次 | AA19: 300 | AB19: 300 | AC19: 275 | AD19: 260 | AE19: 250 | AF19: =IFERROR(FIND("（加收）",C19,1),0) -> 0 | AG19: =IF(AF19>0,LEFT(C19,IFERROR(FIND("-",C19,1),1)-1),C19) -> 血液灌流费 | AH19: =IF(AF19>0,_xlfn.MAXIFS(N:N,C:C,AG19),0)+N19 -> 275 | AI19: =IF(AF19>0,_xlfn.MAXIFS(O:O,C:C,AG19),0)+O19 -> 260 | AJ19: =IF(AF19>0,_xlfn.MAXIFS(P:P,C:C,AG19),0)+P19 -> 250
A20: 14 | B20: 013110000050000 | C20: 血液透析灌流费 | D20: 治疗费 | E20: 通过同时进行血液透析和血液灌流清除血液中过多水分和有害物质。 | F20: 所定价格涵盖消毒、穿刺、建立通路、连接管路、参数设置、透析灌流、监测、封管、处理用物等步骤所需的人力资源和基本物质资源消耗。 | G20: 次 | H20: 本项目中的“监测”指：血温、血压、在线清除率、血容量监测，医院未完成全部四项监测事项的，每少完成一项监测减收5元。 | I20: 620 | J20: 620 | K20: 520 | L20: 520 | M20: 440 | N20: 520 | O20: 520 | P20: 440 | Q20: 医保 | R20: 已落地，直接平移 | S20: 2025年7月15日已落地执行 | T20: 013110000050000 | U20: 013110000050000 | V20: 血液透析灌流费 | W20: 通过同时进行血液透析和血液灌流清除血液中过多水分和有害物质。 | Y20: 次 | Z20: 本项目中的“监测”指：血温、血压、在线清除率、血容量监测，医院未完成全部四项监测事项的，每少完成一项监测减收5元。 | AA20: 620 | AB20: 620 | AC20: 520 | AD20: 520 | AE20: 440 | AF20: =IFERROR(FIND("（加收）",C20,1),0) -> 0 | AG20: =IF(AF20>0,LEFT(C20,IFERROR(FIND("-",C20,1),1)-1),C20) -> 血液透析灌流费 | AH20: =IF(AF20>0,_xlfn.MAXIFS(N:N,C:C,AG20),0)+N20 -> 520 | AI20: =IF(AF20>0,_xlfn.MAXIFS(O:O,C:C,AG20),0)+O20 -> 520 | AJ20: =IF(AF20>0,_xlfn.MAXIFS(P:P,C:C,AG20),0)+P20 -> 440
A21: 15 | B21: 013110000060000 | C21: 血浆置换费 | D21: 治疗费 | E21: 分离血浆、用置换液置换含有有害物质的血浆。 | F21: 所定价格涵盖消毒、穿刺、连接管路、血浆分离置换、回输、去除装置、处理用物等步骤所需的人力资源和基本物质资源消耗。 | G21: 次 | H21: 血浆置换费使用的滤器、血浆分离器、管路按零差率销售价格另行收取相应费用。 | I21: 800 | J21: 720 | N21: 750 | O21: 700 | P21: 595 | Q21: 医保 | R21: 理顺 | S21: 2025年7月15日已落地执行，现将耗材剥离，重新制定价格。 血浆分离器、分离管路全市采购均价分别为2178元、1425元，耗材成本超过项目本身价格。 | T21: 003109050230000-310905023 | U21: 310905023 | V21: 人工肝治疗 | X21: 一次性导管 | Y21: 次 | AA21: 1600 | AB21: 1440 | AC21: 1500 | AD21: 1350 | AE21: 1145 | AF21: =IFERROR(FIND("（加收）",C21,1),0) -> 0 | AG21: =IF(AF21>0,LEFT(C21,IFERROR(FIND("-",C21,1),1)-1),C21) -> 血浆置换费 | AH21: =IF(AF21>0,_xlfn.MAXIFS(N:N,C:C,AG21),0)+N21 -> 750 | AI21: =IF(AF21>0,_xlfn.MAXIFS(O:O,C:C,AG21),0)+O21 -> 700 | AJ21: =IF(AF21>0,_xlfn.MAXIFS(P:P,C:C,AG21),0)+P21 -> 595
A22: 15 | B22: 013110000060000 | C22: 血浆置换费 | D22: 治疗费 | E22: 分离血浆、用置换液置换含有有害物质的血浆。 | F22: 所定价格涵盖消毒、穿刺、连接管路、血浆分离置换、回输、去除装置、处理用物等步骤所需的人力资源和基本物质资源消耗。 | G22: 次 | H22: 血浆置换费使用的滤器、血浆分离器、管路按零差率销售价格另行收取相应费用。 | I22: 800 | J22: 720 | N22: 750 | O22: 700 | P22: 595 | Q22: 医保 | R22: 理顺 | S22: 2025年7月15日已落地执行，现将耗材剥离，重新制定价格。 血浆分离器、分离管路全市采购均价分别为2178元、1425元，耗材成本超过项目本身价格。 | T22: 013110000060000 | U22: 013110000060000 | V22: 血浆置换费 | W22: 分离血浆、用置换液置换含有有害物质的血浆。 | AA22: 2600 | AB22: 2340 | AC22: 2450 | AD22: 2325 | AE22: 2000 | AF22: =IFERROR(FIND("（加收）",C22,1),0) -> 0 | AG22: =IF(AF22>0,LEFT(C22,IFERROR(FIND("-",C22,1),1)-1),C22) -> 血浆置换费 | AH22: =IF(AF22>0,_xlfn.MAXIFS(N:N,C:C,AG22),0)+N22 -> 750 | AI22: =IF(AF22>0,_xlfn.MAXIFS(O:O,C:C,AG22),0)+O22 -> 700 | AJ22: =IF(AF22>0,_xlfn.MAXIFS(P:P,C:C,AG22),0)+P22 -> 595
A23: 17 | B23: 013110000080000 | C23: 连续性肾脏替代治疗费 | D23: 治疗费 | E23: 通过血液净化实现连续肾脏替代治疗和多脏器功能衰竭的生命支持治疗。 | F23: 所定价格涵盖消毒、穿刺、连接管路、上机、血液净化、体外抗凝、回输、去除装置、处理用物等步骤所需的人力资源和基本物质资源消耗。 | G23: 小时 | H23: 连续性肾脏替代治疗使用的滤器、管路按零差率销售价格另行收取相应费用。 | I23: 96 | J23: 96 | K23: 95 | L23: 95 | M23: 86 | N23: 95 | O23: 95 | P23: 86 | Q23: 医保 | R23: 已落地，直接平移 | S23: 新家 | T23: 013110000080000 | U23: 013110000080000 | V23: 连续性肾脏替代治疗费 | Y23: 小时 | AA23: 96 | AB23: 96 | AC23: 95 | AD23: 95 | AE23: 86 | AF23: =IFERROR(FIND("（加收）",C23,1),0) -> 0 | AG23: =IF(AF23>0,LEFT(C23,IFERROR(FIND("-",C23,1),1)-1),C23) -> 连续性肾脏替代治疗费 | AH23: =IF(AF23>0,_xlfn.MAXIFS(N:N,C:C,AG23),0)+N23 -> 95 | AI23: =IF(AF23>0,_xlfn.MAXIFS(O:O,C:C,AG23),0)+O23 -> 95 | AJ23: =IF(AF23>0,_xlfn.MAXIFS(P:P,C:C,AG23),0)+P23 -> 86
A24: 分项 | B24: 013110000080001 | C24: 连续性肾脏替代治疗费-连续性血浆吸附滤过治疗（加收） | D24: 治疗费 | G24: 小时 | I24: 30 | J24: 30 | K24: 28 | L24: 28 | M24: 25 | N24: 28 | O24: 28 | P24: 25 | Q24: 医保 | S24: 2025年7月15日已落地执行 | T24: 013110000080001 | U24: 013110000080001 | V24: 连续性肾脏替代治疗费-连续性血浆吸附滤过治疗（加收） | Y24: 小时 | AA24: 30 | AB24: 30 | AC24: 28 | AD24: 28 | AE24: 25 | AF24: =IFERROR(FIND("（加收）",C24,1),0) -> 23 | AG24: =IF(AF24>0,LEFT(C24,IFERROR(FIND("-",C24,1),1)-1),C24) -> 连续性肾脏替代治疗费 | AH24: =IF(AF24>0,_xlfn.MAXIFS(N:N,C:C,AG24),0)+N24 -> 123 | AI24: =IF(AF24>0,_xlfn.MAXIFS(O:O,C:C,AG24),0)+O24 -> 123 | AJ24: =IF(AF24>0,_xlfn.MAXIFS(P:P,C:C,AG24),0)+P24 -> 111
A25: 23 | B25: 013110000140000 | C25: 腹膜透析外管更换费 | D25: 治疗费 | E25: 通过各种方式更换腹膜透析外接短管。 | F25: 所定价格涵盖消毒、更换管路、封管、处理用物等步骤所需的人力资源和基本物质资源消耗。 | G25: 次 | I25: 45 | J25: 41 | K25: 40 | L25: 40 | M25: 34 | N25: 42 | O25: 40 | P25: 34 | Q25: 医保 | R25: 理顺 | S25: 2025年7月15日已在“腹膜透析换管费”说明中落地执行，此次调整市级理顺比价 | T25: 013311000020000 | U25: 013311000020000 | V25: 腹膜透析换管费（更换外管） | Y25: 次 | AF25: =IFERROR(FIND("（加收）",C25,1),0) -> 0 | AG25: =IF(AF25>0,LEFT(C25,IFERROR(FIND("-",C25,1),1)-1),C25) -> 腹膜透析外管更换费 | AH25: =IF(AF25>0,_xlfn.MAXIFS(N:N,C:C,AG25),0)+N25 -> 42 | AI25: =IF(AF25>0,_xlfn.MAXIFS(O:O,C:C,AG25),0)+O25 -> 40 | AJ25: =IF(AF25>0,_xlfn.MAXIFS(P:P,C:C,AG25),0)+P25 -> 34
A26: 24 | B26: 013110000150000 | C26: 腹膜平衡试验费 | D26: 治疗费 | E26: 对腹膜功能进行检测，调整腹膜透析方案。 | F26: 所定价格涵盖腹透换液、留取标本、测量、计算、出具方案、处理用物等步骤所需的人力资源和基本物质资源消耗。 | G26: 次 | I26: 45 | J26: 41 | K26: 40 | L26: 40 | M26: 34 | N26: 42 | O26: 40 | P26: 34 | Q26: 医保 | R26: 理顺 | S26: 2025年7月15日已落地执行，此次调整市级理顺比价 | T26: 013110000150000 | U26: 013110000150000 | V26: 腹膜平衡试验费 | W26: 对腹膜功能进行检测，调整腹膜透析方案。 | Y26: 次 | AA26: 45 | AB26: 41 | AC26: 40 | AD26: 40 | AE26: 34 | AF26: =IFERROR(FIND("（加收）",C26,1),0) -> 0 | AG26: =IF(AF26>0,LEFT(C26,IFERROR(FIND("-",C26,1),1)-1),C26) -> 腹膜平衡试验费 | AH26: =IF(AF26>0,_xlfn.MAXIFS(N:N,C:C,AG26),0)+N26 -> 42 | AI26: =IF(AF26>0,_xlfn.MAXIFS(O:O,C:C,AG26),0)+O26 -> 40 | AJ26: =IF(AF26>0,_xlfn.MAXIFS(P:P,C:C,AG26),0)+P26 -> 34
A27: 25 | B27: 013311000010000 | C27: 腹膜透析置管费 | D27: 手术费 | E27: 通过各种方式放置腹膜透析导管。 | F27: 所定价格涵盖消毒、切开、穿刺或分离、置管、试水通畅、缝合、处理用物等步骤所需的人力资源和基本物质资源消耗。 | G27: 次 | I27: 440 | J27: 395 | K27: 400 | L27: 400 | M27: 340 | N27: 420 | O27: 395 | P27: 340 | Q27: 医保 | R27: 理顺 | S27: 2025年7月15日已落地执行，现微调市级、县级价格以理顺比价 | T27: 013311000010000 | U27: 013311000010000 | V27: 腹膜透析置管费 | W27: 通过各种方式放置腹膜透析导管。 | Y27: 次 | AA27: 440 | AB27: 395 | AC27: 400 | AD27: 400 | AE27: 340 | AF27: =IFERROR(FIND("（加收）",C27,1),0) -> 0 | AG27: =IF(AF27>0,LEFT(C27,IFERROR(FIND("-",C27,1),1)-1),C27) -> 腹膜透析置管费 | AH27: =IF(AF27>0,_xlfn.MAXIFS(N:N,C:C,AG27),0)+N27 -> 420 | AI27: =IF(AF27>0,_xlfn.MAXIFS(O:O,C:C,AG27),0)+O27 -> 395 | AJ27: =IF(AF27>0,_xlfn.MAXIFS(P:P,C:C,AG27),0)+P27 -> 340
A28: 26 | B28: 013311000020000 | C28: 腹膜透析换管费 | D28: 手术费 | E28: 更换破损、堵塞、移位的腹膜透析导管。 | F28: 所定价格涵盖消毒、切开、拔除旧管、原位置入新管、试水通畅、缝合、处理用物等步骤所需的人力资源和基本物质资源消耗。 | G28: 次 | H28: 不与“腹膜透析置管费”“腹膜透析导管取出费”“腹膜透析导管感染清创费”同时收取。 | I28: 440 | J28: 395 | K28: 420 | L28: 420 | M28: 360 | N28: 420 | O28: 395 | P28: 340 | Q28: 医保 | R28: 理顺 | S28: 2025年7月15日已落地执行，现调整说明，更换外管独立设立项目 微调价格理顺比价 | T28: 013311000020000 | U28: 013311000020000 | V28: 腹膜透析换管费 | W28: 更换破损、堵塞、移位的腹膜透析导管。 | Y28: 次 | Z28: 不与“腹膜透析置管费”“腹膜透析导管取出费”“腹膜透析导管感染清创费”同时收取。更换外管市、县级按40元收取，基层按34元收取。 | AA28: 440 | AB28: 395 | AC28: 420 | AD28: 420 | AE28: 360 | AF28: =IFERROR(FIND("（加收）",C28,1),0) -> 0 | AG28: =IF(AF28>0,LEFT(C28,IFERROR(FIND("-",C28,1),1)-1),C28) -> 腹膜透析换管费 | AH28: =IF(AF28>0,_xlfn.MAXIFS(N:N,C:C,AG28),0)+N28 -> 420 | AI28: =IF(AF28>0,_xlfn.MAXIFS(O:O,C:C,AG28),0)+O28 -> 395 | AJ28: =IF(AF28>0,_xlfn.MAXIFS(P:P,C:C,AG28),0)+P28 -> 340
A29: 31 | B29: 013110000190000 | C29: 体外冲击波碎石费 | D29: 治疗费 | E29: 通过冲击波聚焦能量，裂解尿路结石，便于结石排出。 | F29: 所定价格涵盖体位摆放、机器校准、能量释放、结石裂解、排出体外等步骤所需的人力资源和基本物质资源消耗。 | G29: 次 | H29: 第二次碎石市级医院收取350元/次，县级医院收取315元/次，基层收取268元/次；第三次碎石市级医院收取175元/次，县级医院收取158元/次，基层收取134元/次；第四次起不收费。 | I29: 700 | J29: 630 | K29: 700 | L29: 630 | M29: 535.5 | N29: 700 | O29: 630 | P29: 535 | Q29: 医保 | R29: 平移 | S29: 平移，取整 | T29: 003110000400000-311000040 | U29: 311000040 | V29: 体外冲击波碎石 | W29: 含影像学监测,不含摄片 | Y29: 次 | Z29: 第二次碎石按全价50%计价，第三次按25%计价，第四次起不收费。 | AA29: 700 | AB29: 630 | AC29: 700 | AD29: 630 | AE29: 535.5 | AF29: =IFERROR(FIND("（加收）",C29,1),0) -> 0 | AG29: =IF(AF29>0,LEFT(C29,IFERROR(FIND("-",C29,1),1)-1),C29) -> 体外冲击波碎石费 | AH29: =IF(AF29>0,_xlfn.MAXIFS(N:N,C:C,AG29),0)+N29 -> 700 | AI29: =IF(AF29>0,_xlfn.MAXIFS(O:O,C:C,AG29),0)+O29 -> 630 | AJ29: =IF(AF29>0,_xlfn.MAXIFS(P:P,C:C,AG29),0)+P29 -> 535
A30: 31 | B30: 013110000190000 | C30: 体外冲击波碎石费（第二次） | D30: 治疗费 | G30: 次 | I30: 350 | J30: 315 | K30: 350 | L30: 315 | M30: 267.75 | N30: 350 | O30: 315 | P30: 268 | S30: 平移，取整 | T30: 003110000400000-31100004003 | U30: 31100004003 | V30: 体外冲击波碎石（第二次） | Y30: 次 | Z30: 第二次 | AA30: 350 | AB30: 315 | AC30: 350 | AD30: 315 | AE30: 267.8 | AF30: =IFERROR(FIND("（加收）",C30,1),0) -> 0 | AG30: =IF(AF30>0,LEFT(C30,IFERROR(FIND("-",C30,1),1)-1),C30) -> 体外冲击波碎石费（第二次） | AH30: =IF(AF30>0,_xlfn.MAXIFS(N:N,C:C,AG30),0)+N30 -> 350 | AI30: =IF(AF30>0,_xlfn.MAXIFS(O:O,C:C,AG30),0)+O30 -> 315 | AJ30: =IF(AF30>0,_xlfn.MAXIFS(P:P,C:C,AG30),0)+P30 -> 268
A31: 31 | B31: 013110000190000 | C31: 体外冲击波碎石费（第三次） | D31: 治疗费 | G31: 次 | I31: 175 | J31: 158 | K31: 175 | L31: 157.5 | M31: 133.875 | N31: 175 | O31: 158 | P31: 134 | S31: 平移，取整 | T31: 003110000400000-31100004006 | U31: 31100004006 | V31: 体外冲击波碎石（第三次） | Y31: 次 | Z31: 第三次 | AA31: 175 | AB31: 158 | AC31: 175 | AD31: 157.5 | AE31: 133.9 | AF31: =IFERROR(FIND("（加收）",C31,1),0) -> 0 | AG31: =IF(AF31>0,LEFT(C31,IFERROR(FIND("-",C31,1),1)-1),C31) -> 体外冲击波碎石费（第三次） | AH31: =IF(AF31>0,_xlfn.MAXIFS(N:N,C:C,AG31),0)+N31 -> 175 | AI31: =IF(AF31>0,_xlfn.MAXIFS(O:O,C:C,AG31),0)+O31 -> 158 | AJ31: =IF(AF31>0,_xlfn.MAXIFS(P:P,C:C,AG31),0)+P31 -> 134
A32: 32 | B32: 013110000200000 | C32: 泌尿系镜下治疗费（常规） | D32: 治疗费 | E32: 通过置物、取物等方式对泌尿系统及男性生殖系统病灶进行治疗。 | F32: 所定价格涵盖消毒、下镜、治疗、撤镜等步骤所需的人力资源和基本物质资源消耗。（不含泌尿系镜下检查） | G32: 次 | H32: 同时行常规治疗和特殊治疗的，按照“泌尿系镜下治疗费（特殊）”收取。 | I32: 825 | J32: 743 | K32: 817.32836 | L32: 741.1044 | M32: 640.94595 | N32: 815 | O32: 740 | P32: 640 | Q32: 医保 | R32: 平移取整 | S32: 加权平移取整 | T32: 003110000190200-31100001901 | U32: 31100001901 | V32: 经皮肾盂镜取石术（取异物） | Y32: 次 | Z32: 取异物 | AA32: 880 | AB32: 790 | AC32: 880 | AD32: 800 | AE32: 680 | AF32: =IFERROR(FIND("（加收）",C32,1),0) -> 0 | AG32: =IF(AF32>0,LEFT(C32,IFERROR(FIND("-",C32,1),1)-1),C32) -> 泌尿系镜下治疗费（常规） | AH32: =IF(AF32>0,_xlfn.MAXIFS(N:N,C:C,AG32),0)+N32 -> 815 | AI32: =IF(AF32>0,_xlfn.MAXIFS(O:O,C:C,AG32),0)+O32 -> 740 | AJ32: =IF(AF32>0,_xlfn.MAXIFS(P:P,C:C,AG32),0)+P32 -> 640
A33: 32 | B33: 013110000200000 | C33: 泌尿系镜下治疗费（常规） | D33: 治疗费 | E33: 通过置物、取物等方式对泌尿系统及男性生殖系统病灶进行治疗。 | F33: 所定价格涵盖消毒、下镜、治疗、撤镜等步骤所需的人力资源和基本物质资源消耗。（不含泌尿系镜下检查） | G33: 次 | H33: 同时行常规治疗和特殊治疗的，按照“泌尿系镜下治疗费（特殊）”收取。 | I33: 825 | J33: 743 | K33: 817.32836 | L33: 741.1044 | M33: 640.94595 | N33: 815 | O33: 740 | P33: 640 | Q33: 医保 | R33: 平移取整 | S33: 加权平移取整 | T33: 003311030270000-331103027 | U33: 331103027 | V33: 经尿道膀胱碎石取石术 | W33: 包括血块、异物取出 | Y33: 次 | AA33: 1250 | AB33: 1125 | AC33: 1250 | AD33: 1200 | AE33: 1020 | AF33: =IFERROR(FIND("（加收）",C33,1),0) -> 0 | AG33: =IF(AF33>0,LEFT(C33,IFERROR(FIND("-",C33,1),1)-1),C33) -> 泌尿系镜下治疗费（常规） | AH33: =IF(AF33>0,_xlfn.MAXIFS(N:N,C:C,AG33),0)+N33 -> 815 | AI33: =IF(AF33>0,_xlfn.MAXIFS(O:O,C:C,AG33),0)+O33 -> 740 | AJ33: =IF(AF33>0,_xlfn.MAXIFS(P:P,C:C,AG33),0)+P33 -> 640
A34: 32 | B34: 013110000200000 | C34: 泌尿系镜下治疗费（常规） | D34: 治疗费 | E34: 通过置物、取物等方式对泌尿系统及男性生殖系统病灶进行治疗。 | F34: 所定价格涵盖消毒、下镜、治疗、撤镜等步骤所需的人力资源和基本物质资源消耗。（不含泌尿系镜下检查） | G34: 次 | H34: 同时行常规治疗和特殊治疗的，按照“泌尿系镜下治疗费（特殊）”收取。 | I34: 825 | J34: 743 | K34: 817.32836 | L34: 741.1044 | M34: 640.94595 | N34: 815 | O34: 740 | P34: 640 | Q34: 医保 | R34: 平移取整 | S34: 加权平移取整 | T34: 003311030270000-33110302701 | U34: 33110302701 | V34: 小儿经尿道膀胱碎石取石术 | Y34: 次 | AA34: 1625 | AB34: 1465 | AC34: 1625 | AD34: 1560 | AE34: 1325 | AF34: =IFERROR(FIND("（加收）",C34,1),0) -> 0 | AG34: =IF(AF34>0,LEFT(C34,IFERROR(FIND("-",C34,1),1)-1),C34) -> 泌尿系镜下治疗费（常规） | AH34: =IF(AF34>0,_xlfn.MAXIFS(N:N,C:C,AG34),0)+N34 -> 815 | AI34: =IF(AF34>0,_xlfn.MAXIFS(O:O,C:C,AG34),0)+O34 -> 740 | AJ34: =IF(AF34>0,_xlfn.MAXIFS(P:P,C:C,AG34),0)+P34 -> 640
A35: 32 | B35: 013110000200000 | C35: 泌尿系镜下治疗费（常规） | D35: 治疗费 | E35: 通过置物、取物等方式对泌尿系统及男性生殖系统病灶进行治疗。 | F35: 所定价格涵盖消毒、下镜、治疗、撤镜等步骤所需的人力资源和基本物质资源消耗。（不含泌尿系镜下检查） | G35: 次 | H35: 同时行常规治疗和特殊治疗的，按照“泌尿系镜下治疗费（特殊）”收取。 | I35: 825 | J35: 743 | K35: 817.32836 | L35: 741.1044 | M35: 640.94595 | N35: 815 | O35: 740 | P35: 640 | Q35: 医保 | R35: 平移取整 | S35: 加权平移取整 | T35: 003110000200000-311000020 | U35: 311000020 | V35: 经尿道输尿管镜检查 | W35: 含活检；包括取异物 | Y35: 单侧 | AA35: 495 | AB35: 445 | AC35: 495 | AD35: 450 | AE35: 382.5 | AF35: =IFERROR(FIND("（加收）",C35,1),0) -> 0 | AG35: =IF(AF35>0,LEFT(C35,IFERROR(FIND("-",C35,1),1)-1),C35) -> 泌尿系镜下治疗费（常规） | AH35: =IF(AF35>0,_xlfn.MAXIFS(N:N,C:C,AG35),0)+N35 -> 815 | AI35: =IF(AF35>0,_xlfn.MAXIFS(O:O,C:C,AG35),0)+O35 -> 740 | AJ35: =IF(AF35>0,_xlfn.MAXIFS(P:P,C:C,AG35),0)+P35 -> 640
A36: 32 | B36: 013110000200000 | C36: 泌尿系镜下治疗费（常规） | D36: 治疗费 | E36: 通过置物、取物等方式对泌尿系统及男性生殖系统病灶进行治疗。 | F36: 所定价格涵盖消毒、下镜、治疗、撤镜等步骤所需的人力资源和基本物质资源消耗。（不含泌尿系镜下检查） | G36: 次 | H36: 同时行常规治疗和特殊治疗的，按照“泌尿系镜下治疗费（特殊）”收取。 | I36: 825 | J36: 743 | K36: 817.32836 | L36: 741.1044 | M36: 640.94595 | N36: 815 | O36: 740 | P36: 640 | Q36: 医保 | R36: 平移取整 | S36: 加权平移取整 | T36: 003110000370000-311000037 | U36: 311000037 | V36: 经尿道治疗尿失禁 | W36: 含硬化剂局部注射 | Y36: 次 | AA36: 220 | AB36: 200 | AC36: 220 | AD36: 200 | AE36: 170 | AF36: =IFERROR(FIND("（加收）",C36,1),0) -> 0 | AG36: =IF(AF36>0,LEFT(C36,IFERROR(FIND("-",C36,1),1)-1),C36) -> 泌尿系镜下治疗费（常规） | AH36: =IF(AF36>0,_xlfn.MAXIFS(N:N,C:C,AG36),0)+N36 -> 815 | AI36: =IF(AF36>0,_xlfn.MAXIFS(O:O,C:C,AG36),0)+O36 -> 740 | AJ36: =IF(AF36>0,_xlfn.MAXIFS(P:P,C:C,AG36),0)+P36 -> 640
A37: 32 | B37: 013110000200000 | C37: 泌尿系镜下治疗费（常规） | D37: 治疗费 | E37: 通过置物、取物等方式对泌尿系统及男性生殖系统病灶进行治疗。 | F37: 所定价格涵盖消毒、下镜、治疗、撤镜等步骤所需的人力资源和基本物质资源消耗。（不含泌尿系镜下检查） | G37: 次 | H37: 同时行常规治疗和特殊治疗的，按照“泌尿系镜下治疗费（特殊）”收取。 | I37: 825 | J37: 743 | K37: 817.32836 | L37: 741.1044 | M37: 640.94595 | N37: 815 | O37: 740 | P37: 640 | Q37: 医保 | R37: 平移取整 | S37: 加权平移取整 | T37: 003312010070000-331201007 | U37: 331201007 | V37: 经尿道前列腺气囊扩张术 | X37: 气囊导管 | Y37: 次 | AA37: 250 | AB37: 225 | AC37: 250 | AD37: 240 | AE37: 204 | AF37: =IFERROR(FIND("（加收）",C37,1),0) -> 0 | AG37: =IF(AF37>0,LEFT(C37,IFERROR(FIND("-",C37,1),1)-1),C37) -> 泌尿系镜下治疗费（常规） | AH37: =IF(AF37>0,_xlfn.MAXIFS(N:N,C:C,AG37),0)+N37 -> 815 | AI37: =IF(AF37>0,_xlfn.MAXIFS(O:O,C:C,AG37),0)+O37 -> 740 | AJ37: =IF(AF37>0,_xlfn.MAXIFS(P:P,C:C,AG37),0)+P37 -> 640
A38: 32 | B38: 013110000200000 | C38: 泌尿系镜下治疗费（常规） | D38: 治疗费 | E38: 通过置物、取物等方式对泌尿系统及男性生殖系统病灶进行治疗。 | F38: 所定价格涵盖消毒、下镜、治疗、撤镜等步骤所需的人力资源和基本物质资源消耗。（不含泌尿系镜下检查） | G38: 次 | H38: 同时行常规治疗和特殊治疗的，按照“泌尿系镜下治疗费（特殊）”收取。 | I38: 825 | J38: 743 | K38: 817.32836 | L38: 741.1044 | M38: 640.94595 | N38: 815 | O38: 740 | P38: 640 | Q38: 医保 | R38: 平移取整 | S38: 加权平移取整 | T38: 003312010070000-33120100701 | U38: 33120100701 | V38: 小儿经尿道前列腺气囊扩张术 | Y38: 次 | AA38: 325 | AB38: 295 | AC38: 325 | AD38: 310 | AE38: 265 | AF38: =IFERROR(FIND("（加收）",C38,1),0) -> 0 | AG38: =IF(AF38>0,LEFT(C38,IFERROR(FIND("-",C38,1),1)-1),C38) -> 泌尿系镜下治疗费（常规） | AH38: =IF(AF38>0,_xlfn.MAXIFS(N:N,C:C,AG38),0)+N38 -> 815 | AI38: =IF(AF38>0,_xlfn.MAXIFS(O:O,C:C,AG38),0)+O38 -> 740 | AJ38: =IF(AF38>0,_xlfn.MAXIFS(P:P,C:C,AG38),0)+P38 -> 640
A39: 32 | B39: 013110000200000 | C39: 泌尿系镜下治疗费（常规） | D39: 治疗费 | E39: 通过置物、取物等方式对泌尿系统及男性生殖系统病灶进行治疗。 | F39: 所定价格涵盖消毒、下镜、治疗、撤镜等步骤所需的人力资源和基本物质资源消耗。（不含泌尿系镜下检查） | G39: 次 | H39: 同时行常规治疗和特殊治疗的，按照“泌尿系镜下治疗费（特殊）”收取。 | I39: 825 | J39: 743 | K39: 817.32836 | L39: 741.1044 | M39: 640.94595 | N39: 815 | O39: 740 | P39: 640 | Q39: 医保 | R39: 平移取整 | S39: 加权平移取整 | T39: 003312010070000-33120100702 | U39: 33120100702 | V39: 经膀胱镜经尿道前列腺气囊扩张术 | Y39: 次 | AA39: 500 | AB39: 450 | AC39: 500 | AD39: 465 | AE39: 394 | AF39: =IFERROR(FIND("（加收）",C39,1),0) -> 0 | AG39: =IF(AF39>0,LEFT(C39,IFERROR(FIND("-",C39,1),1)-1),C39) -> 泌尿系镜下治疗费（常规） | AH39: =IF(AF39>0,_xlfn.MAXIFS(N:N,C:C,AG39),0)+N39 -> 815 | AI39: =IF(AF39>0,_xlfn.MAXIFS(O:O,C:C,AG39),0)+O39 -> 740 | AJ39: =IF(AF39>0,_xlfn.MAXIFS(P:P,C:C,AG39),0)+P39 -> 640
A40: 32 | B40: 013110000200000 | C40: 泌尿系镜下治疗费（常规） | D40: 治疗费 | E40: 通过置物、取物等方式对泌尿系统及男性生殖系统病灶进行治疗。 | F40: 所定价格涵盖消毒、下镜、治疗、撤镜等步骤所需的人力资源和基本物质资源消耗。（不含泌尿系镜下检查） | G40: 次 | H40: 同时行常规治疗和特殊治疗的，按照“泌尿系镜下治疗费（特殊）”收取。 | I40: 825 | J40: 743 | K40: 817.32836 | L40: 741.1044 | M40: 640.94595 | N40: 815 | O40: 740 | P40: 640 | Q40: 医保 | R40: 平移取整 | S40: 加权平移取整 | T40: 003312010070000-33120100703 | U40: 33120100703 | V40: 小儿经膀胱镜经尿道前列腺气囊扩张术 | Y40: 次 | AA40: 575 | AB40: 520 | AC40: 575 | AD40: 535 | AE40: 455 | AF40: =IFERROR(FIND("（加收）",C40,1),0) -> 0 | AG40: =IF(AF40>0,LEFT(C40,IFERROR(FIND("-",C40,1),1)-1),C40) -> 泌尿系镜下治疗费（常规） | AH40: =IF(AF40>0,_xlfn.MAXIFS(N:N,C:C,AG40),0)+N40 -> 815 | AI40: =IF(AF40>0,_xlfn.MAXIFS(O:O,C:C,AG40),0)+O40 -> 740 | AJ40: =IF(AF40>0,_xlfn.MAXIFS(P:P,C:C,AG40),0)+P40 -> 640
A41: 32 | B41: 013110000200000 | C41: 泌尿系镜下治疗费（常规） | D41: 治疗费 | E41: 通过置物、取物等方式对泌尿系统及男性生殖系统病灶进行治疗。 | F41: 所定价格涵盖消毒、下镜、治疗、撤镜等步骤所需的人力资源和基本物质资源消耗。（不含泌尿系镜下检查） | G41: 次 | H41: 同时行常规治疗和特殊治疗的，按照“泌尿系镜下治疗费（特殊）”收取。 | I41: 825 | J41: 743 | K41: 817.32836 | L41: 741.1044 | M41: 640.94595 | N41: 815 | O41: 740 | P41: 640 | Q41: 医保 | R41: 平移取整 | S41: 加权平移取整 | T41: 353312030140000-331203014 | U41: 331203014 | V41: 经精囊镜射精管疏通冲洗术 | W41: 消毒，取Wolf4.5/6.5精囊镜连接电视成像系统，以生理盐水为灌注液，直视下将精囊镜经尿道置入膀胱，观察尿道、膀胱，将镜体退至精阜处，仔细观察射精管口，发现射精管口后稍加大灌注液速度，置入斑马导丝，沿斑马导丝用镜体边扩张边将镜体置入一侧射精管内，并逐渐推进精囊内，用生理盐水或药物反复冲洗精囊直至冲洗液变清，并取精囊液送细菌培养。含射精管扩张术、斑马导丝。 | Y41: 侧 | AA41: 1000 | AC41: 900 | AD41: 810 | AE41: 688.5 | AF41: =IFERROR(FIND("（加收）",C41,1),0) -> 0 | AG41: =IF(AF41>0,LEFT(C41,IFERROR(FIND("-",C41,1),1)-1),C41) -> 泌尿系镜下治疗费（常规） | AH41: =IF(AF41>0,_xlfn.MAXIFS(N:N,C:C,AG41),0)+N41 -> 815 | AI41: =IF(AF41>0,_xlfn.MAXIFS(O:O,C:C,AG41),0)+O41 -> 740 | AJ41: =IF(AF41>0,_xlfn.MAXIFS(P:P,C:C,AG41),0)+P41 -> 640
A42: 33 | B42: 013110000210000 | C42: 泌尿系镜下治疗费（特殊） | D42: 治疗费 | E42: 通过电凝、冷冻、蒸汽、射频、微波等各种物理方式对泌尿系统及男性生殖系统病灶进行治疗。 | F42: 所定价格涵盖消毒、下镜、治疗、取出、撤镜等步骤所需的人力资源和基本物质资源消耗。（不含泌尿系镜下检查） | G42: 次 | H42: 1.同一治疗位置使用多种能量源只可收取一次。 2.同时行常规治疗和特殊治疗的，按照“泌尿系镜下治疗费（特殊）”收取。 | I42: 1900 | J42: 1710 | K42: 2248.5461 | L42: 1514.4078 | M42: 1109.2737 | N42: 1875 | O42: 1700 | P42: 1470 | Q42: 医保 | R42: 理顺 | S42: 扣除原项目中涉及的内镜使用费用后加权平均，根据项目间比价关系，为常规的2.3倍。 | T42: 003110000260000-311000026 | U42: 311000026 | V42: 经输尿管镜碎石取石术 | Y42: 次 | Z42: 弹道法基层850元，县级医院1000元，市级医院1100元；激光基层1360元，县级医院1600元，市级医院1760元。 | AA42: 990 | AB42: 890 | AC42: 990 | AD42: 900 | AE42: 765 | AF42: =IFERROR(FIND("（加收）",C42,1),0) -> 0 | AG42: =IF(AF42>0,LEFT(C42,IFERROR(FIND("-",C42,1),1)-1),C42) -> 泌尿系镜下治疗费（特殊） | AH42: =IF(AF42>0,_xlfn.MAXIFS(N:N,C:C,AG42),0)+N42 -> 1875 | AI42: =IF(AF42>0,_xlfn.MAXIFS(O:O,C:C,AG42),0)+O42 -> 1700 | AJ42: =IF(AF42>0,_xlfn.MAXIFS(P:P,C:C,AG42),0)+P42 -> 1470
A43: 33 | B43: 013110000210000 | C43: 泌尿系镜下治疗费（特殊） | D43: 治疗费 | E43: 通过电凝、冷冻、蒸汽、射频、微波等各种物理方式对泌尿系统及男性生殖系统病灶进行治疗。 | F43: 所定价格涵盖消毒、下镜、治疗、取出、撤镜等步骤所需的人力资源和基本物质资源消耗。（不含泌尿系镜下检查） | G43: 次 | H43: 1.同一治疗位置使用多种能量源只可收取一次。 2.同时行常规治疗和特殊治疗的，按照“泌尿系镜下治疗费（特殊）”收取。 | I43: 1900 | J43: 1710 | K43: 2248.5461 | L43: 1514.4078 | M43: 1109.2737 | N43: 1875 | O43: 1700 | P43: 1470 | Q43: 医保 | R43: 理顺 | S43: 扣除原项目中涉及的内镜使用费用后加权平均，根据项目间比价关系，为常规的2.3倍。 | T43: 003110000260000-31100002601 | U43: 31100002601 | V43: 经输尿管镜碎石取石术（弹道法） | Y43: 次 | Z43: 弹道法 | AA43: 1100 | AB43: 990 | AC43: 1100 | AD43: 1000 | AE43: 850 | AF43: =IFERROR(FIND("（加收）",C43,1),0) -> 0 | AG43: =IF(AF43>0,LEFT(C43,IFERROR(FIND("-",C43,1),1)-1),C43) -> 泌尿系镜下治疗费（特殊） | AH43: =IF(AF43>0,_xlfn.MAXIFS(N:N,C:C,AG43),0)+N43 -> 1875 | AI43: =IF(AF43>0,_xlfn.MAXIFS(O:O,C:C,AG43),0)+O43 -> 1700 | AJ43: =IF(AF43>0,_xlfn.MAXIFS(P:P,C:C,AG43),0)+P43 -> 1470
A44: 33 | B44: 013110000210000 | C44: 泌尿系镜下治疗费（特殊） | D44: 治疗费 | E44: 通过电凝、冷冻、蒸汽、射频、微波等各种物理方式对泌尿系统及男性生殖系统病灶进行治疗。 | F44: 所定价格涵盖消毒、下镜、治疗、取出、撤镜等步骤所需的人力资源和基本物质资源消耗。（不含泌尿系镜下检查） | G44: 次 | H44: 1.同一治疗位置使用多种能量源只可收取一次。 2.同时行常规治疗和特殊治疗的，按照“泌尿系镜下治疗费（特殊）”收取。 | I44: 1900 | J44: 1710 | K44: 2248.5461 | L44: 1514.4078 | M44: 1109.2737 | N44: 1875 | O44: 1700 | P44: 1470 | Q44: 医保 | R44: 理顺 | S44: 扣除原项目中涉及的内镜使用费用后加权平均，根据项目间比价关系，为常规的2.3倍。 | T44: 003110000260000-31100002602 | U44: 31100002602 | V44: 经输尿管镜碎石取石术（激光法） | Y44: 次 | Z44: 激光法 | AA44: 1760 | AB44: 1580 | AC44: 1760 | AD44: 1600 | AE44: 1360 | AF44: =IFERROR(FIND("（加收）",C44,1),0) -> 0 | AG44: =IF(AF44>0,LEFT(C44,IFERROR(FIND("-",C44,1),1)-1),C44) -> 泌尿系镜下治疗费（特殊） | AH44: =IF(AF44>0,_xlfn.MAXIFS(N:N,C:C,AG44),0)+N44 -> 1875 | AI44: =IF(AF44>0,_xlfn.MAXIFS(O:O,C:C,AG44),0)+O44 -> 1700 | AJ44: =IF(AF44>0,_xlfn.MAXIFS(P:P,C:C,AG44),0)+P44 -> 1470
A45: 33 | B45: 013110000210000 | C45: 泌尿系镜下治疗费（特殊） | D45: 治疗费 | E45: 通过电凝、冷冻、蒸汽、射频、微波等各种物理方式对泌尿系统及男性生殖系统病灶进行治疗。 | F45: 所定价格涵盖消毒、下镜、治疗、取出、撤镜等步骤所需的人力资源和基本物质资源消耗。（不含泌尿系镜下检查） | G45: 次 | H45: 1.同一治疗位置使用多种能量源只可收取一次。 2.同时行常规治疗和特殊治疗的，按照“泌尿系镜下治疗费（特殊）”收取。 | I45: 1900 | J45: 1710 | K45: 2248.5461 | L45: 1514.4078 | M45: 1109.2737 | N45: 1875 | O45: 1700 | P45: 1470 | Q45: 医保 | R45: 理顺 | S45: 扣除原项目中涉及的内镜使用费用后加权平均，根据项目间比价关系，为常规的2.3倍。 | T45: 003110000350000-311000035 | U45: 311000035 | V45: 经膀胱镜尿道镜特殊治疗 | Y45: 次 | Z45: 激光法基层178.5元，县级医院210元，市级医院231元 | AA45: 176 | AB45: 160 | AC45: 176 | AD45: 160 | AE45: 136 | AF45: =IFERROR(FIND("（加收）",C45,1),0) -> 0 | AG45: =IF(AF45>0,LEFT(C45,IFERROR(FIND("-",C45,1),1)-1),C45) -> 泌尿系镜下治疗费（特殊） | AH45: =IF(AF45>0,_xlfn.MAXIFS(N:N,C:C,AG45),0)+N45 -> 1875 | AI45: =IF(AF45>0,_xlfn.MAXIFS(O:O,C:C,AG45),0)+O45 -> 1700 | AJ45: =IF(AF45>0,_xlfn.MAXIFS(P:P,C:C,AG45),0)+P45 -> 1470
A46: 33 | B46: 013110000210000 | C46: 泌尿系镜下治疗费（特殊） | D46: 治疗费 | E46: 通过电凝、冷冻、蒸汽、射频、微波等各种物理方式对泌尿系统及男性生殖系统病灶进行治疗。 | F46: 所定价格涵盖消毒、下镜、治疗、取出、撤镜等步骤所需的人力资源和基本物质资源消耗。（不含泌尿系镜下检查） | G46: 次 | H46: 1.同一治疗位置使用多种能量源只可收取一次。 2.同时行常规治疗和特殊治疗的，按照“泌尿系镜下治疗费（特殊）”收取。 | I46: 1900 | J46: 1710 | K46: 2248.5461 | L46: 1514.4078 | M46: 1109.2737 | N46: 1875 | O46: 1700 | P46: 1470 | Q46: 医保 | R46: 理顺 | S46: 扣除原项目中涉及的内镜使用费用后加权平均，根据项目间比价关系，为常规的2.3倍。 | T46: 003110000350000-31100003501 | U46: 31100003501 | V46: 经膀胱镜尿道镜特殊治疗（激光法） | Y46: 次 | Z46: 激光法 | AA46: 230 | AB46: 210 | AC46: 231 | AD46: 210 | AE46: 178.5 | AF46: =IFERROR(FIND("（加收）",C46,1),0) -> 0 | AG46: =IF(AF46>0,LEFT(C46,IFERROR(FIND("-",C46,1),1)-1),C46) -> 泌尿系镜下治疗费（特殊） | AH46: =IF(AF46>0,_xlfn.MAXIFS(N:N,C:C,AG46),0)+N46 -> 1875 | AI46: =IF(AF46>0,_xlfn.MAXIFS(O:O,C:C,AG46),0)+O46 -> 1700 | AJ46: =IF(AF46>0,_xlfn.MAXIFS(P:P,C:C,AG46),0)+P46 -> 1470
A47: 33 | B47: 013110000210000 | C47: 泌尿系镜下治疗费（特殊） | D47: 治疗费 | E47: 通过电凝、冷冻、蒸汽、射频、微波等各种物理方式对泌尿系统及男性生殖系统病灶进行治疗。 | F47: 所定价格涵盖消毒、下镜、治疗、取出、撤镜等步骤所需的人力资源和基本物质资源消耗。（不含泌尿系镜下检查） | G47: 次 | H47: 1.同一治疗位置使用多种能量源只可收取一次。 2.同时行常规治疗和特殊治疗的，按照“泌尿系镜下治疗费（特殊）”收取。 | I47: 1900 | J47: 1710 | K47: 2248.5461 | L47: 1514.4078 | M47: 1109.2737 | N47: 1875 | O47: 1700 | P47: 1470 | Q47: 医保 | R47: 理顺 | S47: 扣除原项目中涉及的内镜使用费用后加权平均，根据项目间比价关系，为常规的2.3倍。 | T47: 003311030260000-331103026 | U47: 331103026 | V47: 经尿道膀胱肿瘤特殊治疗 | W47: 指电灼、激光法 | Y47: 次 | Z47: 电切法市级医院2590元，县级医院2330元，基层1980元 | AA47: 2880 | AB47: 2590 | AC47: 2530 | AD47: 2280 | AE47: 1940 | AF47: =IFERROR(FIND("（加收）",C47,1),0) -> 0 | AG47: =IF(AF47>0,LEFT(C47,IFERROR(FIND("-",C47,1),1)-1),C47) -> 泌尿系镜下治疗费（特殊） | AH47: =IF(AF47>0,_xlfn.MAXIFS(N:N,C:C,AG47),0)+N47 -> 1875 | AI47: =IF(AF47>0,_xlfn.MAXIFS(O:O,C:C,AG47),0)+O47 -> 1700 | AJ47: =IF(AF47>0,_xlfn.MAXIFS(P:P,C:C,AG47),0)+P47 -> 1470
A48: 33 | B48: 013110000210000 | C48: 泌尿系镜下治疗费（特殊） | D48: 治疗费 | E48: 通过电凝、冷冻、蒸汽、射频、微波等各种物理方式对泌尿系统及男性生殖系统病灶进行治疗。 | F48: 所定价格涵盖消毒、下镜、治疗、取出、撤镜等步骤所需的人力资源和基本物质资源消耗。（不含泌尿系镜下检查） | G48: 次 | H48: 1.同一治疗位置使用多种能量源只可收取一次。 2.同时行常规治疗和特殊治疗的，按照“泌尿系镜下治疗费（特殊）”收取。 | I48: 1900 | J48: 1710 | K48: 2248.5461 | L48: 1514.4078 | M48: 1109.2737 | N48: 1875 | O48: 1700 | P48: 1470 | Q48: 医保 | R48: 理顺 | S48: 扣除原项目中涉及的内镜使用费用后加权平均，根据项目间比价关系，为常规的2.3倍。 | T48: 003311030260000-33110302601 | U48: 33110302601 | V48: 经尿道膀胱肿瘤特殊治疗（电切法） | Y48: 次 | Z48: 电切法 | AA48: 3360 | AB48: 3020 | AC48: 2590 | AD48: 2330 | AE48: 1980 | AF48: =IFERROR(FIND("（加收）",C48,1),0) -> 0 | AG48: =IF(AF48>0,LEFT(C48,IFERROR(FIND("-",C48,1),1)-1),C48) -> 泌尿系镜下治疗费（特殊） | AH48: =IF(AF48>0,_xlfn.MAXIFS(N:N,C:C,AG48),0)+N48 -> 1875 | AI48: =IF(AF48>0,_xlfn.MAXIFS(O:O,C:C,AG48),0)+O48 -> 1700 | AJ48: =IF(AF48>0,_xlfn.MAXIFS(P:P,C:C,AG48),0)+P48 -> 1470
A49: 33 | B49: 013110000210000 | C49: 泌尿系镜下治疗费（特殊） | D49: 治疗费 | E49: 通过电凝、冷冻、蒸汽、射频、微波等各种物理方式对泌尿系统及男性生殖系统病灶进行治疗。 | F49: 所定价格涵盖消毒、下镜、治疗、取出、撤镜等步骤所需的人力资源和基本物质资源消耗。（不含泌尿系镜下检查） | G49: 次 | H49: 1.同一治疗位置使用多种能量源只可收取一次。 2.同时行常规治疗和特殊治疗的，按照“泌尿系镜下治疗费（特殊）”收取。 | I49: 1900 | J49: 1710 | K49: 2248.5461 | L49: 1514.4078 | M49: 1109.2737 | N49: 1875 | O49: 1700 | P49: 1470 | Q49: 医保 | R49: 理顺 | S49: 扣除原项目中涉及的内镜使用费用后加权平均，根据项目间比价关系，为常规的2.3倍。 | T49: 003311030260000-33110302602 | U49: 33110302602 | V49: 小儿经尿道膀胱肿瘤特殊治疗 | Y49: 次 | AA49: 3745 | AB49: 3365 | AC49: 3290 | AD49: 2965 | AE49: 2520 | AF49: =IFERROR(FIND("（加收）",C49,1),0) -> 0 | AG49: =IF(AF49>0,LEFT(C49,IFERROR(FIND("-",C49,1),1)-1),C49) -> 泌尿系镜下治疗费（特殊） | AH49: =IF(AF49>0,_xlfn.MAXIFS(N:N,C:C,AG49),0)+N49 -> 1875 | AI49: =IF(AF49>0,_xlfn.MAXIFS(O:O,C:C,AG49),0)+O49 -> 1700 | AJ49: =IF(AF49>0,_xlfn.MAXIFS(P:P,C:C,AG49),0)+P49 -> 1470
A50: 33 | B50: 013110000210000 | C50: 泌尿系镜下治疗费（特殊） | D50: 治疗费 | E50: 通过电凝、冷冻、蒸汽、射频、微波等各种物理方式对泌尿系统及男性生殖系统病灶进行治疗。 | F50: 所定价格涵盖消毒、下镜、治疗、取出、撤镜等步骤所需的人力资源和基本物质资源消耗。（不含泌尿系镜下检查） | G50: 次 | H50: 1.同一治疗位置使用多种能量源只可收取一次。 2.同时行常规治疗和特殊治疗的，按照“泌尿系镜下治疗费（特殊）”收取。 | I50: 1900 | J50: 1710 | K50: 2248.5461 | L50: 1514.4078 | M50: 1109.2737 | N50: 1875 | O50: 1700 | P50: 1470 | Q50: 医保 | R50: 理顺 | S50: 扣除原项目中涉及的内镜使用费用后加权平均，根据项目间比价关系，为常规的2.3倍。 | T50: 003311030260000-33110302603 | U50: 33110302603 | V50: 小儿经尿道膀胱肿瘤特殊治疗（电切法） | Y50: 次 | Z50: 电切法 | AA50: 4370 | AB50: 3925 | AC50: 3365 | AD50: 3030 | AE50: 2575 | AF50: =IFERROR(FIND("（加收）",C50,1),0) -> 0 | AG50: =IF(AF50>0,LEFT(C50,IFERROR(FIND("-",C50,1),1)-1),C50) -> 泌尿系镜下治疗费（特殊） | AH50: =IF(AF50>0,_xlfn.MAXIFS(N:N,C:C,AG50),0)+N50 -> 1875 | AI50: =IF(AF50>0,_xlfn.MAXIFS(O:O,C:C,AG50),0)+O50 -> 1700 | AJ50: =IF(AF50>0,_xlfn.MAXIFS(P:P,C:C,AG50),0)+P50 -> 1470
A51: 33 | B51: 013110000210000 | C51: 泌尿系镜下治疗费（特殊） | D51: 治疗费 | E51: 通过电凝、冷冻、蒸汽、射频、微波等各种物理方式对泌尿系统及男性生殖系统病灶进行治疗。 | F51: 所定价格涵盖消毒、下镜、治疗、取出、撤镜等步骤所需的人力资源和基本物质资源消耗。（不含泌尿系镜下检查） | G51: 次 | H51: 1.同一治疗位置使用多种能量源只可收取一次。 2.同时行常规治疗和特殊治疗的，按照“泌尿系镜下治疗费（特殊）”收取。 | I51: 1900 | J51: 1710 | K51: 2248.5461 | L51: 1514.4078 | M51: 1109.2737 | N51: 1875 | O51: 1700 | P51: 1470 | Q51: 医保 | R51: 理顺 | S51: 扣除原项目中涉及的内镜使用费用后加权平均，根据项目间比价关系，为常规的2.3倍。 | T51: 003311030260000-33110302604 | U51: 33110302604 | V51: 经膀胱镜下经尿道膀胱肿瘤特殊治疗 | Y51: 次 | AA51: 3130 | AB51: 2815 | AC51: 2780 | AD51: 2505 | AE51: 2130 | AF51: =IFERROR(FIND("（加收）",C51,1),0) -> 0 | AG51: =IF(AF51>0,LEFT(C51,IFERROR(FIND("-",C51,1),1)-1),C51) -> 泌尿系镜下治疗费（特殊） | AH51: =IF(AF51>0,_xlfn.MAXIFS(N:N,C:C,AG51),0)+N51 -> 1875 | AI51: =IF(AF51>0,_xlfn.MAXIFS(O:O,C:C,AG51),0)+O51 -> 1700 | AJ51: =IF(AF51>0,_xlfn.MAXIFS(P:P,C:C,AG51),0)+P51 -> 1470
A52: 33 | B52: 013110000210000 | C52: 泌尿系镜下治疗费（特殊） | D52: 治疗费 | E52: 通过电凝、冷冻、蒸汽、射频、微波等各种物理方式对泌尿系统及男性生殖系统病灶进行治疗。 | F52: 所定价格涵盖消毒、下镜、治疗、取出、撤镜等步骤所需的人力资源和基本物质资源消耗。（不含泌尿系镜下检查） | G52: 次 | H52: 1.同一治疗位置使用多种能量源只可收取一次。 2.同时行常规治疗和特殊治疗的，按照“泌尿系镜下治疗费（特殊）”收取。 | I52: 1900 | J52: 1710 | K52: 2248.5461 | L52: 1514.4078 | M52: 1109.2737 | N52: 1875 | O52: 1700 | P52: 1470 | Q52: 医保 | R52: 理顺 | S52: 扣除原项目中涉及的内镜使用费用后加权平均，根据项目间比价关系，为常规的2.3倍。 | T52: 003311030260000-33110302605 | U52: 33110302605 | V52: 经膀胱镜下经尿道膀胱肿瘤特殊治疗（电切法） | Y52: 次 | Z52: 电切法 | AA52: 3610 | AB52: 3245 | AC52: 2840 | AD52: 2555 | AE52: 2170 | AF52: =IFERROR(FIND("（加收）",C52,1),0) -> 0 | AG52: =IF(AF52>0,LEFT(C52,IFERROR(FIND("-",C52,1),1)-1),C52) -> 泌尿系镜下治疗费（特殊） | AH52: =IF(AF52>0,_xlfn.MAXIFS(N:N,C:C,AG52),0)+N52 -> 1875 | AI52: =IF(AF52>0,_xlfn.MAXIFS(O:O,C:C,AG52),0)+O52 -> 1700 | AJ52: =IF(AF52>0,_xlfn.MAXIFS(P:P,C:C,AG52),0)+P52 -> 1470
A53: 33 | B53: 013110000210000 | C53: 泌尿系镜下治疗费（特殊） | D53: 治疗费 | E53: 通过电凝、冷冻、蒸汽、射频、微波等各种物理方式对泌尿系统及男性生殖系统病灶进行治疗。 | F53: 所定价格涵盖消毒、下镜、治疗、取出、撤镜等步骤所需的人力资源和基本物质资源消耗。（不含泌尿系镜下检查） | G53: 次 | H53: 1.同一治疗位置使用多种能量源只可收取一次。 2.同时行常规治疗和特殊治疗的，按照“泌尿系镜下治疗费（特殊）”收取。 | I53: 1900 | J53: 1710 | K53: 2248.5461 | L53: 1514.4078 | M53: 1109.2737 | N53: 1875 | O53: 1700 | P53: 1470 | Q53: 医保 | R53: 理顺 | S53: 扣除原项目中涉及的内镜使用费用后加权平均，根据项目间比价关系，为常规的2.3倍。 | T53: 003311030260000-33110302606 | U53: 33110302606 | V53: 小儿经膀胱镜下经尿道膀胱肿瘤特殊治疗 | Y53: 次 | AA53: 3995 | AB53: 3590 | AC53: 3540 | AD53: 3190 | AE53: 2710 | AF53: =IFERROR(FIND("（加收）",C53,1),0) -> 0 | AG53: =IF(AF53>0,LEFT(C53,IFERROR(FIND("-",C53,1),1)-1),C53) -> 泌尿系镜下治疗费（特殊） | AH53: =IF(AF53>0,_xlfn.MAXIFS(N:N,C:C,AG53),0)+N53 -> 1875 | AI53: =IF(AF53>0,_xlfn.MAXIFS(O:O,C:C,AG53),0)+O53 -> 1700 | AJ53: =IF(AF53>0,_xlfn.MAXIFS(P:P,C:C,AG53),0)+P53 -> 1470
A54: 33 | B54: 013110000210000 | C54: 泌尿系镜下治疗费（特殊） | D54: 治疗费 | E54: 通过电凝、冷冻、蒸汽、射频、微波等各种物理方式对泌尿系统及男性生殖系统病灶进行治疗。 | F54: 所定价格涵盖消毒、下镜、治疗、取出、撤镜等步骤所需的人力资源和基本物质资源消耗。（不含泌尿系镜下检查） | G54: 次 | H54: 1.同一治疗位置使用多种能量源只可收取一次。 2.同时行常规治疗和特殊治疗的，按照“泌尿系镜下治疗费（特殊）”收取。 | I54: 1900 | J54: 1710 | K54: 2248.5461 | L54: 1514.4078 | M54: 1109.2737 | N54: 1875 | O54: 1700 | P54: 1470 | Q54: 医保 | R54: 理顺 | S54: 扣除原项目中涉及的内镜使用费用后加权平均，根据项目间比价关系，为常规的2.3倍。 | T54: 003311030260000-33110302607 | U54: 33110302607 | V54: 小儿经膀胱镜下经尿道膀胱肿瘤特殊治疗（电切法） | Y54: 次 | Z54: 电切法 | AA54: 4620 | AB54: 4150 | AC54: 3615 | AD54: 3255 | AE54: 2765 | AF54: =IFERROR(FIND("（加收）",C54,1),0) -> 0 | AG54: =IF(AF54>0,LEFT(C54,IFERROR(FIND("-",C54,1),1)-1),C54) -> 泌尿系镜下治疗费（特殊） | AH54: =IF(AF54>0,_xlfn.MAXIFS(N:N,C:C,AG54),0)+N54 -> 1875 | AI54: =IF(AF54>0,_xlfn.MAXIFS(O:O,C:C,AG54),0)+O54 -> 1700 | AJ54: =IF(AF54>0,_xlfn.MAXIFS(P:P,C:C,AG54),0)+P54 -> 1470
A55: 33 | B55: 013110000210000 | C55: 泌尿系镜下治疗费（特殊） | D55: 治疗费 | E55: 通过电凝、冷冻、蒸汽、射频、微波等各种物理方式对泌尿系统及男性生殖系统病灶进行治疗。 | F55: 所定价格涵盖消毒、下镜、治疗、取出、撤镜等步骤所需的人力资源和基本物质资源消耗。（不含泌尿系镜下检查） | G55: 次 | H55: 1.同一治疗位置使用多种能量源只可收取一次。 2.同时行常规治疗和特殊治疗的，按照“泌尿系镜下治疗费（特殊）”收取。 | I55: 1900 | J55: 1710 | K55: 2248.5461 | L55: 1514.4078 | M55: 1109.2737 | N55: 1875 | O55: 1700 | P55: 1470 | Q55: 医保 | R55: 理顺 | S55: 扣除原项目中涉及的内镜使用费用后加权平均，根据项目间比价关系，为常规的2.3倍。 | T55: 003311030270000-33110302702 | U55: 33110302702 | V55: 膀胱镜下经尿道膀胱碎石取石术 | Y55: 次 | AA55: 1500 | AB55: 1350 | AC55: 1500 | AD55: 1425 | AE55: 1210 | AF55: =IFERROR(FIND("（加收）",C55,1),0) -> 0 | AG55: =IF(AF55>0,LEFT(C55,IFERROR(FIND("-",C55,1),1)-1),C55) -> 泌尿系镜下治疗费（特殊） | AH55: =IF(AF55>0,_xlfn.MAXIFS(N:N,C:C,AG55),0)+N55 -> 1875 | AI55: =IF(AF55>0,_xlfn.MAXIFS(O:O,C:C,AG55),0)+O55 -> 1700 | AJ55: =IF(AF55>0,_xlfn.MAXIFS(P:P,C:C,AG55),0)+P55 -> 1470
A56: 33 | B56: 013110000210000 | C56: 泌尿系镜下治疗费（特殊） | D56: 治疗费 | E56: 通过电凝、冷冻、蒸汽、射频、微波等各种物理方式对泌尿系统及男性生殖系统病灶进行治疗。 | F56: 所定价格涵盖消毒、下镜、治疗、取出、撤镜等步骤所需的人力资源和基本物质资源消耗。（不含泌尿系镜下检查） | G56: 次 | H56: 1.同一治疗位置使用多种能量源只可收取一次。 2.同时行常规治疗和特殊治疗的，按照“泌尿系镜下治疗费（特殊）”收取。 | I56: 1900 | J56: 1710 | K56: 2248.5461 | L56: 1514.4078 | M56: 1109.2737 | N56: 1875 | O56: 1700 | P56: 1470 | Q56: 医保 | R56: 理顺 | S56: 扣除原项目中涉及的内镜使用费用后加权平均，根据项目间比价关系，为常规的2.3倍。 | T56: 003311030270000-33110302703 | U56: 33110302703 | V56: 小儿膀胱镜下经尿道膀胱碎石取石术 | Y56: 次 | AA56: 1875 | AB56: 1690 | AC56: 1875 | AD56: 1785 | AE56: 1515 | AF56: =IFERROR(FIND("（加收）",C56,1),0) -> 0 | AG56: =IF(AF56>0,LEFT(C56,IFERROR(FIND("-",C56,1),1)-1),C56) -> 泌尿系镜下治疗费（特殊） | AH56: =IF(AF56>0,_xlfn.MAXIFS(N:N,C:C,AG56),0)+N56 -> 1875 | AI56: =IF(AF56>0,_xlfn.MAXIFS(O:O,C:C,AG56),0)+O56 -> 1700 | AJ56: =IF(AF56>0,_xlfn.MAXIFS(P:P,C:C,AG56),0)+P56 -> 1470
A57: 33 | B57: 013110000210000 | C57: 泌尿系镜下治疗费（特殊） | D57: 治疗费 | E57: 通过电凝、冷冻、蒸汽、射频、微波等各种物理方式对泌尿系统及男性生殖系统病灶进行治疗。 | F57: 所定价格涵盖消毒、下镜、治疗、取出、撤镜等步骤所需的人力资源和基本物质资源消耗。（不含泌尿系镜下检查） | G57: 次 | H57: 1.同一治疗位置使用多种能量源只可收取一次。 2.同时行常规治疗和特殊治疗的，按照“泌尿系镜下治疗费（特殊）”收取。 | I57: 1900 | J57: 1710 | K57: 2248.5461 | L57: 1514.4078 | M57: 1109.2737 | N57: 1875 | O57: 1700 | P57: 1470 | Q57: 医保 | R57: 理顺 | S57: 扣除原项目中涉及的内镜使用费用后加权平均，根据项目间比价关系，为常规的2.3倍。 | T57: 003312010060000-331201006 | U57: 331201006 | V57: 经尿道前列腺电切术 | Y57: 次 | Z57: 电切法市级医院3635元，县级医院3270元，基层2780元；等离子法市级医院3310元，县级医院2980元，基层2530元 | AA57: 3080 | AB57: 2770 | AC57: 2530 | AD57: 2280 | AE57: 1940 | AF57: =IFERROR(FIND("（加收）",C57,1),0) -> 0 | AG57: =IF(AF57>0,LEFT(C57,IFERROR(FIND("-",C57,1),1)-1),C57) -> 泌尿系镜下治疗费（特殊） | AH57: =IF(AF57>0,_xlfn.MAXIFS(N:N,C:C,AG57),0)+N57 -> 1875 | AI57: =IF(AF57>0,_xlfn.MAXIFS(O:O,C:C,AG57),0)+O57 -> 1700 | AJ57: =IF(AF57>0,_xlfn.MAXIFS(P:P,C:C,AG57),0)+P57 -> 1470
A58: 33 | B58: 013110000210000 | C58: 泌尿系镜下治疗费（特殊） | D58: 治疗费 | E58: 通过电凝、冷冻、蒸汽、射频、微波等各种物理方式对泌尿系统及男性生殖系统病灶进行治疗。 | F58: 所定价格涵盖消毒、下镜、治疗、取出、撤镜等步骤所需的人力资源和基本物质资源消耗。（不含泌尿系镜下检查） | G58: 次 | H58: 1.同一治疗位置使用多种能量源只可收取一次。 2.同时行常规治疗和特殊治疗的，按照“泌尿系镜下治疗费（特殊）”收取。 | I58: 1900 | J58: 1710 | K58: 2248.5461 | L58: 1514.4078 | M58: 1109.2737 | N58: 1875 | O58: 1700 | P58: 1470 | Q58: 医保 | R58: 理顺 | S58: 扣除原项目中涉及的内镜使用费用后加权平均，根据项目间比价关系，为常规的2.3倍。 | T58: 003312010060000-33120100601 | U58: 33120100601 | V58: 经尿道前列腺电切术（电切法） | Y58: 次 | Z58: 电切法 | AA58: 4040 | AB58: 3630 | AC58: 3635 | AD58: 3270 | AE58: 2780 | AF58: =IFERROR(FIND("（加收）",C58,1),0) -> 0 | AG58: =IF(AF58>0,LEFT(C58,IFERROR(FIND("-",C58,1),1)-1),C58) -> 泌尿系镜下治疗费（特殊） | AH58: =IF(AF58>0,_xlfn.MAXIFS(N:N,C:C,AG58),0)+N58 -> 1875 | AI58: =IF(AF58>0,_xlfn.MAXIFS(O:O,C:C,AG58),0)+O58 -> 1700 | AJ58: =IF(AF58>0,_xlfn.MAXIFS(P:P,C:C,AG58),0)+P58 -> 1470
A59: 33 | B59: 013110000210000 | C59: 泌尿系镜下治疗费（特殊） | D59: 治疗费 | E59: 通过电凝、冷冻、蒸汽、射频、微波等各种物理方式对泌尿系统及男性生殖系统病灶进行治疗。 | F59: 所定价格涵盖消毒、下镜、治疗、取出、撤镜等步骤所需的人力资源和基本物质资源消耗。（不含泌尿系镜下检查） | G59: 次 | H59: 1.同一治疗位置使用多种能量源只可收取一次。 2.同时行常规治疗和特殊治疗的，按照“泌尿系镜下治疗费（特殊）”收取。 | I59: 1900 | J59: 1710 | K59: 2248.5461 | L59: 1514.4078 | M59: 1109.2737 | N59: 1875 | O59: 1700 | P59: 1470 | Q59: 医保 | R59: 理顺 | S59: 扣除原项目中涉及的内镜使用费用后加权平均，根据项目间比价关系，为常规的2.3倍。 | T59: 003312010060000-33120100602 | U59: 33120100602 | V59: 经尿道前列腺电切术（等离子法） | Y59: 次 | Z59: 等离子法 | AA59: 4360 | AB59: 3920 | AC59: 3310 | AD59: 2980 | AE59: 2530 | AF59: =IFERROR(FIND("（加收）",C59,1),0) -> 0 | AG59: =IF(AF59>0,LEFT(C59,IFERROR(FIND("-",C59,1),1)-1),C59) -> 泌尿系镜下治疗费（特殊） | AH59: =IF(AF59>0,_xlfn.MAXIFS(N:N,C:C,AG59),0)+N59 -> 1875 | AI59: =IF(AF59>0,_xlfn.MAXIFS(O:O,C:C,AG59),0)+O59 -> 1700 | AJ59: =IF(AF59>0,_xlfn.MAXIFS(P:P,C:C,AG59),0)+P59 -> 1470
A60: 33 | B60: 013110000210000 | C60: 泌尿系镜下治疗费（特殊） | D60: 治疗费 | E60: 通过电凝、冷冻、蒸汽、射频、微波等各种物理方式对泌尿系统及男性生殖系统病灶进行治疗。 | F60: 所定价格涵盖消毒、下镜、治疗、取出、撤镜等步骤所需的人力资源和基本物质资源消耗。（不含泌尿系镜下检查） | G60: 次 | H60: 1.同一治疗位置使用多种能量源只可收取一次。 2.同时行常规治疗和特殊治疗的，按照“泌尿系镜下治疗费（特殊）”收取。 | I60: 1900 | J60: 1710 | K60: 2248.5461 | L60: 1514.4078 | M60: 1109.2737 | N60: 1875 | O60: 1700 | P60: 1470 | Q60: 医保 | R60: 理顺 | S60: 扣除原项目中涉及的内镜使用费用后加权平均，根据项目间比价关系，为常规的2.3倍。 | T60: 003312010060000-33120100603 | U60: 33120100603 | V60: 小儿经尿道前列腺电切术 | Y60: 次 | AA60: 4000 | AB60: 3600 | AC60: 3290 | AD60: 2965 | AE60: 2520 | AF60: =IFERROR(FIND("（加收）",C60,1),0) -> 0 | AG60: =IF(AF60>0,LEFT(C60,IFERROR(FIND("-",C60,1),1)-1),C60) -> 泌尿系镜下治疗费（特殊） | AH60: =IF(AF60>0,_xlfn.MAXIFS(N:N,C:C,AG60),0)+N60 -> 1875 | AI60: =IF(AF60>0,_xlfn.MAXIFS(O:O,C:C,AG60),0)+O60 -> 1700 | AJ60: =IF(AF60>0,_xlfn.MAXIFS(P:P,C:C,AG60),0)+P60 -> 1470
A61: 33 | B61: 013110000210000 | C61: 泌尿系镜下治疗费（特殊） | D61: 治疗费 | E61: 通过电凝、冷冻、蒸汽、射频、微波等各种物理方式对泌尿系统及男性生殖系统病灶进行治疗。 | F61: 所定价格涵盖消毒、下镜、治疗、取出、撤镜等步骤所需的人力资源和基本物质资源消耗。（不含泌尿系镜下检查） | G61: 次 | H61: 1.同一治疗位置使用多种能量源只可收取一次。 2.同时行常规治疗和特殊治疗的，按照“泌尿系镜下治疗费（特殊）”收取。 | I61: 1900 | J61: 1710 | K61: 2248.5461 | L61: 1514.4078 | M61: 1109.2737 | N61: 1875 | O61: 1700 | P61: 1470 | Q61: 医保 | R61: 理顺 | S61: 扣除原项目中涉及的内镜使用费用后加权平均，根据项目间比价关系，为常规的2.3倍。 | T61: 003312010060000-33120100604 | U61: 33120100604 | V61: 小儿经尿道前列腺电切术（电切法） | Y61: 次 | Z61: 电切法 | AA61: 5250 | AB61: 4720 | AC61: 4725 | AD61: 4250 | AE61: 3615 | AF61: =IFERROR(FIND("（加收）",C61,1),0) -> 0 | AG61: =IF(AF61>0,LEFT(C61,IFERROR(FIND("-",C61,1),1)-1),C61) -> 泌尿系镜下治疗费（特殊） | AH61: =IF(AF61>0,_xlfn.MAXIFS(N:N,C:C,AG61),0)+N61 -> 1875 | AI61: =IF(AF61>0,_xlfn.MAXIFS(O:O,C:C,AG61),0)+O61 -> 1700 | AJ61: =IF(AF61>0,_xlfn.MAXIFS(P:P,C:C,AG61),0)+P61 -> 1470
A62: 33 | B62: 013110000210000 | C62: 泌尿系镜下治疗费（特殊） | D62: 治疗费 | E62: 通过电凝、冷冻、蒸汽、射频、微波等各种物理方式对泌尿系统及男性生殖系统病灶进行治疗。 | F62: 所定价格涵盖消毒、下镜、治疗、取出、撤镜等步骤所需的人力资源和基本物质资源消耗。（不含泌尿系镜下检查） | G62: 次 | H62: 1.同一治疗位置使用多种能量源只可收取一次。 2.同时行常规治疗和特殊治疗的，按照“泌尿系镜下治疗费（特殊）”收取。 | I62: 1900 | J62: 1710 | K62: 2248.5461 | L62: 1514.4078 | M62: 1109.2737 | N62: 1875 | O62: 1700 | P62: 1470 | Q62: 医保 | R62: 理顺 | S62: 扣除原项目中涉及的内镜使用费用后加权平均，根据项目间比价关系，为常规的2.3倍。 | T62: 003312010060000-33120100605 | U62: 33120100605 | V62: 小儿经尿道前列腺电切术（等离子法） | Y62: 次 | Z62: 等离子法 | AA62: 5670 | AB62: 5090 | AC62: 4305 | AD62: 3875 | AE62: 3295 | AF62: =IFERROR(FIND("（加收）",C62,1),0) -> 0 | AG62: =IF(AF62>0,LEFT(C62,IFERROR(FIND("-",C62,1),1)-1),C62) -> 泌尿系镜下治疗费（特殊） | AH62: =IF(AF62>0,_xlfn.MAXIFS(N:N,C:C,AG62),0)+N62 -> 1875 | AI62: =IF(AF62>0,_xlfn.MAXIFS(O:O,C:C,AG62),0)+O62 -> 1700 | AJ62: =IF(AF62>0,_xlfn.MAXIFS(P:P,C:C,AG62),0)+P62 -> 1470
A63: 33 | B63: 013110000210000 | C63: 泌尿系镜下治疗费（特殊） | D63: 治疗费 | E63: 通过电凝、冷冻、蒸汽、射频、微波等各种物理方式对泌尿系统及男性生殖系统病灶进行治疗。 | F63: 所定价格涵盖消毒、下镜、治疗、取出、撤镜等步骤所需的人力资源和基本物质资源消耗。（不含泌尿系镜下检查） | G63: 次 | H63: 1.同一治疗位置使用多种能量源只可收取一次。 2.同时行常规治疗和特殊治疗的，按照“泌尿系镜下治疗费（特殊）”收取。 | I63: 1900 | J63: 1710 | K63: 2248.5461 | L63: 1514.4078 | M63: 1109.2737 | N63: 1875 | O63: 1700 | P63: 1470 | Q63: 医保 | R63: 理顺 | S63: 扣除原项目中涉及的内镜使用费用后加权平均，根据项目间比价关系，为常规的2.3倍。 | T63: 003312010060000-33120100606 | U63: 33120100606 | V63: 经膀胱镜经尿道前列腺电切术 | Y63: 次 | AA63: 3130 | AB63: 2815 | AC63: 2780 | AD63: 2505 | AE63: 2130 | AF63: =IFERROR(FIND("（加收）",C63,1),0) -> 0 | AG63: =IF(AF63>0,LEFT(C63,IFERROR(FIND("-",C63,1),1)-1),C63) -> 泌尿系镜下治疗费（特殊） | AH63: =IF(AF63>0,_xlfn.MAXIFS(N:N,C:C,AG63),0)+N63 -> 1875 | AI63: =IF(AF63>0,_xlfn.MAXIFS(O:O,C:C,AG63),0)+O63 -> 1700 | AJ63: =IF(AF63>0,_xlfn.MAXIFS(P:P,C:C,AG63),0)+P63 -> 1470
A64: 33 | B64: 013110000210000 | C64: 泌尿系镜下治疗费（特殊） | D64: 治疗费 | E64: 通过电凝、冷冻、蒸汽、射频、微波等各种物理方式对泌尿系统及男性生殖系统病灶进行治疗。 | F64: 所定价格涵盖消毒、下镜、治疗、取出、撤镜等步骤所需的人力资源和基本物质资源消耗。（不含泌尿系镜下检查） | G64: 次 | H64: 1.同一治疗位置使用多种能量源只可收取一次。 2.同时行常规治疗和特殊治疗的，按照“泌尿系镜下治疗费（特殊）”收取。 | I64: 1900 | J64: 1710 | K64: 2248.5461 | L64: 1514.4078 | M64: 1109.2737 | N64: 1875 | O64: 1700 | P64: 1470 | Q64: 医保 | R64: 理顺 | S64: 扣除原项目中涉及的内镜使用费用后加权平均，根据项目间比价关系，为常规的2.3倍。 | T64: 003312010060000-33120100607 | U64: 33120100607 | V64: 经膀胱镜经尿道前列腺电切术（电切法） | Y64: 次 | Z64: 电切法 | AA64: 4090 | AB64: 3675 | AC64: 3270 | AD64: 2945 | AE64: 2500 | AF64: =IFERROR(FIND("（加收）",C64,1),0) -> 0 | AG64: =IF(AF64>0,LEFT(C64,IFERROR(FIND("-",C64,1),1)-1),C64) -> 泌尿系镜下治疗费（特殊） | AH64: =IF(AF64>0,_xlfn.MAXIFS(N:N,C:C,AG64),0)+N64 -> 1875 | AI64: =IF(AF64>0,_xlfn.MAXIFS(O:O,C:C,AG64),0)+O64 -> 1700 | AJ64: =IF(AF64>0,_xlfn.MAXIFS(P:P,C:C,AG64),0)+P64 -> 1470
A65: 33 | B65: 013110000210000 | C65: 泌尿系镜下治疗费（特殊） | D65: 治疗费 | E65: 通过电凝、冷冻、蒸汽、射频、微波等各种物理方式对泌尿系统及男性生殖系统病灶进行治疗。 | F65: 所定价格涵盖消毒、下镜、治疗、取出、撤镜等步骤所需的人力资源和基本物质资源消耗。（不含泌尿系镜下检查） | G65: 次 | H65: 1.同一治疗位置使用多种能量源只可收取一次。 2.同时行常规治疗和特殊治疗的，按照“泌尿系镜下治疗费（特殊）”收取。 | I65: 1900 | J65: 1710 | K65: 2248.5461 | L65: 1514.4078 | M65: 1109.2737 | N65: 1875 | O65: 1700 | P65: 1470 | Q65: 医保 | R65: 理顺 | S65: 扣除原项目中涉及的内镜使用费用后加权平均，根据项目间比价关系，为常规的2.3倍。 | T65: 003312010060000-33120100608 | U65: 33120100608 | V65: 经膀胱镜经尿道前列腺电切术（等离子法） | Y65: 次 | Z65: 等离子法 | AA65: 4410 | AB65: 3965 | AC65: 3560 | AD65: 3205 | AE65: 2720 | AF65: =IFERROR(FIND("（加收）",C65,1),0) -> 0 | AG65: =IF(AF65>0,LEFT(C65,IFERROR(FIND("-",C65,1),1)-1),C65) -> 泌尿系镜下治疗费（特殊） | AH65: =IF(AF65>0,_xlfn.MAXIFS(N:N,C:C,AG65),0)+N65 -> 1875 | AI65: =IF(AF65>0,_xlfn.MAXIFS(O:O,C:C,AG65),0)+O65 -> 1700 | AJ65: =IF(AF65>0,_xlfn.MAXIFS(P:P,C:C,AG65),0)+P65 -> 1470
A66: 33 | B66: 013110000210000 | C66: 泌尿系镜下治疗费（特殊） | D66: 治疗费 | E66: 通过电凝、冷冻、蒸汽、射频、微波等各种物理方式对泌尿系统及男性生殖系统病灶进行治疗。 | F66: 所定价格涵盖消毒、下镜、治疗、取出、撤镜等步骤所需的人力资源和基本物质资源消耗。（不含泌尿系镜下检查） | G66: 次 | H66: 1.同一治疗位置使用多种能量源只可收取一次。 2.同时行常规治疗和特殊治疗的，按照“泌尿系镜下治疗费（特殊）”收取。 | I66: 1900 | J66: 1710 | K66: 2248.5461 | L66: 1514.4078 | M66: 1109.2737 | N66: 1875 | O66: 1700 | P66: 1470 | Q66: 医保 | R66: 理顺 | S66: 扣除原项目中涉及的内镜使用费用后加权平均，根据项目间比价关系，为常规的2.3倍。 | T66: 003312010060000-33120100609 | U66: 33120100609 | V66: 小儿经膀胱镜经尿道前列腺电切术 | Y66: 次 | AA66: 3995 | AB66: 3590 | AC66: 3540 | AD66: 3190 | AE66: 2710 | AF66: =IFERROR(FIND("（加收）",C66,1),0) -> 0 | AG66: =IF(AF66>0,LEFT(C66,IFERROR(FIND("-",C66,1),1)-1),C66) -> 泌尿系镜下治疗费（特殊） | AH66: =IF(AF66>0,_xlfn.MAXIFS(N:N,C:C,AG66),0)+N66 -> 1875 | AI66: =IF(AF66>0,_xlfn.MAXIFS(O:O,C:C,AG66),0)+O66 -> 1700 | AJ66: =IF(AF66>0,_xlfn.MAXIFS(P:P,C:C,AG66),0)+P66 -> 1470
A67: 33 | B67: 013110000210000 | C67: 泌尿系镜下治疗费（特殊） | D67: 治疗费 | E67: 通过电凝、冷冻、蒸汽、射频、微波等各种物理方式对泌尿系统及男性生殖系统病灶进行治疗。 | F67: 所定价格涵盖消毒、下镜、治疗、取出、撤镜等步骤所需的人力资源和基本物质资源消耗。（不含泌尿系镜下检查） | G67: 次 | H67: 1.同一治疗位置使用多种能量源只可收取一次。 2.同时行常规治疗和特殊治疗的，按照“泌尿系镜下治疗费（特殊）”收取。 | I67: 1900 | J67: 1710 | K67: 2248.5461 | L67: 1514.4078 | M67: 1109.2737 | N67: 1875 | O67: 1700 | P67: 1470 | Q67: 医保 | R67: 理顺 | S67: 扣除原项目中涉及的内镜使用费用后加权平均，根据项目间比价关系，为常规的2.3倍。 | T67: 003312010060000-33120100610 | U67: 33120100610 | V67: 小儿经膀胱镜经尿道前列腺电切术（电切法） | Y67: 次 | Z67: 电切法 | AA67: 5240 | AB67: 4710 | AC67: 4175 | AD67: 3760 | AE67: 3195 | AF67: =IFERROR(FIND("（加收）",C67,1),0) -> 0 | AG67: =IF(AF67>0,LEFT(C67,IFERROR(FIND("-",C67,1),1)-1),C67) -> 泌尿系镜下治疗费（特殊） | AH67: =IF(AF67>0,_xlfn.MAXIFS(N:N,C:C,AG67),0)+N67 -> 1875 | AI67: =IF(AF67>0,_xlfn.MAXIFS(O:O,C:C,AG67),0)+O67 -> 1700 | AJ67: =IF(AF67>0,_xlfn.MAXIFS(P:P,C:C,AG67),0)+P67 -> 1470
A68: 33 | B68: 013110000210000 | C68: 泌尿系镜下治疗费（特殊） | D68: 治疗费 | E68: 通过电凝、冷冻、蒸汽、射频、微波等各种物理方式对泌尿系统及男性生殖系统病灶进行治疗。 | F68: 所定价格涵盖消毒、下镜、治疗、取出、撤镜等步骤所需的人力资源和基本物质资源消耗。（不含泌尿系镜下检查） | G68: 次 | H68: 1.同一治疗位置使用多种能量源只可收取一次。 2.同时行常规治疗和特殊治疗的，按照“泌尿系镜下治疗费（特殊）”收取。 | I68: 1900 | J68: 1710 | K68: 2248.5461 | L68: 1514.4078 | M68: 1109.2737 | N68: 1875 | O68: 1700 | P68: 1470 | Q68: 医保 | R68: 理顺 | S68: 扣除原项目中涉及的内镜使用费用后加权平均，根据项目间比价关系，为常规的2.3倍。 | T68: 003312010060000-33120100611 | U68: 33120100611 | V68: 小儿经膀胱镜经尿道前列腺电切术（等离子法） | Y68: 次 | Z68: 等离子法 | AA68: 5660 | AB68: 5085 | AC68: 4555 | AD68: 4100 | AE68: 3485 | AF68: =IFERROR(FIND("（加收）",C68,1),0) -> 0 | AG68: =IF(AF68>0,LEFT(C68,IFERROR(FIND("-",C68,1),1)-1),C68) -> 泌尿系镜下治疗费（特殊） | AH68: =IF(AF68>0,_xlfn.MAXIFS(N:N,C:C,AG68),0)+N68 -> 1875 | AI68: =IF(AF68>0,_xlfn.MAXIFS(O:O,C:C,AG68),0)+O68 -> 1700 | AJ68: =IF(AF68>0,_xlfn.MAXIFS(P:P,C:C,AG68),0)+P68 -> 1470
A69: 33 | B69: 013110000210000 | C69: 泌尿系镜下治疗费（特殊） | D69: 治疗费 | E69: 通过电凝、冷冻、蒸汽、射频、微波等各种物理方式对泌尿系统及男性生殖系统病灶进行治疗。 | F69: 所定价格涵盖消毒、下镜、治疗、取出、撤镜等步骤所需的人力资源和基本物质资源消耗。（不含泌尿系镜下检查） | G69: 次 | H69: 1.同一治疗位置使用多种能量源只可收取一次。 2.同时行常规治疗和特殊治疗的，按照“泌尿系镜下治疗费（特殊）”收取。 | I69: 1900 | J69: 1710 | K69: 2248.5461 | L69: 1514.4078 | M69: 1109.2737 | N69: 1875 | O69: 1700 | P69: 1470 | Q69: 医保 | R69: 理顺 | S69: 扣除原项目中涉及的内镜使用费用后加权平均，根据项目间比价关系，为常规的2.3倍。 | T69: 003312010060000-331201010 | U69: 331201010 | V69: 经尿道前列腺激光切除术 | W69: 会阴区消毒，尿道润滑，尿道膀胱镜检查，使用激光纤维，剜除前列腺组织，止血，膀胱冲洗，取出前列腺组织，留置尿管。 | Y69: 次 | AA69: 4500 | AB69: 4050 | AC69: 4500 | AD69: 4500 | AE69: 3825 | AF69: =IFERROR(FIND("（加收）",C69,1),0) -> 0 | AG69: =IF(AF69>0,LEFT(C69,IFERROR(FIND("-",C69,1),1)-1),C69) -> 泌尿系镜下治疗费（特殊） | AH69: =IF(AF69>0,_xlfn.MAXIFS(N:N,C:C,AG69),0)+N69 -> 1875 | AI69: =IF(AF69>0,_xlfn.MAXIFS(O:O,C:C,AG69),0)+O69 -> 1700 | AJ69: =IF(AF69>0,_xlfn.MAXIFS(P:P,C:C,AG69),0)+P69 -> 1470
A70: 33 | B70: 013110000210000 | C70: 泌尿系镜下治疗费（特殊） | D70: 治疗费 | E70: 通过电凝、冷冻、蒸汽、射频、微波等各种物理方式对泌尿系统及男性生殖系统病灶进行治疗。 | F70: 所定价格涵盖消毒、下镜、治疗、取出、撤镜等步骤所需的人力资源和基本物质资源消耗。（不含泌尿系镜下检查） | G70: 次 | H70: 1.同一治疗位置使用多种能量源只可收取一次。 2.同时行常规治疗和特殊治疗的，按照“泌尿系镜下治疗费（特殊）”收取。 | I70: 1900 | J70: 1710 | K70: 2248.5461 | L70: 1514.4078 | M70: 1109.2737 | N70: 1875 | O70: 1700 | P70: 1470 | Q70: 医保 | R70: 理顺 | S70: 扣除原项目中涉及的内镜使用费用后加权平均，根据项目间比价关系，为常规的2.3倍。 | T70: 353312030150100-331203015 | U70: 331203015 | V70: 经精囊镜碎石取石术（激光法） | W70: 消毒，取Wolf4.5/6.5精囊镜连接电视成像系统，以生理盐水为灌注液，直视下将精囊镜经尿道置入膀胱，观察尿道、膀胱，将镜体退至精阜处，仔细观察射精管口，发现射精管口后稍加大灌注液速度，轻柔的将镜体置入一侧射精管内，将镜体逐渐推进精囊内，连接激光设备，用激光将结石逐一击碎并用取石钳夹出、套石篮取出或生理盐水冲出结石。含斑马导丝。 | Y70: 侧 | Z70: 激光法 | AA70: 2300 | AC70: 2070 | AD70: 1863 | AE70: 1583.6 | AF70: =IFERROR(FIND("（加收）",C70,1),0) -> 0 | AG70: =IF(AF70>0,LEFT(C70,IFERROR(FIND("-",C70,1),1)-1),C70) -> 泌尿系镜下治疗费（特殊） | AH70: =IF(AF70>0,_xlfn.MAXIFS(N:N,C:C,AG70),0)+N70 -> 1875 | AI70: =IF(AF70>0,_xlfn.MAXIFS(O:O,C:C,AG70),0)+O70 -> 1700 | AJ70: =IF(AF70>0,_xlfn.MAXIFS(P:P,C:C,AG70),0)+P70 -> 1470
A71: 33 | B71: 013110000210000 | C71: 泌尿系镜下治疗费（特殊） | D71: 治疗费 | E71: 通过电凝、冷冻、蒸汽、射频、微波等各种物理方式对泌尿系统及男性生殖系统病灶进行治疗。 | F71: 所定价格涵盖消毒、下镜、治疗、取出、撤镜等步骤所需的人力资源和基本物质资源消耗。（不含泌尿系镜下检查） | G71: 次 | H71: 1.同一治疗位置使用多种能量源只可收取一次。 2.同时行常规治疗和特殊治疗的，按照“泌尿系镜下治疗费（特殊）”收取。 | I71: 1900 | J71: 1710 | K71: 2248.5461 | L71: 1514.4078 | M71: 1109.2737 | N71: 1875 | O71: 1700 | P71: 1470 | Q71: 医保 | R71: 理顺 | S71: 扣除原项目中涉及的内镜使用费用后加权平均，根据项目间比价关系，为常规的2.3倍。 | T71: 353312030150200-331203016 | U71: 331203016 | V71: 经精囊镜碎石取石术（弹道法） | W71: 消毒，取Wolf4.5/6.5精囊镜连接电视成像系统，以生理盐水为灌注液，直视下将精囊镜经尿道置入膀胱，观察尿道、膀胱，将镜体退至精阜处，仔细观察射精管口，发现射精管口后稍加大灌注液速度，轻柔的将镜体置入一侧射精管内，将镜体逐渐推进精囊内，连接气压弹道碎石设备，用探针将结石逐一击碎并用取石钳夹出、套石篮取出或生理盐水冲出结石。含斑马导丝。 | Y71: 侧 | Z71: 弹道法 | AA71: 1600 | AC71: 1440 | AD71: 1296 | AE71: 1101.6 | AF71: =IFERROR(FIND("（加收）",C71,1),0) -> 0 | AG71: =IF(AF71>0,LEFT(C71,IFERROR(FIND("-",C71,1),1)-1),C71) -> 泌尿系镜下治疗费（特殊） | AH71: =IF(AF71>0,_xlfn.MAXIFS(N:N,C:C,AG71),0)+N71 -> 1875 | AI71: =IF(AF71>0,_xlfn.MAXIFS(O:O,C:C,AG71),0)+O71 -> 1700 | AJ71: =IF(AF71>0,_xlfn.MAXIFS(P:P,C:C,AG71),0)+P71 -> 1470
A72: 33 | B72: 013110000210000 | C72: 泌尿系镜下治疗费（特殊） | D72: 治疗费 | E72: 通过电凝、冷冻、蒸汽、射频、微波等各种物理方式对泌尿系统及男性生殖系统病灶进行治疗。 | F72: 所定价格涵盖消毒、下镜、治疗、取出、撤镜等步骤所需的人力资源和基本物质资源消耗。（不含泌尿系镜下检查） | G72: 次 | H72: 1.同一治疗位置使用多种能量源只可收取一次。 2.同时行常规治疗和特殊治疗的，按照“泌尿系镜下治疗费（特殊）”收取。 | I72: 1900 | J72: 1710 | K72: 2248.5461 | L72: 1514.4078 | M72: 1109.2737 | N72: 1875 | O72: 1700 | P72: 1470 | Q72: 医保 | R72: 理顺 | S72: 扣除原项目中涉及的内镜使用费用后加权平均，根据项目间比价关系，为常规的2.3倍。 | T72: 353312030150300-331203017 | U72: 331203017 | V72: 经精囊镜碎石取石术（直接法） | W72: 消毒，取Wolf4.5/6.5精囊镜连接电视成像系统，以生理盐水为灌注液，直视下将精囊镜经尿道置入膀胱，观察尿道、膀胱，将镜体退至精阜处，仔细观察射精管口，发现射精管口后稍加大灌注液速度，轻柔的将镜体置入一侧射精管内，将镜体逐渐推进精囊内，将结石用取石钳夹出、套石篮取出或生理盐水冲出结石。含斑马导丝。 | Y72: 侧 | Z72: 直接法 | AA72: 1400 | AC72: 1260 | AD72: 1134 | AE72: 963.9 | AF72: =IFERROR(FIND("（加收）",C72,1),0) -> 0 | AG72: =IF(AF72>0,LEFT(C72,IFERROR(FIND("-",C72,1),1)-1),C72) -> 泌尿系镜下治疗费（特殊） | AH72: =IF(AF72>0,_xlfn.MAXIFS(N:N,C:C,AG72),0)+N72 -> 1875 | AI72: =IF(AF72>0,_xlfn.MAXIFS(O:O,C:C,AG72),0)+O72 -> 1700 | AJ72: =IF(AF72>0,_xlfn.MAXIFS(P:P,C:C,AG72),0)+P72 -> 1470
A73: 33 | B73: 013110000210000 | C73: 泌尿系镜下治疗费（特殊） | D73: 治疗费 | E73: 通过电凝、冷冻、蒸汽、射频、微波等各种物理方式对泌尿系统及男性生殖系统病灶进行治疗。 | F73: 所定价格涵盖消毒、下镜、治疗、取出、撤镜等步骤所需的人力资源和基本物质资源消耗。（不含泌尿系镜下检查） | G73: 次 | H73: 1.同一治疗位置使用多种能量源只可收取一次。 2.同时行常规治疗和特殊治疗的，按照“泌尿系镜下治疗费（特殊）”收取。 | I73: 1900 | J73: 1710 | K73: 2248.5461 | L73: 1514.4078 | M73: 1109.2737 | N73: 1875 | O73: 1700 | P73: 1470 | Q73: 医保 | R73: 理顺 | S73: 扣除原项目中涉及的内镜使用费用后加权平均，根据项目间比价关系，为常规的2.3倍。 | T73: 353312040150000-331204020 | U73: 331204020 | V73: 经精囊镜肿物切除术 | W73: 消毒，取Wolf4.5/6.5精囊镜连接电视成像系统，以生理盐水为灌注液，直视下将精囊镜经尿道置入膀胱，观察尿道、膀胱，将镜体退至精阜处，仔细观察射精管口，发现射精管口后稍加大灌注液速度，轻柔的将镜体置入一侧射精管内，连接激光设备，激光下电灼或切除肿物、囊肿壁等。含斑马导丝。 | Y73: 侧 | AA73: 2300 | AC73: 2070 | AD73: 1863 | AE73: 1583.6 | AF73: =IFERROR(FIND("（加收）",C73,1),0) -> 0 | AG73: =IF(AF73>0,LEFT(C73,IFERROR(FIND("-",C73,1),1)-1),C73) -> 泌尿系镜下治疗费（特殊） | AH73: =IF(AF73>0,_xlfn.MAXIFS(N:N,C:C,AG73),0)+N73 -> 1875 | AI73: =IF(AF73>0,_xlfn.MAXIFS(O:O,C:C,AG73),0)+O73 -> 1700 | AJ73: =IF(AF73>0,_xlfn.MAXIFS(P:P,C:C,AG73),0)+P73 -> 1470
A74: 33 | B74: 013110000210000 | C74: 泌尿系镜下治疗费（特殊） | D74: 治疗费 | E74: 通过电凝、冷冻、蒸汽、射频、微波等各种物理方式对泌尿系统及男性生殖系统病灶进行治疗。 | F74: 所定价格涵盖消毒、下镜、治疗、取出、撤镜等步骤所需的人力资源和基本物质资源消耗。（不含泌尿系镜下检查） | G74: 次 | H74: 1.同一治疗位置使用多种能量源只可收取一次。 2.同时行常规治疗和特殊治疗的，按照“泌尿系镜下治疗费（特殊）”收取。 | I74: 1900 | J74: 1710 | K74: 2248.5461 | L74: 1514.4078 | M74: 1109.2737 | N74: 1875 | O74: 1700 | P74: 1470 | Q74: 医保 | R74: 理顺 | S74: 扣除原项目中涉及的内镜使用费用后加权平均，根据项目间比价关系，为常规的2.3倍。 | T74: 353312040150000-33120402001 | U74: 33120402001 | V74: 小儿经精囊镜肿物切除术 | Y74: 侧 | AA74: 2990 | AC74: 2690 | AD74: 2420 | AE74: 2055 | AF74: =IFERROR(FIND("（加收）",C74,1),0) -> 0 | AG74: =IF(AF74>0,LEFT(C74,IFERROR(FIND("-",C74,1),1)-1),C74) -> 泌尿系镜下治疗费（特殊） | AH74: =IF(AF74>0,_xlfn.MAXIFS(N:N,C:C,AG74),0)+N74 -> 1875 | AI74: =IF(AF74>0,_xlfn.MAXIFS(O:O,C:C,AG74),0)+O74 -> 1700 | AJ74: =IF(AF74>0,_xlfn.MAXIFS(P:P,C:C,AG74),0)+P74 -> 1470
A75: 33 | B75: 013110000210000 | C75: 泌尿系镜下治疗费（特殊） | D75: 治疗费 | E75: 通过电凝、冷冻、蒸汽、射频、微波等各种物理方式对泌尿系统及男性生殖系统病灶进行治疗。 | F75: 所定价格涵盖消毒、下镜、治疗、取出、撤镜等步骤所需的人力资源和基本物质资源消耗。（不含泌尿系镜下检查） | G75: 次 | H75: 1.同一治疗位置使用多种能量源只可收取一次。 2.同时行常规治疗和特殊治疗的，按照“泌尿系镜下治疗费（特殊）”收取。 | I75: 1900 | J75: 1710 | K75: 2248.5461 | L75: 1514.4078 | M75: 1109.2737 | N75: 1875 | O75: 1700 | P75: 1470 | Q75: 医保 | R75: 理顺 | S75: 扣除原项目中涉及的内镜使用费用后加权平均，根据项目间比价关系，为常规的2.3倍。 | T75: 353110000440000-A331203018 | U75: A331203018 | V75: 经皮肾镜碎石取石术 | W75: 包括气压弹道法、超声碎石法、激光碎石法。 | X75: 导管、导丝、支架 | Y75: 次 | Z75: 两种及以上方法加收20% | AC75: 自主 定价 | AD75: 自主 定价 | AE75: 自主 定价 | AF75: =IFERROR(FIND("（加收）",C75,1),0) -> 0 | AG75: =IF(AF75>0,LEFT(C75,IFERROR(FIND("-",C75,1),1)-1),C75) -> 泌尿系镜下治疗费（特殊） | AH75: =IF(AF75>0,_xlfn.MAXIFS(N:N,C:C,AG75),0)+N75 -> 1875 | AI75: =IF(AF75>0,_xlfn.MAXIFS(O:O,C:C,AG75),0)+O75 -> 1700 | AJ75: =IF(AF75>0,_xlfn.MAXIFS(P:P,C:C,AG75),0)+P75 -> 1470
A76: 33 | B76: 013110000210000 | C76: 泌尿系镜下治疗费（特殊） | D76: 治疗费 | E76: 通过电凝、冷冻、蒸汽、射频、微波等各种物理方式对泌尿系统及男性生殖系统病灶进行治疗。 | F76: 所定价格涵盖消毒、下镜、治疗、取出、撤镜等步骤所需的人力资源和基本物质资源消耗。（不含泌尿系镜下检查） | G76: 次 | H76: 1.同一治疗位置使用多种能量源只可收取一次。 2.同时行常规治疗和特殊治疗的，按照“泌尿系镜下治疗费（特殊）”收取。 | I76: 1900 | J76: 1710 | K76: 2248.5461 | L76: 1514.4078 | M76: 1109.2737 | N76: 1875 | O76: 1700 | P76: 1470 | Q76: 医保 | R76: 理顺 | S76: 扣除原项目中涉及的内镜使用费用后加权平均，根据项目间比价关系，为常规的2.3倍。 | T76: 353110000440000-A33120301801 | U76: A33120301801 | V76: 经皮肾镜碎石取石术（两种及以上方法加收20%） | Y76: 次 | Z76: 两种及以上方法加收20% | AC76: 自主 定价 | AD76: 自主 定价 | AE76: 自主 定价 | AF76: =IFERROR(FIND("（加收）",C76,1),0) -> 0 | AG76: =IF(AF76>0,LEFT(C76,IFERROR(FIND("-",C76,1),1)-1),C76) -> 泌尿系镜下治疗费（特殊） | AH76: =IF(AF76>0,_xlfn.MAXIFS(N:N,C:C,AG76),0)+N76 -> 1875 | AI76: =IF(AF76>0,_xlfn.MAXIFS(O:O,C:C,AG76),0)+O76 -> 1700 | AJ76: =IF(AF76>0,_xlfn.MAXIFS(P:P,C:C,AG76),0)+P76 -> 1470
A77: 34 | B77: 013311000040000 | C77: 泌尿系异物取出费 | D77: 手术费 | E77: 通过手术从下尿路取出异物。 | F77: 所定价格涵盖手术计划、术区准备、消毒、取出异物、缝合、处理用物等步骤所需的人力资源和基本物质资源消耗。 | G77: 次 | I77: 1220 | J77: 1100 | K77: 1125 | L77: 1080 | M77: 918 | N77: 1125 | O77: 1080 | P77: 918 | Q77: 医保 | R77: 平移 | S77: 平移 | T77: 003311040050000-331104005 | U77: 331104005 | V77: 尿道切开取石术 | W77: 包括前后尿道及取异物术 | Y77: 次 | AA77: 1220 | AB77: 1090 | AC77: 1125 | AD77: 1080 | AE77: 918 | AF77: =IFERROR(FIND("（加收）",C77,1),0) -> 0 | AG77: =IF(AF77>0,LEFT(C77,IFERROR(FIND("-",C77,1),1)-1),C77) -> 泌尿系异物取出费 | AH77: =IF(AF77>0,_xlfn.MAXIFS(N:N,C:C,AG77),0)+N77 -> 1125 | AI77: =IF(AF77>0,_xlfn.MAXIFS(O:O,C:C,AG77),0)+O77 -> 1080 | AJ77: =IF(AF77>0,_xlfn.MAXIFS(P:P,C:C,AG77),0)+P77 -> 918
A78: 35 | B78: 013311000050000 | C78: 泌尿系取石费 | D78: 手术费 | E78: 通过手术从下尿路取出结石。 | F78: 所定价格涵盖手术计划、术区准备、消毒、取石、缝合、处理用物等步骤所需的人力资源和基本物质资源消耗。 | G78: 次 | I78: 1350 | J78: 1215 | K78: 1000 | L78: 986.66667 | M78: 918 | N78: 1250 | O78: 1200 | P78: 1020 | Q78: 医保 | R78: 理顺，提高 | S78: 加权平均后，根据项目间比价关系，理顺项目价格（泌尿系异物取出费为该项目的90%） | T78: 003311030010000-331103001 | U78: 331103001 | V78: 膀胱切开取石术 | Y78: 次 | AA78: 1000 | AB78: 900 | AC78: 1000 | AD78: 960 | AE78: 816 | AF78: =IFERROR(FIND("（加收）",C78,1),0) -> 0 | AG78: =IF(AF78>0,LEFT(C78,IFERROR(FIND("-",C78,1),1)-1),C78) -> 泌尿系取石费 | AH78: =IF(AF78>0,_xlfn.MAXIFS(N:N,C:C,AG78),0)+N78 -> 1250 | AI78: =IF(AF78>0,_xlfn.MAXIFS(O:O,C:C,AG78),0)+O78 -> 1200 | AJ78: =IF(AF78>0,_xlfn.MAXIFS(P:P,C:C,AG78),0)+P78 -> 1020
A79: 35 | B79: 013311000050000 | C79: 泌尿系取石费 | D79: 手术费 | E79: 通过手术从下尿路取出结石。 | F79: 所定价格涵盖手术计划、术区准备、消毒、取石、缝合、处理用物等步骤所需的人力资源和基本物质资源消耗。 | G79: 次 | I79: 1350 | J79: 1215 | K79: 1000 | L79: 986.66667 | M79: 918 | N79: 1250 | O79: 1200 | P79: 1020 | Q79: 医保 | R79: 理顺，提高 | S79: 加权平均后，根据项目间比价关系，理顺项目价格（泌尿系异物取出费为该项目的90%） | T79: 003311030010000-33110300102 | U79: 33110300102 | V79: 经腹腔镜膀胱切开取石术 | Y79: 次 | AA79: 1800 | AB79: 1620 | AC79: 1625 | AD79: 1560 | AE79: 1326 | AF79: =IFERROR(FIND("（加收）",C79,1),0) -> 0 | AG79: =IF(AF79>0,LEFT(C79,IFERROR(FIND("-",C79,1),1)-1),C79) -> 泌尿系取石费 | AH79: =IF(AF79>0,_xlfn.MAXIFS(N:N,C:C,AG79),0)+N79 -> 1250 | AI79: =IF(AF79>0,_xlfn.MAXIFS(O:O,C:C,AG79),0)+O79 -> 1200 | AJ79: =IF(AF79>0,_xlfn.MAXIFS(P:P,C:C,AG79),0)+P79 -> 1020
A80: 35 | B80: 013311000050000 | C80: 泌尿系取石费 | D80: 手术费 | E80: 通过手术从下尿路取出结石。 | F80: 所定价格涵盖手术计划、术区准备、消毒、取石、缝合、处理用物等步骤所需的人力资源和基本物质资源消耗。 | G80: 次 | I80: 1350 | J80: 1215 | K80: 1000 | L80: 986.66667 | M80: 918 | N80: 1250 | O80: 1200 | P80: 1020 | Q80: 医保 | R80: 理顺，提高 | S80: 加权平均后，根据项目间比价关系，理顺项目价格（泌尿系异物取出费为该项目的90%） | T80: 003311040050000-331104005 | U80: 331104005 | V80: 尿道切开取石术 | W80: 包括前后尿道及取异物术 | Y80: 次 | AA80: 1220 | AB80: 1090 | AC80: 1125 | AD80: 1080 | AE80: 918 | AF80: =IFERROR(FIND("（加收）",C80,1),0) -> 0 | AG80: =IF(AF80>0,LEFT(C80,IFERROR(FIND("-",C80,1),1)-1),C80) -> 泌尿系取石费 | AH80: =IF(AF80>0,_xlfn.MAXIFS(N:N,C:C,AG80),0)+N80 -> 1250 | AI80: =IF(AF80>0,_xlfn.MAXIFS(O:O,C:C,AG80),0)+O80 -> 1200 | AJ80: =IF(AF80>0,_xlfn.MAXIFS(P:P,C:C,AG80),0)+P80 -> 1020
A81: 35 | B81: 013311000050000 | C81: 泌尿系取石费 | D81: 手术费 | E81: 通过手术从下尿路取出结石。 | F81: 所定价格涵盖手术计划、术区准备、消毒、取石、缝合、处理用物等步骤所需的人力资源和基本物质资源消耗。 | G81: 次 | I81: 1350 | J81: 1215 | K81: 1000 | L81: 986.66667 | M81: 918 | N81: 1250 | O81: 1200 | P81: 1020 | Q81: 医保 | R81: 理顺，提高 | S81: 加权平均后，根据项目间比价关系，理顺项目价格（泌尿系异物取出费为该项目的90%） | T81: 003311040050000-33110400502 | U81: 33110400502 | V81: 经膀胱镜尿道切开取石术 | Y81: 次 | AA81: 1470 | AB81: 1315 | AC81: 1375 | AD81: 1305 | AE81: 1108 | AF81: =IFERROR(FIND("（加收）",C81,1),0) -> 0 | AG81: =IF(AF81>0,LEFT(C81,IFERROR(FIND("-",C81,1),1)-1),C81) -> 泌尿系取石费 | AH81: =IF(AF81>0,_xlfn.MAXIFS(N:N,C:C,AG81),0)+N81 -> 1250 | AI81: =IF(AF81>0,_xlfn.MAXIFS(O:O,C:C,AG81),0)+O81 -> 1200 | AJ81: =IF(AF81>0,_xlfn.MAXIFS(P:P,C:C,AG81),0)+P81 -> 1020
A82: 分项 | B82: 013311000050001 | C82: 泌尿系取石费-上尿路（加收） | D82: 手术费 | G82: 次 | H82: 本项目中的“上尿路”指：肾脏及输尿管。 | I82: 1265 | J82: 1139 | K82: 1224.3925 | L82: 962.92683 | M82: 280 | N82: 1170 | O82: 1120 | P82: 950 | Q82: 医保 | S82: 加权平均后扣除主项拟定价格得到平移价格，根据项目间比价理顺项目价格。 | T82: 003311010160000-331101016 | U82: 331101016 | V82: 肾切开取石术 | W82: 包括肾盂切开、肾实质切开 | Y82: 次 | AA82: 2880 | AB82: 2590 | AC82: 2530 | AD82: 2280 | AE82: 1940 | AF82: =IFERROR(FIND("（加收）",C82,1),0) -> 11 | AG82: =IF(AF82>0,LEFT(C82,IFERROR(FIND("-",C82,1),1)-1),C82) -> 泌尿系取石费 | AH82: =IF(AF82>0,_xlfn.MAXIFS(N:N,C:C,AG82),0)+N82 -> 2420 | AI82: =IF(AF82>0,_xlfn.MAXIFS(O:O,C:C,AG82),0)+O82 -> 2320 | AJ82: =IF(AF82>0,_xlfn.MAXIFS(P:P,C:C,AG82),0)+P82 -> 1970
A83: 分项 | B83: 013311000050001 | C83: 泌尿系取石费-上尿路（加收） | D83: 手术费 | G83: 次 | H83: 本项目中的“上尿路”指：肾脏及输尿管。 | I83: 1265 | J83: 1139 | K83: 1224.3925 | L83: 962.92683 | M83: 280 | N83: 1170 | O83: 1120 | P83: 950 | Q83: 医保 | S83: 加权平均后扣除主项拟定价格得到平移价格，根据项目间比价理顺项目价格。 | T83: 003311010160000-33110101601 | U83: 33110101601 | V83: 小儿肾切开取石术 | Y83: 次 | AA83: 3745 | AB83: 3365 | AC83: 3290 | AD83: 2965 | AE83: 2520 | AF83: =IFERROR(FIND("（加收）",C83,1),0) -> 11 | AG83: =IF(AF83>0,LEFT(C83,IFERROR(FIND("-",C83,1),1)-1),C83) -> 泌尿系取石费 | AH83: =IF(AF83>0,_xlfn.MAXIFS(N:N,C:C,AG83),0)+N83 -> 2420 | AI83: =IF(AF83>0,_xlfn.MAXIFS(O:O,C:C,AG83),0)+O83 -> 2320 | AJ83: =IF(AF83>0,_xlfn.MAXIFS(P:P,C:C,AG83),0)+P83 -> 1970
A84: 分项 | B84: 013311000050001 | C84: 泌尿系取石费-上尿路（加收） | D84: 手术费 | G84: 次 | H84: 本项目中的“上尿路”指：肾脏及输尿管。 | I84: 1265 | J84: 1139 | K84: 1224.3925 | L84: 962.92683 | M84: 280 | N84: 1170 | O84: 1120 | P84: 950 | Q84: 医保 | S84: 加权平均后扣除主项拟定价格得到平移价格，根据项目间比价理顺项目价格。 | T84: 003311010160000-33110101602 | U84: 33110101602 | V84: 经腹腔镜肾切开取石术 | Y84: 次 | AA84: 3680 | AB84: 3310 | AC84: 3155 | AD84: 2880 | AE84: 2450 | AF84: =IFERROR(FIND("（加收）",C84,1),0) -> 11 | AG84: =IF(AF84>0,LEFT(C84,IFERROR(FIND("-",C84,1),1)-1),C84) -> 泌尿系取石费 | AH84: =IF(AF84>0,_xlfn.MAXIFS(N:N,C:C,AG84),0)+N84 -> 2420 | AI84: =IF(AF84>0,_xlfn.MAXIFS(O:O,C:C,AG84),0)+O84 -> 2320 | AJ84: =IF(AF84>0,_xlfn.MAXIFS(P:P,C:C,AG84),0)+P84 -> 1970
A85: 分项 | B85: 013311000050001 | C85: 泌尿系取石费-上尿路（加收） | D85: 手术费 | G85: 次 | H85: 本项目中的“上尿路”指：肾脏及输尿管。 | I85: 1265 | J85: 1139 | K85: 1224.3925 | L85: 962.92683 | M85: 280 | N85: 1170 | O85: 1120 | P85: 950 | Q85: 医保 | S85: 加权平均后扣除主项拟定价格得到平移价格，根据项目间比价理顺项目价格。 | T85: 003311010160000-33110101603 | U85: 33110101603 | V85: 小儿经腹腔镜肾切开取石术 | Y85: 次 | AA85: 4545 | AB85: 4085 | AC85: 3915 | AD85: 3565 | AE85: 3030 | AF85: =IFERROR(FIND("（加收）",C85,1),0) -> 11 | AG85: =IF(AF85>0,LEFT(C85,IFERROR(FIND("-",C85,1),1)-1),C85) -> 泌尿系取石费 | AH85: =IF(AF85>0,_xlfn.MAXIFS(N:N,C:C,AG85),0)+N85 -> 2420 | AI85: =IF(AF85>0,_xlfn.MAXIFS(O:O,C:C,AG85),0)+O85 -> 2320 | AJ85: =IF(AF85>0,_xlfn.MAXIFS(P:P,C:C,AG85),0)+P85 -> 1970
A86: 分项 | B86: 013311000050001 | C86: 泌尿系取石费-上尿路（加收） | D86: 手术费 | G86: 次 | H86: 本项目中的“上尿路”指：肾脏及输尿管。 | I86: 1265 | J86: 1139 | K86: 1224.3925 | L86: 962.92683 | M86: 280 | N86: 1170 | O86: 1120 | P86: 950 | Q86: 医保 | S86: 加权平均后扣除主项拟定价格得到平移价格，根据项目间比价理顺项目价格。 | T86: 003311020070000-331102007 | U86: 331102007 | V86: 输尿管切开取石术 | Y86: 次 | AA86: 1920 | AB86: 1730 | AC86: 1690 | AD86: 1520 | AE86: 1290 | AF86: =IFERROR(FIND("（加收）",C86,1),0) -> 11 | AG86: =IF(AF86>0,LEFT(C86,IFERROR(FIND("-",C86,1),1)-1),C86) -> 泌尿系取石费 | AH86: =IF(AF86>0,_xlfn.MAXIFS(N:N,C:C,AG86),0)+N86 -> 2420 | AI86: =IF(AF86>0,_xlfn.MAXIFS(O:O,C:C,AG86),0)+O86 -> 2320 | AJ86: =IF(AF86>0,_xlfn.MAXIFS(P:P,C:C,AG86),0)+P86 -> 1970
A87: 分项 | B87: 013311000050001 | C87: 泌尿系取石费-上尿路（加收） | D87: 手术费 | G87: 次 | H87: 本项目中的“上尿路”指：肾脏及输尿管。 | I87: 1265 | J87: 1139 | K87: 1224.3925 | L87: 962.92683 | M87: 280 | N87: 1170 | O87: 1120 | P87: 950 | Q87: 医保 | S87: 加权平均后扣除主项拟定价格得到平移价格，根据项目间比价理顺项目价格。 | T87: 003311020070000-33110200701 | U87: 33110200701 | V87: 小儿输尿管切开取石术 | Y87: 次 | AA87: 2495 | AB87: 2250 | AC87: 2195 | AD87: 1975 | AE87: 1680 | AF87: =IFERROR(FIND("（加收）",C87,1),0) -> 11 | AG87: =IF(AF87>0,LEFT(C87,IFERROR(FIND("-",C87,1),1)-1),C87) -> 泌尿系取石费 | AH87: =IF(AF87>0,_xlfn.MAXIFS(N:N,C:C,AG87),0)+N87 -> 2420 | AI87: =IF(AF87>0,_xlfn.MAXIFS(O:O,C:C,AG87),0)+O87 -> 2320 | AJ87: =IF(AF87>0,_xlfn.MAXIFS(P:P,C:C,AG87),0)+P87 -> 1970
A88: 分项 | B88: 013311000050001 | C88: 泌尿系取石费-上尿路（加收） | D88: 手术费 | G88: 次 | H88: 本项目中的“上尿路”指：肾脏及输尿管。 | I88: 1265 | J88: 1139 | K88: 1224.3925 | L88: 962.92683 | M88: 280 | N88: 1170 | O88: 1120 | P88: 950 | Q88: 医保 | S88: 加权平均后扣除主项拟定价格得到平移价格，根据项目间比价理顺项目价格。 | T88: 003311020070001-33110200702 | U88: 33110200702 | V88: 经腹腔镜输尿管切开取石术 | Y88: 次 | AA88: 2720 | AB88: 2450 | AC88: 2315 | AD88: 2120 | AE88: 1300 | AF88: =IFERROR(FIND("（加收）",C88,1),0) -> 11 | AG88: =IF(AF88>0,LEFT(C88,IFERROR(FIND("-",C88,1),1)-1),C88) -> 泌尿系取石费 | AH88: =IF(AF88>0,_xlfn.MAXIFS(N:N,C:C,AG88),0)+N88 -> 2420 | AI88: =IF(AF88>0,_xlfn.MAXIFS(O:O,C:C,AG88),0)+O88 -> 2320 | AJ88: =IF(AF88>0,_xlfn.MAXIFS(P:P,C:C,AG88),0)+P88 -> 1970
A89: 分项 | B89: 013311000050001 | C89: 泌尿系取石费-上尿路（加收） | D89: 手术费 | G89: 次 | H89: 本项目中的“上尿路”指：肾脏及输尿管。 | I89: 1265 | J89: 1139 | K89: 1224.3925 | L89: 962.92683 | M89: 280 | N89: 1170 | O89: 1120 | P89: 950 | Q89: 医保 | S89: 加权平均后扣除主项拟定价格得到平移价格，根据项目间比价理顺项目价格。 | T89: 003311020070001-33110200703 | U89: 33110200703 | V89: 小儿经腹腔镜输尿管切开取石术 | Y89: 次 | AA89: 3295 | AB89: 2970 | AC89: 2820 | AD89: 2575 | AE89: 2190 | AF89: =IFERROR(FIND("（加收）",C89,1),0) -> 11 | AG89: =IF(AF89>0,LEFT(C89,IFERROR(FIND("-",C89,1),1)-1),C89) -> 泌尿系取石费 | AH89: =IF(AF89>0,_xlfn.MAXIFS(N:N,C:C,AG89),0)+N89 -> 2420 | AI89: =IF(AF89>0,_xlfn.MAXIFS(O:O,C:C,AG89),0)+O89 -> 2320 | AJ89: =IF(AF89>0,_xlfn.MAXIFS(P:P,C:C,AG89),0)+P89 -> 1970
A90: 分项 | B90: 013311000050011 | C90: 泌尿系取石费-儿童（加收） | D90: 手术费 | G90: 次 | I90: 405 | J90: 365 | N90: 375 | O90: 360 | P90: 305 | Q90: 医保 | S90: 儿童加收30% | T90: 003311030010000-33110300101 | U90: 33110300101 | V90: 小儿膀胱切开取石术 | Y90: 次 | AA90: 1300 | AB90: 1170 | AC90: 1300 | AD90: 1250 | AE90: 1065 | AF90: =IFERROR(FIND("（加收）",C90,1),0) -> 10 | AG90: =IF(AF90>0,LEFT(C90,IFERROR(FIND("-",C90,1),1)-1),C90) -> 泌尿系取石费 | AH90: =IF(AF90>0,_xlfn.MAXIFS(N:N,C:C,AG90),0)+N90 -> 1625 | AI90: =IF(AF90>0,_xlfn.MAXIFS(O:O,C:C,AG90),0)+O90 -> 1560 | AJ90: =IF(AF90>0,_xlfn.MAXIFS(P:P,C:C,AG90),0)+P90 -> 1325
A91: 分项 | B91: 013311000050011 | C91: 泌尿系取石费-儿童（加收） | D91: 手术费 | G91: 次 | I91: 405 | J91: 365 | N91: 375 | O91: 360 | P91: 305 | Q91: 医保 | S91: 儿童加收30% | T91: 003311030010000-33110300103 | U91: 33110300103 | V91: 小儿经腹腔镜膀胱切开取石术 | Y91: 次 | AA91: 2100 | AB91: 1890 | AC91: 1925 | AD91: 1850 | AE91: 1575 | AF91: =IFERROR(FIND("（加收）",C91,1),0) -> 10 | AG91: =IF(AF91>0,LEFT(C91,IFERROR(FIND("-",C91,1),1)-1),C91) -> 泌尿系取石费 | AH91: =IF(AF91>0,_xlfn.MAXIFS(N:N,C:C,AG91),0)+N91 -> 1625 | AI91: =IF(AF91>0,_xlfn.MAXIFS(O:O,C:C,AG91),0)+O91 -> 1560 | AJ91: =IF(AF91>0,_xlfn.MAXIFS(P:P,C:C,AG91),0)+P91 -> 1325
A92: 分项 | B92: 013311000050011 | C92: 泌尿系取石费-儿童（加收） | D92: 手术费 | G92: 次 | I92: 405 | J92: 365 | N92: 375 | O92: 360 | P92: 305 | Q92: 医保 | S92: 儿童加收30% | T92: 003311040050000-33110400501 | U92: 33110400501 | V92: 小儿尿道切开取石术 | Y92: 次 | AA92: 1585 | AB92: 1415 | AC92: 1465 | AD92: 1405 | AE92: 1195 | AF92: =IFERROR(FIND("（加收）",C92,1),0) -> 10 | AG92: =IF(AF92>0,LEFT(C92,IFERROR(FIND("-",C92,1),1)-1),C92) -> 泌尿系取石费 | AH92: =IF(AF92>0,_xlfn.MAXIFS(N:N,C:C,AG92),0)+N92 -> 1625 | AI92: =IF(AF92>0,_xlfn.MAXIFS(O:O,C:C,AG92),0)+O92 -> 1560 | AJ92: =IF(AF92>0,_xlfn.MAXIFS(P:P,C:C,AG92),0)+P92 -> 1325
A93: 分项 | B93: 013311000050011 | C93: 泌尿系取石费-儿童（加收） | D93: 手术费 | G93: 次 | I93: 405 | J93: 365 | N93: 375 | O93: 360 | P93: 305 | Q93: 医保 | S93: 儿童加收30% | T93: 003311040050000-33110400503 | U93: 33110400503 | V93: 小儿经膀胱镜尿道切开取石术 | Y93: 次 | AA93: 1835 | AB93: 1640 | AC93: 1715 | AD93: 1630 | AE93: 1385 | AF93: =IFERROR(FIND("（加收）",C93,1),0) -> 10 | AG93: =IF(AF93>0,LEFT(C93,IFERROR(FIND("-",C93,1),1)-1),C93) -> 泌尿系取石费 | AH93: =IF(AF93>0,_xlfn.MAXIFS(N:N,C:C,AG93),0)+N93 -> 1625 | AI93: =IF(AF93>0,_xlfn.MAXIFS(O:O,C:C,AG93),0)+O93 -> 1560 | AJ93: =IF(AF93>0,_xlfn.MAXIFS(P:P,C:C,AG93),0)+P93 -> 1325
A94: 36 | B94: 013311000060000 | C94: 泌尿系造瘘费 | D94: 手术费 | E94: 通过手术建立泌尿系与皮肤的瘘道。 | F94: 所定价格涵盖手术计划、术区准备、消毒、穿刺、建立瘘道、引流、缝合、处理用物等步骤所需的人力资源和基本物质资源消耗。 | G94: 次 | I94: 357 | J94: 321 | K94: 537.11932 | L94: 458.01808 | M94: 706.125 | N94: 355 | O94: 320 | P94: 285 | Q94: 医保 | R94: 理顺，降低 | S94: 加权平均后按照不高于省级理顺价格 | T94: 003110000220000-311000022 | U94: 311000022 | V94: 经皮输尿管内管置入术 | Y94: 次 | AA94: 440 | AB94: 395 | AC94: 440 | AD94: 400 | AE94: 340 | AF94: =IFERROR(FIND("（加收）",C94,1),0) -> 0 | AG94: =IF(AF94>0,LEFT(C94,IFERROR(FIND("-",C94,1),1)-1),C94) -> 泌尿系造瘘费 | AH94: =IF(AF94>0,_xlfn.MAXIFS(N:N,C:C,AG94),0)+N94 -> 355 | AI94: =IF(AF94>0,_xlfn.MAXIFS(O:O,C:C,AG94),0)+O94 -> 320 | AJ94: =IF(AF94>0,_xlfn.MAXIFS(P:P,C:C,AG94),0)+P94 -> 285
A95: 36 | B95: 013311000060000 | C95: 泌尿系造瘘费 | D95: 手术费 | E95: 通过手术建立泌尿系与皮肤的瘘道。 | F95: 所定价格涵盖手术计划、术区准备、消毒、穿刺、建立瘘道、引流、缝合、处理用物等步骤所需的人力资源和基本物质资源消耗。 | G95: 次 | I95: 357 | J95: 321 | K95: 537.11932 | L95: 458.01808 | M95: 706.125 | N95: 355 | O95: 320 | P95: 285 | Q95: 医保 | R95: 理顺，降低 | S95: 加权平均后按照不高于省级理顺价格 | T95: 003110000330000-311000033 | U95: 311000033 | V95: 膀胱穿刺造瘘术 | Y95: 次 | Z95: 六岁及以下儿童在原价基础上加收30% | AA95: 235 | AB95: 210 | AC95: 225 | AD95: 205 | AE95: 175 | AF95: =IFERROR(FIND("（加收）",C95,1),0) -> 0 | AG95: =IF(AF95>0,LEFT(C95,IFERROR(FIND("-",C95,1),1)-1),C95) -> 泌尿系造瘘费 | AH95: =IF(AF95>0,_xlfn.MAXIFS(N:N,C:C,AG95),0)+N95 -> 355 | AI95: =IF(AF95>0,_xlfn.MAXIFS(O:O,C:C,AG95),0)+O95 -> 320 | AJ95: =IF(AF95>0,_xlfn.MAXIFS(P:P,C:C,AG95),0)+P95 -> 285
A96: 36 | B96: 013311000060000 | C96: 泌尿系造瘘费 | D96: 手术费 | E96: 通过手术建立泌尿系与皮肤的瘘道。 | F96: 所定价格涵盖手术计划、术区准备、消毒、穿刺、建立瘘道、引流、缝合、处理用物等步骤所需的人力资源和基本物质资源消耗。 | G96: 次 | I96: 357 | J96: 321 | K96: 537.11932 | L96: 458.01808 | M96: 706.125 | N96: 355 | O96: 320 | P96: 285 | Q96: 医保 | R96: 理顺，降低 | S96: 加权平均后按照不高于省级理顺价格 | T96: 003311030050000-331103005 | U96: 331103005 | V96: 膀胱造瘘术 | Y96: 次 | AA96: 1000 | AB96: 900 | AC96: 1000 | AD96: 960 | AE96: 816 | AF96: =IFERROR(FIND("（加收）",C96,1),0) -> 0 | AG96: =IF(AF96>0,LEFT(C96,IFERROR(FIND("-",C96,1),1)-1),C96) -> 泌尿系造瘘费 | AH96: =IF(AF96>0,_xlfn.MAXIFS(N:N,C:C,AG96),0)+N96 -> 355 | AI96: =IF(AF96>0,_xlfn.MAXIFS(O:O,C:C,AG96),0)+O96 -> 320 | AJ96: =IF(AF96>0,_xlfn.MAXIFS(P:P,C:C,AG96),0)+P96 -> 285
A97: 36 | B97: 013311000060000 | C97: 泌尿系造瘘费 | D97: 手术费 | E97: 通过手术建立泌尿系与皮肤的瘘道。 | F97: 所定价格涵盖手术计划、术区准备、消毒、穿刺、建立瘘道、引流、缝合、处理用物等步骤所需的人力资源和基本物质资源消耗。 | G97: 次 | I97: 357 | J97: 321 | K97: 537.11932 | L97: 458.01808 | M97: 706.125 | N97: 355 | O97: 320 | P97: 285 | Q97: 医保 | R97: 理顺，降低 | S97: 加权平均后按照不高于省级理顺价格 | T97: 003311040170000-331104017 | U97: 331104017 | V97: 尿道会阴造口术 | Y97: 次 | AA97: 875 | AB97: 790 | AC97: 875 | AD97: 840 | AE97: 714 | AF97: =IFERROR(FIND("（加收）",C97,1),0) -> 0 | AG97: =IF(AF97>0,LEFT(C97,IFERROR(FIND("-",C97,1),1)-1),C97) -> 泌尿系造瘘费 | AH97: =IF(AF97>0,_xlfn.MAXIFS(N:N,C:C,AG97),0)+N97 -> 355 | AI97: =IF(AF97>0,_xlfn.MAXIFS(O:O,C:C,AG97),0)+O97 -> 320 | AJ97: =IF(AF97>0,_xlfn.MAXIFS(P:P,C:C,AG97),0)+P97 -> 285
A98: 分项 | B98: 013311000060001 | C98: 泌尿系造瘘费-上尿路（加收） | D98: 手术费 | G98: 次 | H98: 本项目中的“上尿路”指：肾脏及输尿管。 | I98: 1280 | J98: 1152 | K98: 1145 | L98: 1120 | M98: #DIV/0! | N98: 1145 | O98: 1120 | P98: 1000 | Q98: 医保 | S98: 加权平均后扣除主项拟定价格得到平移价格 | T98: 003311010130000-331101013 | U98: 331101013 | V98: 肾实质切开造瘘术 | Y98: 次 | AA98: 1620 | AB98: 1460 | AC98: 1500 | AD98: 1440 | AE98: 1224 | AF98: =IFERROR(FIND("（加收）",C98,1),0) -> 11 | AG98: =IF(AF98>0,LEFT(C98,IFERROR(FIND("-",C98,1),1)-1),C98) -> 泌尿系造瘘费 | AH98: =IF(AF98>0,_xlfn.MAXIFS(N:N,C:C,AG98),0)+N98 -> 1500 | AI98: =IF(AF98>0,_xlfn.MAXIFS(O:O,C:C,AG98),0)+O98 -> 1440 | AJ98: =IF(AF98>0,_xlfn.MAXIFS(P:P,C:C,AG98),0)+P98 -> 1285
A99: 分项 | B99: 013311000060001 | C99: 泌尿系造瘘费-上尿路（加收） | D99: 手术费 | G99: 次 | H99: 本项目中的“上尿路”指：肾脏及输尿管。 | I99: 1280 | J99: 1152 | K99: 1145 | L99: 1120 | M99: #DIV/0! | N99: 1145 | O99: 1120 | P99: 1000 | Q99: 医保 | S99: 加权平均后扣除主项拟定价格得到平移价格 | T99: 003311010130000-33110101301 | U99: 33110101301 | V99: 小儿肾实质切开造瘘术 | Y99: 次 | AA99: 2105 | AB99: 1900 | AC99: 1950 | AD99: 1870 | AE99: 1590 | AF99: =IFERROR(FIND("（加收）",C99,1),0) -> 11 | AG99: =IF(AF99>0,LEFT(C99,IFERROR(FIND("-",C99,1),1)-1),C99) -> 泌尿系造瘘费 | AH99: =IF(AF99>0,_xlfn.MAXIFS(N:N,C:C,AG99),0)+N99 -> 1500 | AI99: =IF(AF99>0,_xlfn.MAXIFS(O:O,C:C,AG99),0)+O99 -> 1440 | AJ99: =IF(AF99>0,_xlfn.MAXIFS(P:P,C:C,AG99),0)+P99 -> 1285
A100: 分项 | B100: 013311000060001 | C100: 泌尿系造瘘费-上尿路（加收） | D100: 手术费 | G100: 次 | H100: 本项目中的“上尿路”指：肾脏及输尿管。 | I100: 1280 | J100: 1152 | K100: 1145 | L100: 1120 | M100: #DIV/0! | N100: 1145 | O100: 1120 | P100: 1000 | Q100: 医保 | S100: 加权平均后扣除主项拟定价格得到平移价格 | T100: 003311010130000-33110101302 | U100: 33110101302 | V100: 经腹腔镜肾实质切开造瘘术 | Y100: 次 | AA100: 2420 | AB100: 2180 | AC100: 2125 | AD100: 2040 | AE100: 1734 | AF100: =IFERROR(FIND("（加收）",C100,1),0) -> 11 | AG100: =IF(AF100>0,LEFT(C100,IFERROR(FIND("-",C100,1),1)-1),C100) -> 泌尿系造瘘费 | AH100: =IF(AF100>0,_xlfn.MAXIFS(N:N,C:C,AG100),0)+N100 -> 1500 | AI100: =IF(AF100>0,_xlfn.MAXIFS(O:O,C:C,AG100),0)+O100 -> 1440 | AJ100: =IF(AF100>0,_xlfn.MAXIFS(P:P,C:C,AG100),0)+P100 -> 1285
...

Sheet Sheet1
A1: id | B1: code | C1: sever_type | D1: change_time | E1: old_hilist_code | F1: new_hilist_code | G1: hilist_name | H1: selfpay_prop | I1: old_price | J1: old_price_city | K1: old_price_town | L1: old_price_village | M1: new_price | N1: new_price_city | O1: new_price_town | P1: new_price_village | Q1: unit | R1: batch | S1: is_use_old | T1: merge_type | U1: cnt_change_model | V1: cnt_change_value | W1: ="insert into server_list_change_all_20250525 ("&_xlfn.TEXTJOIN(",",TRUE,A1:V1)&") values" -> insert into server_list_change_all_20250525 (id,code,sever_type,change_time,old_hilist_code,new_hilist_code,hilist_name,selfpay_prop,old_price,old_price_city,old_price_town,old_price_village,new_price,new_price_city,new_price_town,new_price_village,unit,batch,is_use_old,merge_type,cnt_change_model,cnt_change_value) values
A2: 3094 | B2: null | C2: 1 | D2: 2026-04-28 00:00:00 | E2: 003110000390000-311000039 | F2: 003110000390000-311000039 | G2: 尿流动力学检测 | H2: null | I2: null | J2: 165 | K2: 150 | L2: 127.5 | M2: null | N2: 165 | O2: 150 | P2: 128 | Q2: 次 | R2: 27 | S2: 1 | T2: normal | U2: main | V2: 0 | W2: ="("&A2&","&B2&","&C2&",'"&D2&"','"&E2&"','"&F2&"','"&G2&"',"&H2&","&I2&","&J2&","&K2&","&L2&","&M2&","&N2&","&O2&","&P2&",'"&Q2&"',"&R2&","&S2&",'"&T2&"','"&U2&"',"&V2&")," -> (3094,null,1,'2026-04-28 00:00:00','003110000390000-311000039','003110000390000-311000039','尿流动力学检测',null,null,165,150,127.5,null,165,150,128,'次',27,1,'normal','main',0),
A3: 3095 | B3: null | C3: 1 | D3: 2026-04-28 00:00:00 | E3: 003110000380000-311000038 | F3: 003110000380000-311000038 | G3: 尿流率检测 | H3: null | I3: null | J3: 66 | K3: 60 | L3: 51 | M3: null | N3: 66 | O3: 59 | P3: 51 | Q3: 次 | R3: 27 | S3: 1 | T3: normal | U3: main | V3: 0 | W3: ="("&A3&","&B3&","&C3&",'"&D3&"','"&E3&"','"&F3&"','"&G3&"',"&H3&","&I3&","&J3&","&K3&","&L3&","&M3&","&N3&","&O3&","&P3&",'"&Q3&"',"&R3&","&S3&",'"&T3&"','"&U3&"',"&V3&")," -> (3095,null,1,'2026-04-28 00:00:00','003110000380000-311000038','003110000380000-311000038','尿流率检测',null,null,66,60,51,null,66,59,51,'次',27,1,'normal','main',0),
A4: 3096 | B4: null | C4: 1 | D4: 2026-04-28 00:00:00 | E4: 003110000180000-311000018 | F4: 003110000180000-311000018 | G4: 经皮肾盂镜检查 | H4: null | I4: null | J4: 660 | K4: 600 | L4: 510 | M4: null | N4: 660 | O4: 595 | P4: 510 | Q4: 单侧 | R4: 27 | S4: 1 | T4: normal | U4: main | V4: 0 | W4: ="("&A4&","&B4&","&C4&",'"&D4&"','"&E4&"','"&F4&"','"&G4&"',"&H4&","&I4&","&J4&","&K4&","&L4&","&M4&","&N4&","&O4&","&P4&",'"&Q4&"',"&R4&","&S4&",'"&T4&"','"&U4&"',"&V4&")," -> (3096,null,1,'2026-04-28 00:00:00','003110000180000-311000018','003110000180000-311000018','经皮肾盂镜检查',null,null,660,600,510,null,660,595,510,'单侧',27,1,'normal','main',0),
A5: 3097 | B5: null | C5: 1 | D5: 2026-04-28 00:00:00 | E5: 003110000200000-311000020 | F5: 003110000200000-311000020 | G5: 经尿道输尿管镜检查 | H5: null | I5: null | J5: 495 | K5: 450 | L5: 382.5 | M5: null | N5: 495 | O5: 445 | P5: 380 | Q5: 单侧 | R5: 27 | S5: 1 | T5: normal | U5: main | V5: 0 | W5: ="("&A5&","&B5&","&C5&",'"&D5&"','"&E5&"','"&F5&"','"&G5&"',"&H5&","&I5&","&J5&","&K5&","&L5&","&M5&","&N5&","&O5&","&P5&",'"&Q5&"',"&R5&","&S5&",'"&T5&"','"&U5&"',"&V5&")," -> (3097,null,1,'2026-04-28 00:00:00','003110000200000-311000020','003110000200000-311000020','经尿道输尿管镜检查',null,null,495,450,382.5,null,495,445,380,'单侧',27,1,'normal','main',0),
A6: 3098 | B6: null | C6: 1 | D6: 2026-04-28 00:00:00 | E6: 353111000290000-311100020 | F6: 353111000290000-311100020 | G6: 经尿道精囊镜检查 | H6: null | I6: null | J6: 720 | K6: 648 | L6: 550.8 | M6: null | N6: 495 | O6: 445 | P6: 380 | Q6: 侧 | R6: 27 | S6: 1 | T6: normal | U6: main | V6: 0 | W6: ="("&A6&","&B6&","&C6&",'"&D6&"','"&E6&"','"&F6&"','"&G6&"',"&H6&","&I6&","&J6&","&K6&","&L6&","&M6&","&N6&","&O6&","&P6&",'"&Q6&"',"&R6&","&S6&",'"&T6&"','"&U6&"',"&V6&")," -> (3098,null,1,'2026-04-28 00:00:00','353111000290000-311100020','353111000290000-311100020','经尿道精囊镜检查',null,null,720,648,550.8,null,495,445,380,'侧',27,1,'normal','main',0),
A7: 3099 | B7: null | C7: 1 | D7: 2026-04-28 00:00:00 | E7: 003110000340000-311000034 | F7: 003110000340000-311000034 | G7: 膀胱镜尿道镜检查 | H7: null | I7: null | J7: 132 | K7: 120 | L7: 102 | M7: null | N7: 132 | O7: 120 | P7: 102 | Q7: 次 | R7: 27 | S7: 1 | T7: normal | U7: main | V7: 0 | W7: ="("&A7&","&B7&","&C7&",'"&D7&"','"&E7&"','"&F7&"','"&G7&"',"&H7&","&I7&","&J7&","&K7&","&L7&","&M7&","&N7&","&O7&","&P7&",'"&Q7&"',"&R7&","&S7&",'"&T7&"','"&U7&"',"&V7&")," -> (3099,null,1,'2026-04-28 00:00:00','003110000340000-311000034','003110000340000-311000034','膀胱镜尿道镜检查',null,null,132,120,102,null,132,120,102,'次',27,1,'normal','main',0),
A8: 3100 | B8: null | C8: 1 | D8: 2026-04-28 00:00:00 | E8: 003111000030000-311100003 | F8: 003111000030000-311100003 | G8: 夜间阴茎胀大试验 | H8: null | I8: null | J8: 99 | K8: 89 | L8: 77 | M8: null | N8: 99 | O8: 89 | P8: 77 | Q8: 次 | R8: 27 | S8: 1 | T8: normal | U8: main | V8: 0 | W8: ="("&A8&","&B8&","&C8&",'"&D8&"','"&E8&"','"&F8&"','"&G8&"',"&H8&","&I8&","&J8&","&K8&","&L8&","&M8&","&N8&","&O8&","&P8&",'"&Q8&"',"&R8&","&S8&",'"&T8&"','"&U8&"',"&V8&")," -> (3100,null,1,'2026-04-28 00:00:00','003111000030000-311100003','003111000030000-311100003','夜间阴茎胀大试验',null,null,99,89,77,null,99,89,77,'次',27,1,'normal','main',0),
A9: 3101 | B9: null | C9: 1 | D9: 2026-04-28 00:00:00 | E9: 003111000040000-311100004 | F9: 003111000040000-311100004 | G9: 阴茎超声血流图检查 | H9: null | I9: null | J9: 88 | K9: 80 | L9: 68 | M9: null | N9: 77 | O9: 69 | P9: 60 | Q9: 次 | R9: 27 | S9: 1 | T9: normal | U9: main | V9: 0 | W9: ="("&A9&","&B9&","&C9&",'"&D9&"','"&E9&"','"&F9&"','"&G9&"',"&H9&","&I9&","&J9&","&K9&","&L9&","&M9&","&N9&","&O9&","&P9&",'"&Q9&"',"&R9&","&S9&",'"&T9&"','"&U9&"',"&V9&")," -> (3101,null,1,'2026-04-28 00:00:00','003111000040000-311100004','003111000040000-311100004','阴茎超声血流图检查',null,null,88,80,68,null,77,69,60,'次',27,1,'normal','main',0),
A10: 3102 | B10: null | C10: 1 | D10: 2026-04-28 00:00:00 | E10: 003111000110000-311100011 | F10: 003111000110000-311100011 | G10: 阴茎动脉测压术 | H10: null | I10: null | J10: 44 | K10: 40 | L10: 34 | M10: null | N10: 77 | O10: 69 | P10: 60 | Q10: 次 | R10: 27 | S10: 1 | T10: normal | U10: main | V10: 0 | W10: ="("&A10&","&B10&","&C10&",'"&D10&"','"&E10&"','"&F10&"','"&G10&"',"&H10&","&I10&","&J10&","&K10&","&L10&","&M10&","&N10&","&O10&","&P10&",'"&Q10&"',"&R10&","&S10&",'"&T10&"','"&U10&"',"&V10&")," -> (3102,null,1,'2026-04-28 00:00:00','003111000110000-311100011','003111000110000-311100011','阴茎动脉测压术',null,null,44,40,34,null,77,69,60,'次',27,1,'normal','main',0),
A11: 3103 | B11: null | C11: 1 | D11: 2026-04-28 00:00:00 | E11: 003111000050000-311100005 | F11: 003111000050000-311100005 | G11: 阴茎勃起神经检查 | H11: null | I11: null | J11: 110 | K11: 100 | L11: 85 | M11: null | N11: 110 | O11: 99 | P11: 85 | Q11: 次 | R11: 27 | S11: 1 | T11: normal | U11: main | V11: 0 | W11: ="("&A11&","&B11&","&C11&",'"&D11&"','"&E11&"','"&F11&"','"&G11&"',"&H11&","&I11&","&J11&","&K11&","&L11&","&M11&","&N11&","&O11&","&P11&",'"&Q11&"',"&R11&","&S11&",'"&T11&"','"&U11&"',"&V11&")," -> (3103,null,1,'2026-04-28 00:00:00','003111000050000-311100005','003111000050000-311100005','阴茎勃起神经检查',null,null,110,100,85,null,110,99,85,'次',27,1,'normal','main',0),
A12: 3104 | B12: null | C12: 1 | D12: 2026-04-28 00:00:00 | E12: 003109050230000-310905023 | F12: 003109050230000-310905023 | G12: 人工肝治疗 | H12: null | I12: null | J12: 1500 | K12: 1350 | L12: 1145 | M12: null | N12: 2250 | O12: 2050 | P12: 1740 | Q12: 次 | R12: 27 | S12: 1 | T12: normal | U12: main | V12: 0 | W12: ="("&A12&","&B12&","&C12&",'"&D12&"','"&E12&"','"&F12&"','"&G12&"',"&H12&","&I12&","&J12&","&K12&","&L12&","&M12&","&N12&","&O12&","&P12&",'"&Q12&"',"&R12&","&S12&",'"&T12&"','"&U12&"',"&V12&")," -> (3104,null,1,'2026-04-28 00:00:00','003109050230000-310905023','003109050230000-310905023','人工肝治疗',null,null,1500,1350,1145,null,2250,2050,1740,'次',27,1,'normal','main',0),
A13: 3105 | B13: null | C13: 1 | D13: 2026-04-28 00:00:00 | E13: 013110000060000 | F13: 013110000060000 | G13: 血浆置换费 | H13: null | I13: null | J13: 2450 | K13: 2325 | L13: 2000 | M13: null | N13: 3200 | O13: 3025 | P13: 2595 | R13: 27 | S13: 1 | T13: normal | U13: main | V13: 0 | W13: ="("&A13&","&B13&","&C13&",'"&D13&"','"&E13&"','"&F13&"','"&G13&"',"&H13&","&I13&","&J13&","&K13&","&L13&","&M13&","&N13&","&O13&","&P13&",'"&Q13&"',"&R13&","&S13&",'"&T13&"','"&U13&"',"&V13&")," -> (3105,null,1,'2026-04-28 00:00:00','013110000060000','013110000060000','血浆置换费',null,null,2450,2325,2000,null,3200,3025,2595,'',27,1,'normal','main',0),
A14: 3106 | B14: null | C14: 1 | D14: 2026-04-28 00:00:00 | E14: 013110000150000 | F14: 013110000150000 | G14: 腹膜平衡试验费 | H14: null | I14: null | J14: 40 | K14: 40 | L14: 34 | M14: null | N14: 42 | O14: 40 | P14: 34 | Q14: 次 | R14: 27 | S14: 1 | T14: normal | U14: main | V14: 0 | W14: ="("&A14&","&B14&","&C14&",'"&D14&"','"&E14&"','"&F14&"','"&G14&"',"&H14&","&I14&","&J14&","&K14&","&L14&","&M14&","&N14&","&O14&","&P14&",'"&Q14&"',"&R14&","&S14&",'"&T14&"','"&U14&"',"&V14&")," -> (3106,null,1,'2026-04-28 00:00:00','013110000150000','013110000150000','腹膜平衡试验费',null,null,40,40,34,null,42,40,34,'次',27,1,'normal','main',0),
A15: 3107 | B15: null | C15: 1 | D15: 2026-04-28 00:00:00 | E15: 013311000010000 | F15: 013311000010000 | G15: 腹膜透析置管费 | H15: null | I15: null | J15: 400 | K15: 400 | L15: 340 | M15: null | N15: 420 | O15: 395 | P15: 340 | Q15: 次 | R15: 27 | S15: 1 | T15: normal | U15: main | V15: 0 | W15: ="("&A15&","&B15&","&C15&",'"&D15&"','"&E15&"','"&F15&"','"&G15&"',"&H15&","&I15&","&J15&","&K15&","&L15&","&M15&","&N15&","&O15&","&P15&",'"&Q15&"',"&R15&","&S15&",'"&T15&"','"&U15&"',"&V15&")," -> (3107,null,1,'2026-04-28 00:00:00','013311000010000','013311000010000','腹膜透析置管费',null,null,400,400,340,null,420,395,340,'次',27,1,'normal','main',0),
A16: 3108 | B16: null | C16: 1 | D16: 2026-04-28 00:00:00 | E16: 003110000010000-311000001 | F16: 003110000010000-311000001 | G16: 腹膜透析置管费 | H16: null | I16: null | J16: 400 | K16: 400 | L16: 340 | M16: null | N16: 420 | O16: 395 | P16: 340 | Q16: 次 | R16: 27 | S16: 1 | T16: normal | U16: main | V16: 0 | W16: ="("&A16&","&B16&","&C16&",'"&D16&"','"&E16&"','"&F16&"','"&G16&"',"&H16&","&I16&","&J16&","&K16&","&L16&","&M16&","&N16&","&O16&","&P16&",'"&Q16&"',"&R16&","&S16&",'"&T16&"','"&U16&"',"&V16&")," -> (3108,null,1,'2026-04-28 00:00:00','003110000010000-311000001','003110000010000-311000001','腹膜透析置管费',null,null,400,400,340,null,420,395,340,'次',27,1,'normal','main',0),
A17: 3109 | B17: null | C17: 1 | D17: 2026-04-28 00:00:00 | E17: 013311000020000 | F17: 013311000020000 | G17: 腹膜透析换管费 | H17: null | I17: null | J17: 420 | K17: 420 | L17: 360 | M17: null | N17: 420 | O17: 395 | P17: 340 | Q17: 次 | R17: 27 | S17: 1 | T17: normal | U17: main | V17: 0 | W17: ="("&A17&","&B17&","&C17&",'"&D17&"','"&E17&"','"&F17&"','"&G17&"',"&H17&","&I17&","&J17&","&K17&","&L17&","&M17&","&N17&","&O17&","&P17&",'"&Q17&"',"&R17&","&S17&",'"&T17&"','"&U17&"',"&V17&")," -> (3109,null,1,'2026-04-28 00:00:00','013311000020000','013311000020000','腹膜透析换管费',null,null,420,420,360,null,420,395,340,'次',27,1,'normal','main',0),
A18: 3110 | B18: null | C18: 1 | D18: 2026-04-28 00:00:00 | E18: 013110000170000 | F18: 013110000170000 | G18: 腹膜透析导管取出费 | H18: null | I18: null | J18: 400 | K18: 400 | L18: 340 | M18: null | N18: 420 | O18: 395 | P18: 340 | Q18: 次 | R18: 27 | S18: 1 | T18: normal | U18: main | V18: 0 | W18: ="("&A18&","&B18&","&C18&",'"&D18&"','"&E18&"','"&F18&"','"&G18&"',"&H18&","&I18&","&J18&","&K18&","&L18&","&M18&","&N18&","&O18&","&P18&",'"&Q18&"',"&R18&","&S18&",'"&T18&"','"&U18&"',"&V18&")," -> (3110,null,1,'2026-04-28 00:00:00','013110000170000','013110000170000','腹膜透析导管取出费',null,null,400,400,340,null,420,395,340,'次',27,1,'normal','main',0),
A19: 3111 | B19: null | C19: 1 | D19: 2026-04-28 00:00:00 | E19: 003110000010100-31100000101 | F19: 003110000010100-31100000101 | G19: 腹膜透析导管取出费 | H19: null | I19: null | J19: 400 | K19: 400 | L19: 340 | M19: null | N19: 420 | O19: 395 | P19: 340 | Q19: 次 | R19: 27 | S19: 1 | T19: normal | U19: main | V19: 0 | W19: ="("&A19&","&B19&","&C19&",'"&D19&"','"&E19&"','"&F19&"','"&G19&"',"&H19&","&I19&","&J19&","&K19&","&L19&","&M19&","&N19&","&O19&","&P19&",'"&Q19&"',"&R19&","&S19&",'"&T19&"','"&U19&"',"&V19&")," -> (3111,null,1,'2026-04-28 00:00:00','003110000010100-31100000101','003110000010100-31100000101','腹膜透析导管取出费',null,null,400,400,340,null,420,395,340,'次',27,1,'normal','main',0),
A20: 3112 | B20: null | C20: 1 | D20: 2026-04-28 00:00:00 | E20: 003110000400000-311000040 | F20: 003110000400000-311000040 | G20: 体外冲击波碎石 | H20: null | I20: null | J20: 700 | K20: 630 | L20: 535.5 | M20: null | N20: 700 | O20: 630 | P20: 535 | Q20: 次 | R20: 27 | S20: 1 | T20: normal | U20: main | V20: 0 | W20: ="("&A20&","&B20&","&C20&",'"&D20&"','"&E20&"','"&F20&"','"&G20&"',"&H20&","&I20&","&J20&","&K20&","&L20&","&M20&","&N20&","&O20&","&P20&",'"&Q20&"',"&R20&","&S20&",'"&T20&"','"&U20&"',"&V20&")," -> (3112,null,1,'2026-04-28 00:00:00','003110000400000-311000040','003110000400000-311000040','体外冲击波碎石',null,null,700,630,535.5,null,700,630,535,'次',27,1,'normal','main',0),
A21: 3113 | B21: null | C21: 1 | D21: 2026-04-28 00:00:00 | E21: 003110000400000-31100004003 | F21: 003110000400000-31100004003 | G21: 体外冲击波碎石（第二次） | H21: null | I21: null | J21: 350 | K21: 315 | L21: 267.8 | M21: null | N21: 350 | O21: 315 | P21: 268 | Q21: 次 | R21: 27 | S21: 1 | T21: normal | U21: main | V21: 0 | W21: ="("&A21&","&B21&","&C21&",'"&D21&"','"&E21&"','"&F21&"','"&G21&"',"&H21&","&I21&","&J21&","&K21&","&L21&","&M21&","&N21&","&O21&","&P21&",'"&Q21&"',"&R21&","&S21&",'"&T21&"','"&U21&"',"&V21&")," -> (3113,null,1,'2026-04-28 00:00:00','003110000400000-31100004003','003110000400000-31100004003','体外冲击波碎石（第二次）',null,null,350,315,267.8,null,350,315,268,'次',27,1,'normal','main',0),
A22: 3114 | B22: null | C22: 1 | D22: 2026-04-28 00:00:00 | E22: 003110000400000-31100004006 | F22: 003110000400000-31100004006 | G22: 体外冲击波碎石（第三次） | H22: null | I22: null | J22: 175 | K22: 157.5 | L22: 133.9 | M22: null | N22: 175 | O22: 158 | P22: 134 | Q22: 次 | R22: 27 | S22: 1 | T22: normal | U22: main | V22: 0 | W22: ="("&A22&","&B22&","&C22&",'"&D22&"','"&E22&"','"&F22&"','"&G22&"',"&H22&","&I22&","&J22&","&K22&","&L22&","&M22&","&N22&","&O22&","&P22&",'"&Q22&"',"&R22&","&S22&",'"&T22&"','"&U22&"',"&V22&")," -> (3114,null,1,'2026-04-28 00:00:00','003110000400000-31100004006','003110000400000-31100004006','体外冲击波碎石（第三次）',null,null,175,157.5,133.9,null,175,158,134,'次',27,1,'normal','main',0),
A23: 3115 | B23: null | C23: 1 | D23: 2026-04-28 00:00:00 | E23: 003110000190200-31100001901 | F23: 003110000190200-31100001901 | G23: 经皮肾盂镜取石术（取异物） | H23: null | I23: null | J23: 880 | K23: 800 | L23: 680 | M23: null | N23: 815 | O23: 740 | P23: 640 | Q23: 次 | R23: 27 | S23: 1 | T23: normal | U23: main | V23: 0 | W23: ="("&A23&","&B23&","&C23&",'"&D23&"','"&E23&"','"&F23&"','"&G23&"',"&H23&","&I23&","&J23&","&K23&","&L23&","&M23&","&N23&","&O23&","&P23&",'"&Q23&"',"&R23&","&S23&",'"&T23&"','"&U23&"',"&V23&")," -> (3115,null,1,'2026-04-28 00:00:00','003110000190200-31100001901','003110000190200-31100001901','经皮肾盂镜取石术（取异物）',null,null,880,800,680,null,815,740,640,'次',27,1,'normal','main',0),
A24: 3116 | B24: null | C24: 1 | D24: 2026-04-28 00:00:00 | E24: 003311030270000-331103027 | F24: 003311030270000-331103027 | G24: 经尿道膀胱碎石取石术 | H24: null | I24: null | J24: 1250 | K24: 1200 | L24: 1020 | M24: null | N24: 815 | O24: 740 | P24: 640 | Q24: 次 | R24: 27 | S24: 1 | T24: normal | U24: main | V24: 0 | W24: ="("&A24&","&B24&","&C24&",'"&D24&"','"&E24&"','"&F24&"','"&G24&"',"&H24&","&I24&","&J24&","&K24&","&L24&","&M24&","&N24&","&O24&","&P24&",'"&Q24&"',"&R24&","&S24&",'"&T24&"','"&U24&"',"&V24&")," -> (3116,null,1,'2026-04-28 00:00:00','003311030270000-331103027','003311030270000-331103027','经尿道膀胱碎石取石术',null,null,1250,1200,1020,null,815,740,640,'次',27,1,'normal','main',0),
A25: 3117 | B25: null | C25: 1 | D25: 2026-04-28 00:00:00 | E25: 003311030270000-33110302701 | F25: 003311030270000-33110302701 | G25: 小儿经尿道膀胱碎石取石术 | H25: null | I25: null | J25: 1625 | K25: 1560 | L25: 1325 | M25: null | N25: 815 | O25: 740 | P25: 640 | Q25: 次 | R25: 27 | S25: 1 | T25: normal | U25: main | V25: 0 | W25: ="("&A25&","&B25&","&C25&",'"&D25&"','"&E25&"','"&F25&"','"&G25&"',"&H25&","&I25&","&J25&","&K25&","&L25&","&M25&","&N25&","&O25&","&P25&",'"&Q25&"',"&R25&","&S25&",'"&T25&"','"&U25&"',"&V25&")," -> (3117,null,1,'2026-04-28 00:00:00','003311030270000-33110302701','003311030270000-33110302701','小儿经尿道膀胱碎石取石术',null,null,1625,1560,1325,null,815,740,640,'次',27,1,'normal','main',0),
... A575: 3667 | B575: null | C575: 1 | D575: 2026-04-28 00:00:00 | E575: 003310080150000-33100801503 | F575: 003310080150000-33100801503 | G575: 小儿经腹腔镜腹膜后肿瘤切除术 | H575: null | I575: null | J575: 5020 | K575: 4550 | L575: 3870 | M575: null | N575: 5460 | O575: 4875 | P575: 4135 | Q575: 次 | R575: 27 | S575: 1 | T575: normal | U575: main | V575: 0 | W575: ="("&A575&","&B575&","&C575&",'"&D575&"','"&E575&"','"&F575&"','"&G575&"',"&H575&","&I575&","&J575&","&K575&","&L575&","&M575&","&N575&","&O575&","&P575&",'"&Q575&"',"&R575&","&S575&",'"&T575&"','"&U575&"',"&V575&")," -> (3667,null,1,'2026-04-28 00:00:00','003310080150000-33100801503','003310080150000-33100801503','小儿经腹腔镜腹膜后肿瘤切除术',null,null,5020,4550,3870,null,5460,4875,4135,'次',27,1,'normal','main',0),

Sheet Sheet4(非最新）
B1: id | C1: list_type | F1: list_type_name | G1: old_hilist_code | H1: old_price | I1: old_price_city | J1: old_price_town | K1: old_price_village | L1: new_price | M1: new_price_city | N1: new_price_town | O1: new_price_village | P1: is_use_old | Q1: is_main | R1: cnt_change_model | S1: cnt_change_value | T1: 数量3 | U1: 数量2 | V1: 数量1 | W1: 预计差额3 | X1: 预计差额2 | Y1: 预计差额1 | Z1: 实际差额3 | AA1: 实际差额2 | AB1: 实际差额1
A2: 211 | B2: =_xlfn.XLOOKUP(G2,Sheet1!E:E,Sheet1!A:A) -> 3094 | C2: 201 | D2: =_xlfn.XLOOKUP(G2,'规范整合泌尿系统医疗服务价格映射表12.11 (2)'!T:T,'规范整合泌尿系统医疗服务价格映射表12.11 (2)'!A:A) -> 2 | E2: 尿流动力学检查费 | F2: =_xlfn.XLOOKUP(G2,Sheet1!F:F,Sheet1!G:G) -> 尿流动力学检测 | G2: 003110000390000-311000039 | I2: 165 | J2: 150 | K2: 127.5 | M2: 165 | N2: 150 | O2: 128 | P2: 1 | Q2: 1 | R2: main | S2: 0 | T2: 184.3 | U2: 13 | V2: 0 | W2: 0 | X2: 0 | Y2: 0 | Z2: 0 | AA2: 0 | AB2: 0 | AC2: =Z2+AA2+AB2 -> 0
A3: 193 | B3: =_xlfn.XLOOKUP(G3,Sheet1!E:E,Sheet1!A:A) -> 3095 | C3: 201 | D3: =_xlfn.XLOOKUP(G3,'规范整合泌尿系统医疗服务价格映射表12.11 (2)'!T:T,'规范整合泌尿系统医疗服务价格映射表12.11 (2)'!A:A) -> 2 | E3: 尿流动力学检查费（尿流率检测） | F3: =_xlfn.XLOOKUP(G3,Sheet1!F:F,Sheet1!G:G) -> 尿流率检测 | G3: 003110000380000-311000038 | I3: 66 | J3: 60 | K3: 51 | M3: 66 | N3: 59 | O3: 51 | P3: 1 | Q3: 1 | R3: main | S3: 0 | T3: 220.3 | U3: 1149.5 | V3: 0 | W3: 0 | X3: -1149.5 | Y3: 0 | Z3: 0 | AA3: -1149.5 | AB3: 0 | AC3: =Z3+AA3+AB3 -> -1149.5
A4: 62 | B4: =_xlfn.XLOOKUP(G4,Sheet1!E:E,Sheet1!A:A) -> 3096 | C4: 201 | D4: =_xlfn.XLOOKUP(G4,'规范整合泌尿系统医疗服务价格映射表12.11 (2)'!T:T,'规范整合泌尿系统医疗服务价格映射表12.11 (2)'!A:A) -> 3 | E4: 泌尿系镜检查费（肾镜） | F4: =_xlfn.XLOOKUP(G4,Sheet1!F:F,Sheet1!G:G) -> 经皮肾盂镜检查 | G4: 003110000180000-311000018 | I4: 660 | J4: 600 | K4: 510 | M4: 660 | N4: 595 | O4: 510 | P4: 1 | Q4: 1 | R4: main | S4: 0 | T4: 55.5 | U4: 12 | V4: 0 | W4: 0 | X4: -60 | Y4: 0 | Z4: 0 | AA4: -60 | AB4: 0 | AC4: =Z4+AA4+AB4 -> -60
A5: 69 | B5: =_xlfn.XLOOKUP(G5,Sheet1!E:E,Sheet1!A:A) -> 3097 | C5: 201 | D5: =_xlfn.XLOOKUP(G5,'规范整合泌尿系统医疗服务价格映射表12.11 (2)'!T:T,'规范整合泌尿系统医疗服务价格映射表12.11 (2)'!A:A) -> 4 | E5: 泌尿系镜检查费（输尿管镜） | F5: =_xlfn.XLOOKUP(G5,Sheet1!F:F,Sheet1!G:G) -> 经尿道输尿管镜检查 | G5: 003110000200000-311000020 | I5: 495 | J5: 450 | K5: 382.5 | M5: 495 | N5: 445 | O5: 380 | P5: 1 | Q5: 1 | R5: main | S5: 0 | T5: 92.61 | U5: 176.8 | V5: 11 | W5: 0 | X5: -884 | Y5: -27.5 | Z5: 0 | AA5: -1041.5 | AB5: -27.5 | AC5: =Z5+AA5+AB5 -> -1069
A6: 10 | B6: =_xlfn.XLOOKUP(G6,Sheet1!E:E,Sheet1!A:A) -> 3098 | C6: 201 | D6: =_xlfn.XLOOKUP(G6,'规范整合泌尿系统医疗服务价格映射表12.11 (2)'!T:T,'规范整合泌尿系统医疗服务价格映射表12.11 (2)'!A:A) -> 分项 | E6: 泌尿系镜检查费（输尿管镜）-精囊镜检查（扩展） | F6: =_xlfn.XLOOKUP(G6,Sheet1!F:F,Sheet1!G:G) -> 经尿道精囊镜检查 | G6: 353111000290000-311100020 | I6: 720 | J6: 648 | K6: 550.8 | M6: 495 | N6: 445 | O6: 380 | P6: 1 | Q6: 1 | R6: main | S6: 0 | T6: 1 | U6: 0 | V6: 0 | W6: -225 | X6: 0 | Y6: 0 | Z6: -225 | AA6: 0 | AB6: 0 | AC6: =Z6+AA6+AB6 -> -225
A7: 11 | B7: =_xlfn.XLOOKUP(G7,Sheet1!E:E,Sheet1!A:A) -> 3099 | C7: 201 | D7: =_xlfn.XLOOKUP(G7,'规范整合泌尿系统医疗服务价格映射表12.11 (2)'!T:T,'规范整合泌尿系统医疗服务价格映射表12.11 (2)'!A:A) -> 5 | E7: 泌尿系镜检查费（膀胱镜尿道镜） | F7: =_xlfn.XLOOKUP(G7,Sheet1!F:F,Sheet1!G:G) -> 膀胱镜尿道镜检查 | G7: 003110000340000-311000034 | I7: 132 | J7: 120 | K7: 102 | M7: 132 | N7: 120 | O7: 102 | P7: 1 | Q7: 1 | R7: main | S7: 0 | T7: 536.3 | U7: 323.8 | V7: 28.5 | W7: 0 | X7: 0 | Y7: 0 | Z7: 0 | AA7: 120 | AB7: 0 | AC7: =Z7+AA7+AB7 -> 120
A8: 61 | B8: =_xlfn.XLOOKUP(G8,Sheet1!E:E,Sheet1!A:A) -> 3100 | C8: 201 | D8: =_xlfn.XLOOKUP(G8,'规范整合泌尿系统医疗服务价格映射表12.11 (2)'!T:T,'规范整合泌尿系统医疗服务价格映射表12.11 (2)'!A:A) -> 7 | E8: 阴茎勃起检查费 | F8: =_xlfn.XLOOKUP(G8,Sheet1!F:F,Sheet1!G:G) -> 夜间阴茎胀大试验 | G8: 003111000030000-311100003 | I8: 99 | J8: 89 | K8: 77 | M8: 99 | N8: 89 | O8: 77 | P8: 1 | Q8: 1 | R8: main | S8: 0 | T8: 6 | U8: 1 | V8: 0 | W8: 0 | X8: 0 | Y8: 0 | Z8: 0 | AA8: 0 | AB8: 0 | AC8: =Z8+AA8+AB8 -> 0
A9: 217 | B9: =_xlfn.XLOOKUP(G9,Sheet1!E:E,Sheet1!A:A) -> 3103 | C9: 201 | D9: =_xlfn.XLOOKUP(G9,'规范整合泌尿系统医疗服务价格映射表12.11 (2)'!T:T,'规范整合泌尿系统医疗服务价格映射表12.11 (2)'!A:A) -> 9 | E9: 阴茎勃起神经检查费 | F9: =_xlfn.XLOOKUP(G9,Sheet1!F:F,Sheet1!G:G) -> 阴茎勃起神经检查 | G9: 003111000050000-311100005 | I9: 110 | J9: 100 | K9: 85 | M9: 110 | N9: 99 | O9: 85 | P9: 1 | Q9: 1 | R9: main | S9: 0 | T9: 0 | U9: 21 | V9: 0 | W9: 0 | X9: -21 | Y9: 0 | Z9: 0 | AA9: -21 | AB9: 0 | AC9: =Z9+AA9+AB9 -> -21
A10: 107 | B10: =_xlfn.XLOOKUP(G10,Sheet1!E:E,Sheet1!A:A) -> 3104 | C10: 201 | D10: =_xlfn.XLOOKUP(G10,'规范整合泌尿系统医疗服务价格映射表12.11 (2)'!T:T,'规范整合泌尿系统医疗服务价格映射表12.11 (2)'!A:A) -> 15 | E10: 血浆置换费 | F10: =_xlfn.XLOOKUP(G10,Sheet1!F:F,Sheet1!G:G) -> 人工肝治疗 | G10: 003109050230000-310905023 | I10: 1500 | J10: 1350 | K10: 1145 | M10: 2250 | N10: 2050 | O10: 1740 | P10: 1 | Q10: 1 | R10: main | S10: 0 | T10: 6 | U10: 11 | V10: 0 | W10: 4500 | X10: 7700 | Y10: 0 | Z10: 4500 | AA10: 7700 | AB10: 0 | AC10: =Z10+AA10+AB10 -> 12200
A11: 78 | B11: =_xlfn.XLOOKUP(G11,Sheet1!E:E,Sheet1!A:A) -> 3108 | C11: 201 | D11: =_xlfn.XLOOKUP(G11,'规范整合泌尿系统医疗服务价格映射表12.11 (2)'!T:T,'规范整合泌尿系统医疗服务价格映射表12.11 (2)'!A:A) -> #N/A | E11: #N/A | F11: =_xlfn.XLOOKUP(G11,Sheet1!F:F,Sheet1!G:G) -> 腹膜透析置管费 | G11: 003110000010000-311000001 | I11: 400 | J11: 400 | K11: 340 | M11: 420 | N11: 395 | O11: 340 | P11: 1 | Q11: 1 | R11: main | S11: 0 | T11: 58 | U11: 35 | V11: 0 | W11: 1160 | X11: -175 | Y11: 0 | Z11: 1160 | AA11: -175 | AB11: 0 | AC11: =Z11+AA11+AB11 -> 985
A12: 48 | B12: =_xlfn.XLOOKUP(G12,Sheet1!E:E,Sheet1!A:A) -> 3111 | C12: 201 | D12: =_xlfn.XLOOKUP(G12,'规范整合泌尿系统医疗服务价格映射表12.11 (2)'!T:T,'规范整合泌尿系统医疗服务价格映射表12.11 (2)'!A:A) -> #N/A | F12: =_xlfn.XLOOKUP(G12,Sheet1!F:F,Sheet1!G:G) -> 腹膜透析导管取出费 | G12: 003110000010100-31100000101 | I12: 400 | J12: 400 | K12: 340 | M12: 420 | N12: 395 | O12: 340 | P12: 1 | Q12: 1 | R12: main | S12: 0 | T12: 24 | U12: 14.5 | V12: 0 | W12: 480 | X12: -72.5 | Y12: 0 | Z12: 480 | AA12: -72.5 | AB12: 0 | AC12: =Z12+AA12+AB12 -> 407.5
A13: 20 | B13: =_xlfn.XLOOKUP(G13,Sheet1!E:E,Sheet1!A:A) -> 3112 | C13: 201 | D13: =_xlfn.XLOOKUP(G13,'规范整合泌尿系统医疗服务价格映射表12.11 (2)'!T:T,'规范整合泌尿系统医疗服务价格映射表12.11 (2)'!A:A) -> 31 | E13: 体外冲击波碎石费 | F13: =_xlfn.XLOOKUP(G13,Sheet1!F:F,Sheet1!G:G) -> 体外冲击波碎石 | G13: 003110000400000-311000040 | I13: 700 | J13: 630 | K13: 535.5 | M13: 700 | N13: 630 | O13: 535 | P13: 1 | Q13: 1 | R13: main | S13: 0 | T13: 159 | U13: 2077 | V13: 3731 | W13: 0 | X13: 0 | Y13: -1865.5 | Z13: 0 | AA13: 1134 | AB13: -1763.5 | AC13: =Z13+AA13+AB13 -> -629.5
A14: 140 | B14: =_xlfn.XLOOKUP(G14,Sheet1!E:E,Sheet1!A:A) -> 3113 | C14: 201 | D14: =_xlfn.XLOOKUP(G14,'规范整合泌尿系统医疗服务价格映射表12.11 (2)'!T:T,'规范整合泌尿系统医疗服务价格映射表12.11 (2)'!A:A) -> 31 | E14: 体外冲击波碎石费（第二次） | F14: =_xlfn.XLOOKUP(G14,Sheet1!F:F,Sheet1!G:G) -> 体外冲击波碎石（第二次） | G14: 003110000400000-31100004003 | I14: 350 | J14: 315 | K14: 267.8 | M14: 350 | N14: 315 | O14: 268 | P14: 1 | Q14: 1 | R14: main | S14: 0 | T14: 7 | U14: 184 | V14: 347 | W14: 0 | X14: 0 | Y14: 69.4 | Z14: 0 | AA14: 0 | AB14: 98 | AC14: =Z14+AA14+AB14 -> 98
A15: 73 | B15: =_xlfn.XLOOKUP(G15,Sheet1!E:E,Sheet1!A:A) -> 3114 | C15: 201 | D15: =_xlfn.XLOOKUP(G15,'规范整合泌尿系统医疗服务价格映射表12.11 (2)'!T:T,'规范整合泌尿系统医疗服务价格映射表12.11 (2)'!A:A) -> 31 | E15: 体外冲击波碎石费（第三次） | F15: =_xlfn.XLOOKUP(G15,Sheet1!F:F,Sheet1!G:G) -> 体外冲击波碎石（第三次） | G15: 003110000400000-31100004006 | I15: 175 | J15: 157.5 | K15: 133.9 | M15: 175 | N15: 158 | O15: 134 | P15: 1 | Q15: 1 | R15: main | S15: 0 | T15: 2 | U15: 9 | V15: 16 | W15: 0 | X15: 4.5 | Y15: 1.6 | Z15: 0 | AA15: 4.5 | AB15: 2.525 | AC15: =Z15+AA15+AB15 -> 7.025
A16: 35 | B16: =_xlfn.XLOOKUP(G16,Sheet1!E:E,Sheet1!A:A) -> 3115 | C16: 201 | D16: =_xlfn.XLOOKUP(G16,'规范整合泌尿系统医疗服务价格映射表12.11 (2)'!T:T,'规范整合泌尿系统医疗服务价格映射表12.11 (2)'!A:A) -> 32 | E16: 泌尿系镜下治疗费（常规） | F16: =_xlfn.XLOOKUP(G16,Sheet1!F:F,Sheet1!G:G) -> 经皮肾盂镜取石术（取异物） | G16: 003110000190200-31100001901 | I16: 880 | J16: 800 | K16: 680 | M16: 815 | N16: 740 | O16: 640 | P16: 1 | Q16: 1 | R16: main | S16: 0 | T16: 1 | U16: 0 | V16: 0 | W16: -65 | X16: 0 | Y16: 0 | Z16: -65 | AA16: 0 | AB16: 0 | AC16: =Z16+AA16+AB16 -> -65
A17: 121 | B17: =_xlfn.XLOOKUP(G17,Sheet1!E:E,Sheet1!A:A) -> 3116 | C17: 201 | D17: =_xlfn.XLOOKUP(G17,'规范整合泌尿系统医疗服务价格映射表12.11 (2)'!T:T,'规范整合泌尿系统医疗服务价格映射表12.11 (2)'!A:A) -> 32 | F17: =_xlfn.XLOOKUP(G17,Sheet1!F:F,Sheet1!G:G) -> 经尿道膀胱碎石取石术 | G17: 003311030270000-331103027 | I17: 1250 | J17: 1200 | K17: 1020 | M17: 815 | N17: 740 | O17: 640 | P17: 1 | Q17: 1 | R17: main | S17: 0 | T17: 71.7 | U17: 112.3 | V17: 6.5 | W17: -31189.5 | X17: -51658 | Y17: -2470 | Z17: -31189.5 | AA17: -50278 | AB17: -2470 | AC17: =Z17+AA17+AB17 -> -83937.5
A18: 142 | B18: =_xlfn.XLOOKUP(G18,Sheet1!E:E,Sheet1!A:A) -> 3124 | C18: 201 | D18: =_xlfn.XLOOKUP(G18,'规范整合泌尿系统医疗服务价格映射表12.11 (2)'!T:T,'规范整合泌尿系统医疗服务价格映射表12.11 (2)'!A:A) -> 33 | E18: 泌尿系镜下治疗费（特殊） | F18: =_xlfn.XLOOKUP(G18,Sheet1!F:F,Sheet1!G:G) -> 经输尿管镜碎石取石术 | G18: 003110000260000-311000026 | I18: 990 | J18: 900 | K18: 765 | M18: 2370 | N18: 2145 | O18: 1850 | P18: 1 | Q18: 1 | R18: main | S18: 0 | T18: 29 | U18: 11 | V18: 1 | W18: 40020 | X18: 13695 | Y18: 1085 | Z18: 40020 | AA18: 13695 | AB18: 1085 | AC18: =Z18+AA18+AB18 -> 54800
A19: 164 | B19: =_xlfn.XLOOKUP(G19,Sheet1!E:E,Sheet1!A:A) -> 3125 | C19: 201 | D19: =_xlfn.XLOOKUP(G19,'规范整合泌尿系统医疗服务价格映射表12.11 (2)'!T:T,'规范整合泌尿系统医疗服务价格映射表12.11 (2)'!A:A) -> 33 | F19: =_xlfn.XLOOKUP(G19,Sheet1!F:F,Sheet1!G:G) -> 经输尿管镜碎石取石术（弹道法） | G19: 003110000260000-31100002601 | I19: 1100 | J19: 1000 | K19: 850 | M19: 2370 | N19: 2145 | O19: 1850 | P19: 1 | Q19: 1 | R19: main | S19: 0 | T19: 17.5 | U19: 13.5 | V19: 0 | W19: 22225 | X19: 15457.5 | Y19: 0 | Z19: 22225 | AA19: 14957.5 | AB19: 0 | AC19: =Z19+AA19+AB19 -> 37182.5
A20: 24 | B20: =_xlfn.XLOOKUP(G20,Sheet1!E:E,Sheet1!A:A) -> 3126 | C20: 201 | D20: =_xlfn.XLOOKUP(G20,'规范整合泌尿系统医疗服务价格映射表12.11 (2)'!T:T,'规范整合泌尿系统医疗服务价格映射表12.11 (2)'!A:A) -> 33 | F20: =_xlfn.XLOOKUP(G20,Sheet1!F:F,Sheet1!G:G) -> 经输尿管镜碎石取石术（激光法） | G20: 003110000260000-31100002602 | I20: 1760 | J20: 1600 | K20: 1360 | M20: 2370 | N20: 2145 | O20: 1850 | P20: 1 | Q20: 1 | R20: main | S20: 0 | T20: 2551.5 | U20: 4352.5 | V20: 831 | W20: 1556415 | X20: 2372112.5 | Y20: 407190 | Z20: 1556415 | AA20: 2411472.5 | AB20: 407190 | AC20: =Z20+AA20+AB20 -> 4375077.5
A21: 58 | B21: =_xlfn.XLOOKUP(G21,Sheet1!E:E,Sheet1!A:A) -> 3127 | C21: 201 | D21: =_xlfn.XLOOKUP(G21,'规范整合泌尿系统医疗服务价格映射表12.11 (2)'!T:T,'规范整合泌尿系统医疗服务价格映射表12.11 (2)'!A:A) -> 33 | F21: =_xlfn.XLOOKUP(G21,Sheet1!F:F,Sheet1!G:G) -> 经膀胱镜尿道镜特殊治疗 | G21: 003110000350000-311000035 | I21: 176 | J21: 160 | K21: 136 | M21: 2007 | N21: 1820 | O21: 1572 | P21: 1 | Q21: 1 | R21: main | S21: 0 | T21: 11 | U21: 10 | V21: 0 | W21: 20141 | X21: 16600 | Y21: 0 | Z21: 20141 | AA21: 16584 | AB21: 0 | AC21: =Z21+AA21+AB21 -> 36725
A22: 158 | B22: =_xlfn.XLOOKUP(G22,Sheet1!E:E,Sheet1!A:A) -> 3128 | C22: 201 | D22: =_xlfn.XLOOKUP(G22,'规范整合泌尿系统医疗服务价格映射表12.11 (2)'!T:T,'规范整合泌尿系统医疗服务价格映射表12.11 (2)'!A:A) -> 33 | F22: =_xlfn.XLOOKUP(G22,Sheet1!F:F,Sheet1!G:G) -> 经膀胱镜尿道镜特殊治疗（激光法） | G22: 003110000350000-31100003501 | I22: 231 | J22: 210 | K22: 178.5 | M22: 2007 | N22: 1820 | O22: 1572 | P22: 1 | Q22: 1 | R22: main | S22: 0 | T22: 2 | U22: 7 | V22: 0 | W22: 3552 | X22: 11270 | Y22: 0 | Z22: 3552 | AA22: 11270 | AB22: 0 | AC22: =Z22+AA22+AB22 -> 14822
A23: 199 | B23: =_xlfn.XLOOKUP(G23,Sheet1!E:E,Sheet1!A:A) -> 3129 | C23: 201 | D23: =_xlfn.XLOOKUP(G23,'规范整合泌尿系统医疗服务价格映射表12.11 (2)'!T:T,'规范整合泌尿系统医疗服务价格映射表12.11 (2)'!A:A) -> 33 | F23: =_xlfn.XLOOKUP(G23,Sheet1!F:F,Sheet1!G:G) -> 经尿道膀胱肿瘤特殊治疗 | G23: 003311030260000-331103026 | I23: 2530 | J23: 2280 | K23: 1940 | M23: 1875 | N23: 1700 | O23: 1470 | P23: 1 | Q23: 1 | R23: main | S23: 0 | T23: 14.8 | U23: 16 | V23: 0.5 | W23: -9694 | X23: -9280 | Y23: -235 | Z23: -9694 | AA23: -9280 | AB23: -235 | AC23: =Z23+AA23+AB23 -> -19209
A24: 88 | B24: =_xlfn.XLOOKUP(G24,Sheet1!E:E,Sheet1!A:A) -> 3130 | C24: 201 | D24: =_xlfn.XLOOKUP(G24,'规范整合泌尿系统医疗服务价格映射表12.11 (2)'!T:T,'规范整合泌尿系统医疗服务价格映射表12.11 (2)'!A:A) -> 33 | F24: =_xlfn.XLOOKUP(G24,Sheet1!F:F,Sheet1!G:G) -> 经尿道膀胱肿瘤特殊治疗（电切法） | G24: 003311030260000-33110302601 | I24: 2590 | J24: 2330 | K24: 1980 | M24: 1875 | N24: 1700 | O24: 1470 | P24: 1 | Q24: 1 | R24: main | S24: 0 | T24: 69.5 | U24: 121 | V24: 10.5 | W24: -49692.5 | X24: -76230 | Y24: -5355 | Z24: -49692.5 | AA24: -72385 | AB24: -5355 | AC24: =Z24+AA24+AB24 -> -127432.5
A25: 165 | B25: =_xlfn.XLOOKUP(G25,Sheet1!E:E,Sheet1!A:A) -> 3133 | C25: 201 | D25: =_xlfn.XLOOKUP(G25,'规范整合泌尿系统医疗服务价格映射表12.11 (2)'!T:T,'规范整合泌尿系统医疗服务价格映射表12.11 (2)'!A:A) -> 33 | F25: =_xlfn.XLOOKUP(G25,Sheet1!F:F,Sheet1!G:G) -> 经膀胱镜下经尿道膀胱肿瘤特殊治疗 | G25: 003311030260000-33110302604 | I25: 2780 | J25: 2505 | K25: 2130 | M25: 2007 | N25: 1820 | O25: 1572 | P25: 1 | Q25: 1 | R25: main | S25: 0 | T25: 235.5 | U25: 54 | V25: 3 | W25: -182041.5 | X25: -36990 | Y25: -1674 | Z25: -182041.5 | AA25: -36990 | AB25: -1674 | AC25: =Z25+AA25+AB25 -> -220705.5
A26: 111 | B26: =_xlfn.XLOOKUP(G26,Sheet1!E:E,Sheet1!A:A) -> 3134 | C26: 201 | D26: =_xlfn.XLOOKUP(G26,'规范整合泌尿系统医疗服务价格映射表12.11 (2)'!T:T,'规范整合泌尿系统医疗服务价格映射表12.11 (2)'!A:A) -> 33 | F26: =_xlfn.XLOOKUP(G26,Sheet1!F:F,Sheet1!G:G) -> 经膀胱镜下经尿道膀胱肿瘤特殊治疗（电切法） | G26: 003311030260000-33110302605 | I26: 2840 | J26: 2555 | K26: 2170 | M26: 2007 | N26: 1820 | O26: 1572 | P26: 1 | Q26: 1 | R26: main | S26: 0 | T26: 136.3 | U26: 101 | V26: 9 | W26: -113537.9 | X26: -74235 | Y26: -5382 | Z26: -113537.9 | AA26: -72572.5 | AB26: -5382 | AC26: =Z26+AA26+AB26 -> -191492.4
A27: 108 | B27: =_xlfn.XLOOKUP(G27,Sheet1!E:E,Sheet1!A:A) -> 3137 | C27: 201 | D27: =_xlfn.XLOOKUP(G27,'规范整合泌尿系统医疗服务价格映射表12.11 (2)'!T:T,'规范整合泌尿系统医疗服务价格映射表12.11 (2)'!A:A) -> 33 | F27: =_xlfn.XLOOKUP(G27,Sheet1!F:F,Sheet1!G:G) -> 膀胱镜下经尿道膀胱碎石取石术 | G27: 003311030270000-33110302702 | I27: 1500 | J27: 1425 | K27: 1210 | M27: 2007 | N27: 1820 | O27: 1572 | P27: 1 | Q27: 1 | R27: main | S27: 0 | T27: 144.3 | U27: 253.5 | V27: 49 | W27: 73160.1 | X27: 100132.5 | Y27: 17738 | Z27: 73160.1 | AA27: 101557.5 | AB27: 17738 | AC27: =Z27+AA27+AB27 -> 192455.6
A28: 208 | B28: =_xlfn.XLOOKUP(G28,Sheet1!E:E,Sheet1!A:A) -> 3138 | C28: 201 | D28: =_xlfn.XLOOKUP(G28,'规范整合泌尿系统医疗服务价格映射表12.11 (2)'!T:T,'规范整合泌尿系统医疗服务价格映射表12.11 (2)'!A:A) -> 33 | F28: =_xlfn.XLOOKUP(G28,Sheet1!F:F,Sheet1!G:G) -> 小儿膀胱镜下经尿道膀胱碎石取石术 | G28: 003311030270000-33110302703 | I28: 1875 | J28: 1785 | K28: 1515 | M28: 2007 | N28: 1820 | O28: 1572 | P28: 1 | Q28: 1 | R28: main | S28: 0 | T28: 1 | U28: 0 | V28: 0 | W28: 132 | X28: 0 | Y28: 0 | Z28: 132 | AA28: 0 | AB28: 0 | AC28: =Z28+AA28+AB28 -> 132
A29: 105 | B29: =_xlfn.XLOOKUP(G29,Sheet1!E:E,Sheet1!A:A) -> 3139 | C29: 201 | D29: =_xlfn.XLOOKUP(G29,'规范整合泌尿系统医疗服务价格映射表12.11 (2)'!T:T,'规范整合泌尿系统医疗服务价格映射表12.11 (2)'!A:A) -> 33 | F29: =_xlfn.XLOOKUP(G29,Sheet1!F:F,Sheet1!G:G) -> 经尿道前列腺电切术 | G29: 003312010060000-331201006 | I29: 2530 | J29: 2280 | K29: 1940 | M29: 1875 | N29: 1700 | O29: 1470 | P29: 1 | Q29: 1 | R29: main | S29: 0 | T29: 1 | U29: 3 | V29: 0 | W29: -655 | X29: -1740 | Y29: 0 | Z29: -655 | AA29: -1740 | AB29: 0 | AC29: =Z29+AA29+AB29 -> -2395
A30: 74 | B30: =_xlfn.XLOOKUP(G30,Sheet1!E:E,Sheet1!A:A) -> 3140 | C30: 201 | D30: =_xlfn.XLOOKUP(G30,'规范整合泌尿系统医疗服务价格映射表12.11 (2)'!T:T,'规范整合泌尿系统医疗服务价格映射表12.11 (2)'!A:A) -> 33 | F30: =_xlfn.XLOOKUP(G30,Sheet1!F:F,Sheet1!G:G) -> 经尿道前列腺电切术（电切法） | G30: 003312010060000-33120100601 | I30: 3635 | J30: 3270 | K30: 2780 | M30: 1875 | N30: 1700 | O30: 1470 | P30: 1 | Q30: 1 | R30: main | S30: 0 | T30: 4 | U30: 4 | V30: 0 | W30: -7040 | X30: -6280 | Y30: 0 | Z30: -5195 | AA30: -3670 | AB30: 0 | AC30: =Z30+AA30+AB30 -> -8865
... A37: 182 | B37: =_xlfn.XLOOKUP(G37,Sheet1!E:E,Sheet1!A:A) -> 3158 | C37: 201 | D37: =_xlfn.XLOOKUP(G37,'规范整合泌尿系统医疗服务价格映射表12.11 (2)'!T:T,'规范整合泌尿系统医疗服务价格映射表12.11 (2)'!A:A) -> 33 | F37: =_xlfn.XLOOKUP(G37,Sheet1!F:F,Sheet1!G:G) -> 经皮肾镜碎石取石术（两种及以上方法加收20%） | G37: 353110000440000-A33120301801 | I37: 0 | J37: 0 | K37: 0 | M37: 0 | N37: 0 | O37: 0 | P37: 1 | Q37: 1 | R37: main | S37: 0 | T37: 38 | U37: 0 | V37: 0 | W37: 0 | X37: 0 | Y37: 0 | Z37: -34740 | AA37: 0 | AB37: 0 | AC37: =Z37+AA37+AB37 -> -34740
A38: 57 | B38: =_xlfn.XLOOKUP(G38,Sheet1!E:E,Sheet1!A:A) -> 3159 | C38: 201 | D38: =_xlfn.XLOOKUP(G38,'规范整合泌尿系统医疗服务价格映射表12.11 (2)'!T:T,'规范整合泌尿系统医疗服务价格映射表12.11 (2)'!A:A) -> 34 | E38: 泌尿系异物取出费 | F38: =_xlfn.XLOOKUP(G38,Sheet1!F:F,Sheet1!G:G) -> 尿道切开取石术 | G38: 003311040050000-331104005 | I38: 1125 | J38: 1080 | K38: 918 | M38: 1125 | N38: 1080 | O38: 918 | P38: 1 | Q38: 1 | R38: main | S38: 0 | T38: 0 | U38: 2 | V38: 1 | W38: 0 | X38: 0 | Y38: 0 | Z38: 0 | AA38: 540 | AB38: 0 | AC38: =Z38+AA38+AB38 -> 540
A39: 84 | B39: =_xlfn.XLOOKUP(G39,Sheet1!E:E,Sheet1!A:A) -> 3160 | C39: 201 | D39: =_xlfn.XLOOKUP(G39,'规范整合泌尿系统医疗服务价格映射表12.11 (2)'!T:T,'规范整合泌尿系统医疗服务价格映射表12.11 (2)'!A:A) -> 35 | E39: 泌尿系取石费 | F39: =_xlfn.XLOOKUP(G39,Sheet1!F:F,Sheet1!G:G) -> 膀胱切开取石术 | G39: 003311030010000-331103001 | I39: 1000 | J39: 960 | K39: 816 | M39: 1250 | N39: 1200 | O39: 1020 | P39: 1 | Q39: 1 | R39: main | S39: 0 | T39: 11.5 | U39: 7 | V39: 0 | W39: 2875 | X39: 1680 | Y39: 0 | Z39: 2875 | AA39: 1680 | AB39: 0 | AC39: =Z39+AA39+AB39 -> 4555
A40: 68 | B40: =_xlfn.XLOOKUP(G40,Sheet1!E:E,Sheet1!A:A) -> 3163 | C40: 201 | D40: =_xlfn.XLOOKUP(G40,'规范整合泌尿系统医疗服务价格映射表12.11 (2)'!T:T,'规范整合泌尿系统医疗服务价格映射表12.11 (2)'!A:A) -> 分项 | E40: 泌尿系取石费-上尿路（加收） | F40: =_xlfn.XLOOKUP(G40,Sheet1!F:F,Sheet1!G:G) -> 肾切开取石术 | G40: 003311010160000-331101016 | I40: 2530 | J40: 2280 | K40: 1940 | M40: 2420 | N40: 2320 | O40: 1970 | P40: 1 | Q40: 1 | R40: main | S40: 0 | T40: 1.5 | U40: 3.5 | V40: 0 | W40: -165 | X40: 140 | Y40: 0 | Z40: -165 | AA40: 140 | AB40: 0 | AC40: =Z40+AA40+AB40 -> -25
A41: 139 | B41: =_xlfn.XLOOKUP(G41,Sheet1!E:E,Sheet1!A:A) -> 3165 | C41: 201 | D41: =_xlfn.XLOOKUP(G41,'规范整合泌尿系统医疗服务价格映射表12.11 (2)'!T:T,'规范整合泌尿系统医疗服务价格映射表12.11 (2)'!A:A) -> 分项 | F41: =_xlfn.XLOOKUP(G41,Sheet1!F:F,Sheet1!G:G) -> 经腹腔镜肾切开取石术 | G41: 003311010160000-33110101602 | I41: 3155 | J41: 2880 | K41: 2450 | M41: 2420 | N41: 2320 | O41: 1970 | P41: 1 | Q41: 1 | R41: main | S41: 0 | T41: 12 | U41: 2 | V41: 0 | W41: -8820 | X41: -1120 | Y41: 0 | Z41: -8820 | AA41: -1120 | AB41: 0 | AC41: =Z41+AA41+AB41 -> -9940
A42: 154 | B42: =_xlfn.XLOOKUP(G42,Sheet1!E:E,Sheet1!A:A) -> 3167 | C42: 201 | D42: =_xlfn.XLOOKUP(G42,'规范整合泌尿系统医疗服务价格映射表12.11 (2)'!T:T,'规范整合泌尿系统医疗服务价格映射表12.11 (2)'!A:A) -> 分项 | F42: =_xlfn.XLOOKUP(G42,Sheet1!F:F,Sheet1!G:G) -> 输尿管切开取石术 | G42: 003311020070000-331102007 | I42: 1690 | J42: 1520 | K42: 1290 | M42: 2420 | N42: 2320 | O42: 1970 | P42: 1 | Q42: 1 | R42: main | S42: 0 | T42: 3 | U42: 2 | V42: 0 | W42: 2190 | X42: 1600 | Y42: 0 | Z42: 2190 | AA42: 1600 | AB42: 0 | AC42: =Z42+AA42+AB42 -> 3790
A43: 80 | B43: =_xlfn.XLOOKUP(G43,Sheet1!E:E,Sheet1!A:A) -> 3169 | C43: 201 | D43: =_xlfn.XLOOKUP(G43,'规范整合泌尿系统医疗服务价格映射表12.11 (2)'!T:T,'规范整合泌尿系统医疗服务价格映射表12.11 (2)'!A:A) -> 分项 | F43: =_xlfn.XLOOKUP(G43,Sheet1!F:F,Sheet1!G:G) -> 经腹腔镜输尿管切开取石术 | G43: 003311020070001-33110200702 | I43: 2315 | J43: 2120 | K43: 1300 | M43: 2420 | N43: 2320 | O43: 1970 | P43: 1 | Q43: 1 | R43: main | S43: 0 | T43: 37 | U43: 13 | V43: 2 | W43: 3885 | X43: 2600 | Y43: 1340 | Z43: 3885 | AA43: 2600 | AB43: 1340 | AC43: =Z43+AA43+AB43 -> 7825
A44: 152 | B44: =_xlfn.XLOOKUP(G44,Sheet1!E:E,Sheet1!A:A) -> 3175 | C44: 201 | D44: =_xlfn.XLOOKUP(G44,'规范整合泌尿系统医疗服务价格映射表12.11 (2)'!T:T,'规范整合泌尿系统医疗服务价格映射表12.11 (2)'!A:A) -> 36 | E44: 泌尿系造瘘费 | F44: =_xlfn.XLOOKUP(G44,Sheet1!F:F,Sheet1!G:G) -> 经皮输尿管内管置入术 | G44: 003110000220000-311000022 | I44: 440 | J44: 400 | K44: 340 | M44: 355 | N44: 320 | O44: 285 | P44: 1 | Q44: 1 | R44: main | S44: 0 | T44: 74.5 | U44: 81.5 | V44: 0.5 | W44: -6332.5 | X44: -6520 | Y44: -27.5 | Z44: -6332.5 | AA44: -6520 | AB44: -27.5 | AC44: =Z44+AA44+AB44 -> -12880
A45: 99 | B45: =_xlfn.XLOOKUP(G45,Sheet1!E:E,Sheet1!A:A) -> 3176 | C45: 201 | D45: =_xlfn.XLOOKUP(G45,'规范整合泌尿系统医疗服务价格映射表12.11 (2)'!T:T,'规范整合泌尿系统医疗服务价格映射表12.11 (2)'!A:A) -> 36 | F45: =_xlfn.XLOOKUP(G45,Sheet1!F:F,Sheet1!G:G) -> 膀胱穿刺造瘘术 | G45: 003110000330000-311000033 | I45: 225 | J45: 205 | K45: 175 | M45: 355 | N45: 320 | O45: 285 | P45: 1 | Q45: 1 | R45: main | S45: 0 | T45: 39.41 | U45: 31.7 | V45: 0 | W45: 5123.3 | X45: 3645.5 | Y45: 0 | Z45: 5123.3 | AA45: 3645.5 | AB45: 0 | AC45: =Z45+AA45+AB45 -> 8768.8
A46: 29 | B46: =_xlfn.XLOOKUP(G46,Sheet1!E:E,Sheet1!A:A) -> 3177 | C46: 201 | D46: =_xlfn.XLOOKUP(G46,'规范整合泌尿系统医疗服务价格映射表12.11 (2)'!T:T,'规范整合泌尿系统医疗服务价格映射表12.11 (2)'!A:A) -> 36 | F46: =_xlfn.XLOOKUP(G46,Sheet1!F:F,Sheet1!G:G) -> 膀胱造瘘术 | G46: 003311030050000-331103005 | I46: 1000 | J46: 960 | K46: 816 | M46: 355 | N46: 320 | O46: 285 | P46: 1 | Q46: 1 | R46: main | S46: 0 | T46: 58.5 | U46: 27.8 | V46: 5.5 | W46: -37732.5 | X46: -17792 | Y46: -2920.5 | Z46: -37732.5 | AA46: -17852 | AB46: -2920.5 | AC46: =Z46+AA46+AB46 -> -58505
A47: 148 | B47: =_xlfn.XLOOKUP(G47,Sheet1!E:E,Sheet1!A:A) -> 3178 | C47: 201 | D47: =_xlfn.XLOOKUP(G47,'规范整合泌尿系统医疗服务价格映射表12.11 (2)'!T:T,'规范整合泌尿系统医疗服务价格映射表12.11 (2)'!A:A) -> 36 | F47: =_xlfn.XLOOKUP(G47,Sheet1!F:F,Sheet1!G:G) -> 尿道会阴造口术 | G47: 003311040170000-331104017 | I47: 875 | J47: 840 | K47: 714 | M47: 355 | N47: 320 | O47: 285 | P47: 1 | Q47: 1 | R47: main | S47: 0 | T47: 0 | U47: 1 | V47: 0 | W47: 0 | X47: -520 | Y47: 0 | Z47: 0 | AA47: -520 | AB47: 0 | AC47: =Z47+AA47+AB47 -> -520
A48: 51 | B48: =_xlfn.XLOOKUP(G48,Sheet1!E:E,Sheet1!A:A) -> 3179 | C48: 201 | D48: =_xlfn.XLOOKUP(G48,'规范整合泌尿系统医疗服务价格映射表12.11 (2)'!T:T,'规范整合泌尿系统医疗服务价格映射表12.11 (2)'!A:A) -> 分项 | E48: 泌尿系造瘘费-上尿路（加收） | F48: =_xlfn.XLOOKUP(G48,Sheet1!F:F,Sheet1!G:G) -> 肾实质切开造瘘术 | G48: 003311010130000-331101013 | I48: 1500 | J48: 1440 | K48: 1224 | M48: 1500 | N48: 1440 | O48: 1285 | P48: 1 | Q48: 1 | R48: main | S48: 0 | T48: 25 | U48: 8.5 | V48: 0 | W48: 0 | X48: 0 | Y48: 0 | Z48: 0 | AA48: -210 | AB48: 0 | AC48: =Z48+AA48+AB48 -> -210
A49: 38 | B49: =_xlfn.XLOOKUP(G49,Sheet1!E:E,Sheet1!A:A) -> 3184 | C49: 201 | D49: =_xlfn.XLOOKUP(G49,'规范整合泌尿系统医疗服务价格映射表12.11 (2)'!T:T,'规范整合泌尿系统医疗服务价格映射表12.11 (2)'!A:A) -> 分项 | E49: 泌尿系造瘘费-儿童（加收） | F49: =_xlfn.XLOOKUP(G49,Sheet1!F:F,Sheet1!G:G) -> 小儿膀胱造瘘术 | G49: 003311030050000-33110300501 | I49: 1300 | J49: 1250 | K49: 1065 | M49: 460 | N49: 416 | O49: 371 | P49: 1 | Q49: 1 | R49: main | S49: 0 | T49: 4 | U49: 0 | V49: 0 | W49: -3360 | X49: 0 | Y49: 0 | Z49: -3360 | AA49: 0 | AB49: 0 | AC49: =Z49+AA49+AB49 -> -3360
A50: 109 | B50: =_xlfn.XLOOKUP(G50,Sheet1!E:E,Sheet1!A:A) -> 3188 | C50: 201 | D50: =_xlfn.XLOOKUP(G50,'规范整合泌尿系统医疗服务价格映射表12.11 (2)'!T:T,'规范整合泌尿系统医疗服务价格映射表12.11 (2)'!A:A) -> 37 | E50: 泌尿道瘘修补费 | F50: =_xlfn.XLOOKUP(G50,Sheet1!F:F,Sheet1!G:G) -> 尿道瘘修补术 | G50: 003311040180000-331104018 | I50: 1250 | J50: 1200 | K50: 1020 | M50: 1360 | N50: 1225 | O50: 1050 | P50: 1 | Q50: 1 | R50: main | S50: 0 | T50: 3 | U50: 0 | V50: 0 | W50: 330 | X50: 0 | Y50: 0 | Z50: 330 | AA50: 0 | AB50: 0 | AC50: =Z50+AA50+AB50 -> 330
A51: 43 | B51: =_xlfn.XLOOKUP(G51,Sheet1!E:E,Sheet1!A:A) -> 3189 | C51: 201 | D51: =_xlfn.XLOOKUP(G51,'规范整合泌尿系统医疗服务价格映射表12.11 (2)'!T:T,'规范整合泌尿系统医疗服务价格映射表12.11 (2)'!A:A) -> 分项 | E51: 泌尿道瘘修补费-儿童（加收） | F51: =_xlfn.XLOOKUP(G51,Sheet1!F:F,Sheet1!G:G) -> 小儿尿道直肠瘘修补术 | G51: 003311040150000-33110401501 | I51: 3290 | J51: 2965 | K51: 2520 | M51: 1770 | N51: 1590 | O51: 1365 | P51: 1 | Q51: 1 | R51: main | S51: 0 | T51: 1 | U51: 0 | V51: 0 | W51: -1520 | X51: 0 | Y51: 0 | Z51: 125 | AA51: 0 | AB51: 0 | AC51: =Z51+AA51+AB51 -> 125
A52: 127 | B52: =_xlfn.XLOOKUP(G52,Sheet1!E:E,Sheet1!A:A) -> 3191 | C52: 201 | D52: =_xlfn.XLOOKUP(G52,'规范整合泌尿系统医疗服务价格映射表12.11 (2)'!T:T,'规范整合泌尿系统医疗服务价格映射表12.11 (2)'!A:A) -> 分项 | F52: =_xlfn.XLOOKUP(G52,Sheet1!F:F,Sheet1!G:G) -> 小儿尿道瘘修补术 | G52: 003311040180000-33110401801 | I52: 1625 | J52: 1560 | K52: 1325 | M52: 1770 | N52: 1590 | O52: 1365 | P52: 1 | Q52: 1 | R52: main | S52: 0 | T52: 4 | U52: 0 | V52: 0 | W52: 580 | X52: 0 | Y52: 0 | Z52: 580 | AA52: 0 | AB52: 0 | AC52: =Z52+AA52+AB52 -> 580
A53: 157 | B53: =_xlfn.XLOOKUP(G53,Sheet1!E:E,Sheet1!A:A) -> 3192 | C53: 201 | D53: =_xlfn.XLOOKUP(G53,'规范整合泌尿系统医疗服务价格映射表12.11 (2)'!T:T,'规范整合泌尿系统医疗服务价格映射表12.11 (2)'!A:A) -> 38 | E53: 肾穿刺费 | F53: =_xlfn.XLOOKUP(G53,Sheet1!F:F,Sheet1!G:G) -> 肾穿刺术 | G53: 003110000150000-311000015 | I53: 145 | J53: 130 | K53: 110 | M53: 175 | N53: 160 | O53: 135 | P53: 1 | Q53: 1 | R53: main | S53: 0 | T53: 931 | U53: 270 | V53: 6 | W53: 27930 | X53: 8100 | Y53: 150 | Z53: 27930 | AA53: 8100 | AB53: 150 | AC53: =Z53+AA53+AB53 -> 36180
A54: 64 | B54: =_xlfn.XLOOKUP(G54,Sheet1!E:E,Sheet1!A:A) -> 3193 | C54: 201 | D54: =_xlfn.XLOOKUP(G54,'规范整合泌尿系统医疗服务价格映射表12.11 (2)'!T:T,'规范整合泌尿系统医疗服务价格映射表12.11 (2)'!A:A) -> 分项 | E54: 肾穿刺费-肾周脓肿引流（加收） | F54: =_xlfn.XLOOKUP(G54,Sheet1!F:F,Sheet1!G:G) -> 肾周脓肿引流术 | G54: 003110000170000-311000017 | I54: 220 | J54: 200 | K54: 170 | M54: 235 | N54: 215 | O54: 182 | P54: 1 | Q54: 1 | R54: main | S54: 0 | T54: 3 | U54: 66 | V54: 0 | W54: 45 | X54: 990 | Y54: 0 | Z54: 45 | AA54: 990 | AB54: 0 | AC54: =Z54+AA54+AB54 -> 1035
A55: 120 | B55: =_xlfn.XLOOKUP(G55,Sheet1!E:E,Sheet1!A:A) -> 3194 | C55: 201 | D55: =_xlfn.XLOOKUP(G55,'规范整合泌尿系统医疗服务价格映射表12.11 (2)'!T:T,'规范整合泌尿系统医疗服务价格映射表12.11 (2)'!A:A) -> 分项 | F55: =_xlfn.XLOOKUP(G55,Sheet1!F:F,Sheet1!G:G) -> 肾周脓肿引流术（切开引流） | G55: 003110000170000-31100001701 | I55: 880 | J55: 800 | K55: 680 | M55: 235 | N55: 215 | O55: 182 | P55: 1 | Q55: 1 | R55: main | S55: 0 | T55: 3 | U55: 1 | V55: 0 | W55: -1935 | X55: -585 | Y55: 0 | Z55: -1935 | AA55: -585 | AB55: 0 | AC55: =Z55+AA55+AB55 -> -2520
A56: 218 | B56: =_xlfn.XLOOKUP(G56,Sheet1!E:E,Sheet1!A:A) -> 3195 | C56: 201 | D56: =_xlfn.XLOOKUP(G56,'规范整合泌尿系统医疗服务价格映射表12.11 (2)'!T:T,'规范整合泌尿系统医疗服务价格映射表12.11 (2)'!A:A) -> 分项 | F56: =_xlfn.XLOOKUP(G56,Sheet1!F:F,Sheet1!G:G) -> 肾周脓肿引流术（积液引流） | G56: 003110000170100-31100001702 | I56: 220 | J56: 200 | K56: 170 | M56: 235 | N56: 215 | O56: 182 | P56: 1 | Q56: 1 | R56: main | S56: 0 | T56: 0 | U56: 11 | V56: 0 | W56: 0 | X56: 165 | Y56: 0 | Z56: 0 | AA56: 165 | AB56: 0 | AC56: =Z56+AA56+AB56 -> 165
A57: 13 | B57: =_xlfn.XLOOKUP(G57,Sheet1!E:E,Sheet1!A:A) -> 3199 | C57: 201 | D57: =_xlfn.XLOOKUP(G57,'规范整合泌尿系统医疗服务价格映射表12.11 (2)'!T:T,'规范整合泌尿系统医疗服务价格映射表12.11 (2)'!A:A) -> 39 | E57: 肾周围淋巴管剥脱费 | F57: =_xlfn.XLOOKUP(G57,Sheet1!F:F,Sheet1!G:G) -> 经腹腔镜肾周围淋巴管剥脱术 | G57: 003311010050000-33110100502 | I57: 3155 | J57: 2880 | K57: 2450 | M57: 3155 | N57: 2880 | O57: 2450 | P57: 1 | Q57: 1 | R57: main | S57: 0 | T57: 9 | U57: 0 | V57: 0 | W57: 0 | X57: 0 | Y57: 0 | Z57: 0 | AA57: 0 | AB57: 0 | AC57: =Z57+AA57+AB57 -> 0
A58: 221 | B58: =_xlfn.XLOOKUP(G58,Sheet1!E:E,Sheet1!A:A) -> 3218 | C58: 201 | D58: =_xlfn.XLOOKUP(G58,'规范整合泌尿系统医疗服务价格映射表12.11 (2)'!T:T,'规范整合泌尿系统医疗服务价格映射表12.11 (2)'!A:A) -> 43 | E58: 肾囊肿去顶费 | F58: =_xlfn.XLOOKUP(G58,Sheet1!F:F,Sheet1!G:G) -> 肾囊肿切除术 | G58: 003311010140000-331101014 | I58: 1500 | J58: 1440 | K58: 1224 | M58: 2000 | N58: 1850 | O58: 1580 | P58: 1 | Q58: 1 | R58: main | S58: 0 | T58: 12.5 | U58: 6.5 | V58: 0.5 | W58: 6250 | X58: 2665 | Y58: 178 | Z58: 6250 | AA58: 2665 | AB58: 178 | AC58: =Z58+AA58+AB58 -> 9093
A59: 163 | B59: =_xlfn.XLOOKUP(G59,Sheet1!E:E,Sheet1!A:A) -> 3219 | C59: 201 | D59: =_xlfn.XLOOKUP(G59,'规范整合泌尿系统医疗服务价格映射表12.11 (2)'!T:T,'规范整合泌尿系统医疗服务价格映射表12.11 (2)'!A:A) -> 43 | F59: =_xlfn.XLOOKUP(G59,Sheet1!F:F,Sheet1!G:G) -> 经腹腔镜肾囊肿切除术 | G59: 003311010140001-33110101402 | I59: 2125 | J59: 2040 | K59: 1734 | M59: 2040 | N59: 1850 | O59: 1580 | P59: 1 | Q59: 1 | R59: main | S59: 0 | T59: 209 | U59: 113 | V59: 5 | W59: -26125 | X59: -21470 | Y59: -770 | Z59: -26125 | AA59: -21470 | AB59: -770 | AC59: =Z59+AA59+AB59 -> -48365
A60: 132 | B60: =_xlfn.XLOOKUP(G60,Sheet1!E:E,Sheet1!A:A) -> 3220 | C60: 201 | D60: =_xlfn.XLOOKUP(G60,'规范整合泌尿系统医疗服务价格映射表12.11 (2)'!T:T,'规范整合泌尿系统医疗服务价格映射表12.11 (2)'!A:A) -> 43 | F60: =_xlfn.XLOOKUP(G60,Sheet1!F:F,Sheet1!G:G) -> 多囊肾去顶减压术 | G60: 003311010150000-331101015 | I60: 2360 | J60: 2120 | K60: 1800 | M60: 2000 | N60: 1850 | O60: 1580 | P60: 1 | Q60: 1 | R60: main | S60: 0 | T60: 1 | U60: 1.5 | V60: 0 | W60: -360 | X60: -405 | Y60: 0 | Z60: -360 | AA60: -405 | AB60: 0 | AC60: =Z60+AA60+AB60 -> -765
A61: 207 | B61: =_xlfn.XLOOKUP(G61,Sheet1!E:E,Sheet1!A:A) -> 3221 | C61: 201 | D61: =_xlfn.XLOOKUP(G61,'规范整合泌尿系统医疗服务价格映射表12.11 (2)'!T:T,'规范整合泌尿系统医疗服务价格映射表12.11 (2)'!A:A) -> 43 | F61: =_xlfn.XLOOKUP(G61,Sheet1!F:F,Sheet1!G:G) -> 经腹腔镜多囊肾去顶减压术 | G61: 003311010150000-33110101502 | I61: 2985 | J61: 2720 | K61: 2310 | M61: 2000 | N61: 1850 | O61: 1580 | P61: 1 | Q61: 1 | R61: main | S61: 0 | T61: 7 | U61: 8 | V61: 0 | W61: -6895 | X61: -6960 | Y61: 0 | Z61: -6895 | AA61: -5730 | AB61: 0 | AC61: =Z61+AA61+AB61 -> -12625
A62: 137 | B62: =_xlfn.XLOOKUP(G62,Sheet1!E:E,Sheet1!A:A) -> 3226 | C62: 201 | D62: =_xlfn.XLOOKUP(G62,'规范整合泌尿系统医疗服务价格映射表12.11 (2)'!T:T,'规范整合泌尿系统医疗服务价格映射表12.11 (2)'!A:A) -> 44 | E62: 肾部分切除费 | F62: =_xlfn.XLOOKUP(G62,Sheet1!F:F,Sheet1!G:G) -> 肾部分切除术 | G62: 003311010090000-331101009 | I62: 3290 | J62: 2960 | K62: 2365 | M62: 3200 | N62: 2900 | O62: 2500 | P62: 1 | Q62: 1 | R62: main | S62: 0 | T62: 3 | U62: 3.5 | V62: 0 | W62: -270 | X62: -210 | Y62: 0 | Z62: -270 | AA62: -210 | AB62: 0 | AC62: =Z62+AA62+AB62 -> -480
A63: 72 | B63: =_xlfn.XLOOKUP(G63,Sheet1!E:E,Sheet1!A:A) -> 3227 | C63: 201 | D63: =_xlfn.XLOOKUP(G63,'规范整合泌尿系统医疗服务价格映射表12.11 (2)'!T:T,'规范整合泌尿系统医疗服务价格映射表12.11 (2)'!A:A) -> 44 | F63: =_xlfn.XLOOKUP(G63,Sheet1!F:F,Sheet1!G:G) -> 经腹腔镜肾部分切除术 | G63: 003311010090000-33110100902 | I63: 3915 | J63: 3560 | K63: 2875 | M63: 3200 | N63: 2900 | O63: 2500 | P63: 1 | Q63: 1 | R63: main | S63: 0 | T63: 151 | U63: 52 | V63: 0 | W63: -107965 | X63: -34320 | Y63: 0 | Z63: -107965 | AA63: -34320 | AB63: 0 | AC63: =Z63+AA63+AB63 -> -142285
A64: 83 | B64: =_xlfn.XLOOKUP(G64,Sheet1!E:E,Sheet1!A:A) -> 3229 | C64: 201 | D64: =_xlfn.XLOOKUP(G64,'规范整合泌尿系统医疗服务价格映射表12.11 (2)'!T:T,'规范整合泌尿系统医疗服务价格映射表12.11 (2)'!A:A) -> 44 | F64: =_xlfn.XLOOKUP(G64,Sheet1!F:F,Sheet1!G:G) -> 经腹腔镜肾肿瘤剔除术 | G64: 003311010070000-33110100702 | I64: 3665 | J64: 3340 | K64: 2840 | M64: 3200 | N64: 2900 | O64: 2500 | P64: 1 | Q64: 1 | R64: main | S64: 0 | T64: 1 | U64: 0 | V64: 1 | W64: -465 | X64: 0 | Y64: -340 | Z64: -465 | AA64: 0 | AB64: -340 | AC64: =Z64+AA64+AB64 -> -805
A65: 92 | B65: =_xlfn.XLOOKUP(G65,Sheet1!E:E,Sheet1!A:A) -> 3230 | C65: 201 | D65: =_xlfn.XLOOKUP(G65,'规范整合泌尿系统医疗服务价格映射表12.11 (2)'!T:T,'规范整合泌尿系统医疗服务价格映射表12.11 (2)'!A:A) -> 44 | F65: =_xlfn.XLOOKUP(G65,Sheet1!F:F,Sheet1!G:G) -> 肾肿瘤腔静脉内瘤栓切取术 | G65: 003311010250000-331101025 | I65: 6240 | J65: 5620 | K65: 4780 | M65: 0 | N65: 0 | O65: 0 | P65: 1 | Q65: 1 | R65: main | S65: 0 | T65: 0.5 | U65: 0 | V65: 0 | W65: -3120 | X65: 0 | Y65: 0 | Z65: -3120 | AA65: 0 | AB65: 0 | AC65: =Z65+AA65+AB65 -> -3120
A66: 196 | B66: =_xlfn.XLOOKUP(G66,Sheet1!E:E,Sheet1!A:A) -> 3242 | C66: 201 | D66: =_xlfn.XLOOKUP(G66,'规范整合泌尿系统医疗服务价格映射表12.11 (2)'!T:T,'规范整合泌尿系统医疗服务价格映射表12.11 (2)'!A:A) -> 45 | E66: 肾全切费 | F66: =_xlfn.XLOOKUP(G66,Sheet1!F:F,Sheet1!G:G) -> 经输尿管镜肿瘤切除术 | G66: 003110000230000-311000023 | I66: 880 | J66: 800 | K66: 680 | M66: 3100 | N66: 2800 | O66: 2400 | P66: 1 | Q66: 1 | R66: main | S66: 0 | T66: 1 | U66: 1 | V66: 0 | W66: 2220 | X66: 2000 | Y66: 0 | Z66: 2220 | AA66: 2000 | AB66: 0 | AC66: =Z66+AA66+AB66 -> 4220
A67: 77 | B67: =_xlfn.XLOOKUP(G67,Sheet1!E:E,Sheet1!A:A) -> 3243 | C67: 201 | D67: =_xlfn.XLOOKUP(G67,'规范整合泌尿系统医疗服务价格映射表12.11 (2)'!T:T,'规范整合泌尿系统医疗服务价格映射表12.11 (2)'!A:A) -> 45 | F67: =_xlfn.XLOOKUP(G67,Sheet1!F:F,Sheet1!G:G) -> 经输尿管镜肿瘤切除术（激光法、液电法） | G67: 003110000230000-31100002301 | I67: 1100 | J67: 1000 | K67: 850 | M67: 3100 | N67: 2800 | O67: 2400 | P67: 1 | Q67: 1 | R67: main | S67: 0 | T67: 2 | U67: 1.5 | V67: 0 | W67: 4000 | X67: 2700 | Y67: 0 | Z67: 4000 | AA67: 2700 | AB67: 0 | AC67: =Z67+AA67+AB67 -> 6700
A68: 60 | B68: =_xlfn.XLOOKUP(G68,Sheet1!E:E,Sheet1!A:A) -> 3244 | C68: 201 | D68: =_xlfn.XLOOKUP(G68,'规范整合泌尿系统医疗服务价格映射表12.11 (2)'!T:T,'规范整合泌尿系统医疗服务价格映射表12.11 (2)'!A:A) -> 45 | F68: =_xlfn.XLOOKUP(G68,Sheet1!F:F,Sheet1!G:G) -> 根治性肾切除术 | G68: 003311010100000-331101010 | I68: 4740 | J68: 4270 | K68: 3630 | M68: 3100 | N68: 2800 | O68: 2400 | P68: 1 | Q68: 1 | R68: main | S68: 0 | T68: 2 | U68: 2 | V68: 0 | W68: -3280 | X68: -2940 | Y68: 0 | Z68: -3280 | AA68: -2940 | AB68: 0 | AC68: =Z68+AA68+AB68 -> -6220
A69: 82 | B69: =_xlfn.XLOOKUP(G69,Sheet1!E:E,Sheet1!A:A) -> 3245 | C69: 201 | D69: =_xlfn.XLOOKUP(G69,'规范整合泌尿系统医疗服务价格映射表12.11 (2)'!T:T,'规范整合泌尿系统医疗服务价格映射表12.11 (2)'!A:A) -> 45 | F69: =_xlfn.XLOOKUP(G69,Sheet1!F:F,Sheet1!G:G) -> 经腹腔镜根治性肾切除术 | G69: 003311010100000-33110101002 | I69: 5365 | J69: 4870 | K69: 4140 | M69: 3100 | N69: 2800 | O69: 2400 | P69: 1 | Q69: 1 | R69: main | S69: 0 | T69: 88 | U69: 18 | V69: 0 | W69: -199320 | X69: -37260 | Y69: 0 | Z69: -199320 | AA69: -37260 | AB69: 0 | AC69: =Z69+AA69+AB69 -> -236580
A70: 27 | B70: =_xlfn.XLOOKUP(G70,Sheet1!E:E,Sheet1!A:A) -> 3246 | C70: 201 | D70: =_xlfn.XLOOKUP(G70,'规范整合泌尿系统医疗服务价格映射表12.11 (2)'!T:T,'规范整合泌尿系统医疗服务价格映射表12.11 (2)'!A:A) -> 45 | F70: =_xlfn.XLOOKUP(G70,Sheet1!F:F,Sheet1!G:G) -> 肾切除术 | G70: 003311010080000-331101008 | I70: 2530 | J70: 2280 | K70: 1940 | M70: 3100 | N70: 2800 | O70: 2400 | P70: 1 | Q70: 1 | R70: main | S70: 0 | T70: 8 | U70: 6.5 | V70: 0 | W70: 4560 | X70: 3380 | Y70: 0 | Z70: 4560 | AA70: 3380 | AB70: 0 | AC70: =Z70+AA70+AB70 -> 7940
A71: 40 | B71: =_xlfn.XLOOKUP(G71,Sheet1!E:E,Sheet1!A:A) -> 3247 | C71: 201 | D71: =_xlfn.XLOOKUP(G71,'规范整合泌尿系统医疗服务价格映射表12.11 (2)'!T:T,'规范整合泌尿系统医疗服务价格映射表12.11 (2)'!A:A) -> 45 | F71: =_xlfn.XLOOKUP(G71,Sheet1!F:F,Sheet1!G:G) -> 经腹腔镜肾切除术 | G71: 003311010080001-33110100802 | I71: 3155 | J71: 2880 | K71: 2450 | M71: 3100 | N71: 2800 | O71: 2400 | P71: 1 | Q71: 1 | R71: main | S71: 0 | T71: 69 | U71: 24 | V71: 1 | W71: -3795 | X71: -1920 | Y71: -50 | Z71: -3795 | AA71: -1920 | AB71: -50 | AC71: =Z71+AA71+AB71 -> -5765
A72: 186 | B72: =_xlfn.XLOOKUP(G72,Sheet1!E:E,Sheet1!A:A) -> 3252 | C72: 201 | D72: =_xlfn.XLOOKUP(G72,'规范整合泌尿系统医疗服务价格映射表12.11 (2)'!T:T,'规范整合泌尿系统医疗服务价格映射表12.11 (2)'!A:A) -> 46 | E72: 肾上腺部分切除费 | F72: =_xlfn.XLOOKUP(G72,Sheet1!F:F,Sheet1!G:G) -> 肾上腺切除术 | G72: 003303000210000-330300021 | I72: 3090 | J72: 2780 | K72: 2360 | M72: 3780 | N72: 3430 | O72: 2930 | P72: 1 | Q72: 1 | R72: main | S72: 0 | T72: 4 | U72: 1.5 | V72: 0 | W72: 2760 | X72: 975 | Y72: 0 | Z72: 2760 | AA72: 975 | AB72: 0 | AC72: =Z72+AA72+AB72 -> 3735
A73: 151 | B73: =_xlfn.XLOOKUP(G73,Sheet1!E:E,Sheet1!A:A) -> 3253 | C73: 201 | D73: =_xlfn.XLOOKUP(G73,'规范整合泌尿系统医疗服务价格映射表12.11 (2)'!T:T,'规范整合泌尿系统医疗服务价格映射表12.11 (2)'!A:A) -> 46 | F73: =_xlfn.XLOOKUP(G73,Sheet1!F:F,Sheet1!G:G) -> 经腹腔镜肾上腺切除术 | G73: 003303000210002-33030002102 | I73: 3715 | J73: 3380 | K73: 2870 | M73: 3780 | N73: 3430 | O73: 2930 | P73: 1 | Q73: 1 | R73: main | S73: 0 | T73: 201 | U73: 56 | V73: 0 | W73: 13065 | X73: 2800 | Y73: 0 | Z73: 13065 | AA73: 3310 | AB73: 0 | AC73: =Z73+AA73+AB73 -> 16375
A74: 176 | B74: =_xlfn.XLOOKUP(G74,Sheet1!E:E,Sheet1!A:A) -> 3255 | C74: 201 | D74: =_xlfn.XLOOKUP(G74,'规范整合泌尿系统医疗服务价格映射表12.11 (2)'!T:T,'规范整合泌尿系统医疗服务价格映射表12.11 (2)'!A:A) -> 分项 | E74: 肾上腺部分切除费-肾上腺嗜铬细胞瘤切除（加收） | F74: =_xlfn.XLOOKUP(G74,Sheet1!F:F,Sheet1!G:G) -> 经腹腔镜肾上腺嗜铬细胞瘤切除术 | G74: 003303000220000-33030002202 | I74: 4755 | J74: 4320 | K74: 3670 | M74: 4755 | N74: 4320 | O74: 3680 | P74: 1 | Q74: 1 | R74: main | S74: 0 | T74: 9 | U74: 6 | V74: 0 | W74: 0 | X74: 0 | Y74: 0 | Z74: 0 | AA74: 0 | AB74: 0 | AC74: =Z74+AA74+AB74 -> 0
A75: 223 | B75: =_xlfn.XLOOKUP(G75,Sheet1!E:E,Sheet1!A:A) -> 3262 | C75: 201 | D75: =_xlfn.XLOOKUP(G75,'规范整合泌尿系统医疗服务价格映射表12.11 (2)'!T:T,'规范整合泌尿系统医疗服务价格映射表12.11 (2)'!A:A) -> 49 | E75: 输尿管部分切除费 | F75: =_xlfn.XLOOKUP(G75,Sheet1!F:F,Sheet1!G:G) -> 输尿管狭窄段切除再吻合术 | G75: 003311020090000-331102009 | I75: 2375 | J75: 2140 | K75: 1710 | M75: 2900 | N75: 2600 | O75: 2250 | P75: 1 | Q75: 1 | R75: main | S75: 0 | T75: 1.5 | U75: 0 | V75: 0 | W75: 787.5 | X75: 0 | Y75: 0 | Z75: 787.5 | AA75: 0 | AB75: 0 | AC75: =Z75+AA75+AB75 -> 787.5
A76: 143 | B76: =_xlfn.XLOOKUP(G76,Sheet1!E:E,Sheet1!A:A) -> 3263 | C76: 201 | D76: =_xlfn.XLOOKUP(G76,'规范整合泌尿系统医疗服务价格映射表12.11 (2)'!T:T,'规范整合泌尿系统医疗服务价格映射表12.11 (2)'!A:A) -> 49 | F76: =_xlfn.XLOOKUP(G76,Sheet1!F:F,Sheet1!G:G) -> 经腹腔镜输尿管狭窄段切除再吻合术 | G76: 003311020090000-33110200902 | I76: 3000 | J76: 2740 | K76: 2220 | M76: 2900 | N76: 2600 | O76: 2250 | P76: 1 | Q76: 1 | R76: main | S76: 0 | T76: 12 | U76: 2 | V76: 0 | W76: -1200 | X76: -280 | Y76: 0 | Z76: -1200 | AA76: -280 | AB76: 0 | AC76: =Z76+AA76+AB76 -> -1480
A77: 201 | B77: =_xlfn.XLOOKUP(G77,Sheet1!E:E,Sheet1!A:A) -> 3264 | C77: 201 | D77: =_xlfn.XLOOKUP(G77,'规范整合泌尿系统医疗服务价格映射表12.11 (2)'!T:T,'规范整合泌尿系统医疗服务价格映射表12.11 (2)'!A:A) -> 49 | F77: =_xlfn.XLOOKUP(G77,Sheet1!F:F,Sheet1!G:G) -> 输尿管膀胱再植术 | G77: 003311020120000-331102012 | I77: 1860 | J77: 1670 | K77: 1420 | M77: 2900 | N77: 2600 | O77: 2250 | P77: 1 | Q77: 1 | R77: main | S77: 0 | T77: 3 | U77: 4 | V77: 0.5 | W77: 3120 | X77: 3720 | Y77: 415 | Z77: 3120 | AA77: 3720 | AB77: 415 | AC77: =Z77+AA77+AB77 -> 7255
A78: 133 | B78: =_xlfn.XLOOKUP(G78,Sheet1!E:E,Sheet1!A:A) -> 3265 | C78: 201 | D78: =_xlfn.XLOOKUP(G78,'规范整合泌尿系统医疗服务价格映射表12.11 (2)'!T:T,'规范整合泌尿系统医疗服务价格映射表12.11 (2)'!A:A) -> 49 | F78: =_xlfn.XLOOKUP(G78,Sheet1!F:F,Sheet1!G:G) -> 经腹腔镜输尿管膀胱再植术 | G78: 003311020120000-33110201202 | I78: 2485 | J78: 2270 | K78: 1930 | M78: 2900 | N78: 2600 | O78: 2250 | P78: 1 | Q78: 1 | R78: main | S78: 0 | T78: 11 | U78: 3 | V78: 1 | W78: 4565 | X78: 990 | Y78: 320 | Z78: 4565 | AA78: 990 | AB78: 320 | AC78: =Z78+AA78+AB78 -> 5875
A79: 175 | B79: =_xlfn.XLOOKUP(G79,Sheet1!E:E,Sheet1!A:A) -> 3270 | C79: 201 | D79: =_xlfn.XLOOKUP(G79,'规范整合泌尿系统医疗服务价格映射表12.11 (2)'!T:T,'规范整合泌尿系统医疗服务价格映射表12.11 (2)'!A:A) -> 49 | F79: =_xlfn.XLOOKUP(G79,Sheet1!F:F,Sheet1!G:G) -> 输尿管损伤修补术 | G79: 003311020080000-331102008 | I79: 1500 | J79: 1440 | K79: 1224 | M79: 1478.75 | N79: 1312.5 | O79: 1155 | P79: 1 | Q79: 1 | R79: main | S79: 0 | T79: 0 | U79: 1 | V79: 0 | W79: 0 | X79: -127.5 | Y79: 0 | Z79: 0 | AA79: -127.5 | AB79: 0 | AC79: =Z79+AA79+AB79 -> -127.5
A80: 8 | B80: =_xlfn.XLOOKUP(G80,Sheet1!E:E,Sheet1!A:A) -> 3272 | C80: 201 | D80: =_xlfn.XLOOKUP(G80,'规范整合泌尿系统医疗服务价格映射表12.11 (2)'!T:T,'规范整合泌尿系统医疗服务价格映射表12.11 (2)'!A:A) -> 49 | F80: =_xlfn.XLOOKUP(G80,Sheet1!F:F,Sheet1!G:G) -> 输尿管开口囊肿切除术 | G80: 003311020100000-331102010 | I80: 1860 | J80: 1670 | K80: 1420 | M80: 1478.75 | N80: 1312.5 | O80: 1155 | P80: 1 | Q80: 1 | R80: main | S80: 0 | T80: 2 | U80: 6 | V80: 1.5 | W80: -762.5 | X80: -2145 | Y80: -397.5 | Z80: -762.5 | AA80: -2145 | AB80: -397.5 | AC80: =Z80+AA80+AB80 -> -3305
A81: 18 | B81: =_xlfn.XLOOKUP(G81,Sheet1!E:E,Sheet1!A:A) -> 3274 | C81: 201 | D81: =_xlfn.XLOOKUP(G81,'规范整合泌尿系统医疗服务价格映射表12.11 (2)'!T:T,'规范整合泌尿系统医疗服务价格映射表12.11 (2)'!A:A) -> 49 | F81: =_xlfn.XLOOKUP(G81,Sheet1!F:F,Sheet1!G:G) -> 输尿管残端切除术 | G81: 003311020110000-331102011 | I81: 1250 | J81: 1200 | K81: 1020 | M81: 1478.75 | N81: 1312.5 | O81: 1155 | P81: 1 | Q81: 1 | R81: main | S81: 0 | T81: 9.5 | U81: 1.5 | V81: 0 | W81: 2173.125 | X81: 168.75 | Y81: 0 | Z81: 2173.125 | AA81: 168.75 | AB81: 0 | AC81: =Z81+AA81+AB81 -> 2341.875
A82: 6 | B82: =_xlfn.XLOOKUP(G82,Sheet1!E:E,Sheet1!A:A) -> 3277 | C82: 201 | D82: =_xlfn.XLOOKUP(G82,'规范整合泌尿系统医疗服务价格映射表12.11 (2)'!T:T,'规范整合泌尿系统医疗服务价格映射表12.11 (2)'!A:A) -> 49 | F82: =_xlfn.XLOOKUP(G82,Sheet1!F:F,Sheet1!G:G) -> 经膀胱镜输尿管间嵴切除术 | G82: 003312030120000-33120301202 | I82: 1125 | J82: 1065 | K82: 904 | M82: 1478.75 | N82: 1312.5 | O82: 1155 | P82: 1 | Q82: 1 | R82: main | S82: 0 | T82: 0 | U82: 2 | V82: 0 | W82: 0 | X82: 495 | Y82: 0 | Z82: 0 | AA82: 495 | AB82: 0 | AC82: =Z82+AA82+AB82 -> 495
A83: 117 | B83: =_xlfn.XLOOKUP(G83,Sheet1!E:E,Sheet1!A:A) -> 3278 | C83: 201 | D83: =_xlfn.XLOOKUP(G83,'规范整合泌尿系统医疗服务价格映射表12.11 (2)'!T:T,'规范整合泌尿系统医疗服务价格映射表12.11 (2)'!A:A) -> 分项 | E83: 输尿管部分切除费-儿童（加收） | F83: =_xlfn.XLOOKUP(G83,Sheet1!F:F,Sheet1!G:G) -> 小儿输尿管膀胱再植术 | G83: 003311020120000-33110201201 | I83: 2420 | J83: 2170 | K83: 1845 | M83: 3770 | N83: 3380 | O83: 2925 | P83: 1 | Q83: 1 | R83: main | S83: 0 | T83: 1 | U83: 0 | V83: 0 | W83: 1350 | X83: 0 | Y83: 0 | Z83: 1350 | AA83: 0 | AB83: 0 | AC83: =Z83+AA83+AB83 -> 1350
A84: 21 | B84: =_xlfn.XLOOKUP(G84,Sheet1!E:E,Sheet1!A:A) -> 3279 | C84: 201 | D84: =_xlfn.XLOOKUP(G84,'规范整合泌尿系统医疗服务价格映射表12.11 (2)'!T:T,'规范整合泌尿系统医疗服务价格映射表12.11 (2)'!A:A) -> 分项 | F84: =_xlfn.XLOOKUP(G84,Sheet1!F:F,Sheet1!G:G) -> 小儿经腹腔镜输尿管膀胱再植术 | G84: 003311020120000-33110201203 | I84: 3045 | J84: 2770 | K84: 2355 | M84: 3770 | N84: 3380 | O84: 2925 | P84: 1 | Q84: 1 | R84: main | S84: 0 | T84: 4 | U84: 0 | V84: 0 | W84: 2900 | X84: 0 | Y84: 0 | Z84: 2900 | AA84: 0 | AB84: 0 | AC84: =Z84+AA84+AB84 -> 2900
A85: 91 | B85: =_xlfn.XLOOKUP(G85,Sheet1!E:E,Sheet1!A:A) -> 3281 | C85: 201 | D85: =_xlfn.XLOOKUP(G85,'规范整合泌尿系统医疗服务价格映射表12.11 (2)'!T:T,'规范整合泌尿系统医疗服务价格映射表12.11 (2)'!A:A) -> 50 | E85: 肾输尿管全长切除费 | F85: =_xlfn.XLOOKUP(G85,Sheet1!F:F,Sheet1!G:G) -> 经腹腔镜重复肾重复输尿管切除术 | G85: 003311010110000-33110101102 | I85: 3665 | J85: 3340 | K85: 2840 | M85: 3800 | N85: 3420 | O85: 2950 | P85: 1 | Q85: 1 | R85: main | S85: 0 | T85: 4 | U85: 1 | V85: 0 | W85: 540 | X85: 80 | Y85: 0 | Z85: 540 | AA85: 80 | AB85: 0 | AC85: =Z85+AA85+AB85 -> 620
A86: 190 | B86: =_xlfn.XLOOKUP(G86,Sheet1!E:E,Sheet1!A:A) -> 3282 | C86: 201 | D86: =_xlfn.XLOOKUP(G86,'规范整合泌尿系统医疗服务价格映射表12.11 (2)'!T:T,'规范整合泌尿系统医疗服务价格映射表12.11 (2)'!A:A) -> 50 | F86: =_xlfn.XLOOKUP(G86,Sheet1!F:F,Sheet1!G:G) -> 肾盂癌根治术 | G86: 003311020010000-331102001 | I86: 4130 | J86: 3720 | K86: 3160 | M86: 3800 | N86: 3420 | O86: 2950 | P86: 1 | Q86: 1 | R86: main | S86: 0 | T86: 1 | U86: 1 | V86: 0 | W86: -330 | X86: -300 | Y86: 0 | Z86: -330 | AA86: -300 | AB86: 0 | AC86: =Z86+AA86+AB86 -> -630
A87: 4 | B87: =_xlfn.XLOOKUP(G87,Sheet1!E:E,Sheet1!A:A) -> 3283 | C87: 201 | D87: =_xlfn.XLOOKUP(G87,'规范整合泌尿系统医疗服务价格映射表12.11 (2)'!T:T,'规范整合泌尿系统医疗服务价格映射表12.11 (2)'!A:A) -> 50 | F87: =_xlfn.XLOOKUP(G87,Sheet1!F:F,Sheet1!G:G) -> 经腹腔镜肾盂癌根治术 | G87: 003311020010001-33110200102 | I87: 4755 | J87: 4320 | K87: 3670 | M87: 3800 | N87: 3420 | O87: 2950 | P87: 1 | Q87: 1 | R87: main | S87: 0 | T87: 28 | U87: 11 | V87: 1 | W87: -26740 | X87: -9900 | Y87: -720 | Z87: -26740 | AA87: -9900 | AB87: -720 | AC87: =Z87+AA87+AB87 -> -37360
A88: 34 | B88: =_xlfn.XLOOKUP(G88,Sheet1!E:E,Sheet1!A:A) -> 3288 | C88: 201 | D88: =_xlfn.XLOOKUP(G88,'规范整合泌尿系统医疗服务价格映射表12.11 (2)'!T:T,'规范整合泌尿系统医疗服务价格映射表12.11 (2)'!A:A) -> 51 | E88: 输尿管支架置入费 | F88: =_xlfn.XLOOKUP(G88,Sheet1!F:F,Sheet1!G:G) -> 经膀胱镜输尿管支架置入术 | G88: 003110000270000-311000027 | I88: 275 | J88: 250 | K88: 212.5 | M88: 330 | N88: 300 | O88: 255 | P88: 1 | Q88: 1 | R88: main | S88: 0 | T88: 369 | U88: 475 | V88: 433.5 | W88: 20295 | X88: 23750 | Y88: 18423.75 | Z88: 20295 | AA88: 23612.5 | AB88: 18423.75 | AC88: =Z88+AA88+AB88 -> 62331.25
A89: 46 | B89: =_xlfn.XLOOKUP(G89,Sheet1!E:E,Sheet1!A:A) -> 3289 | C89: 201 | D89: =_xlfn.XLOOKUP(G89,'规范整合泌尿系统医疗服务价格映射表12.11 (2)'!T:T,'规范整合泌尿系统医疗服务价格映射表12.11 (2)'!A:A) -> 51 | F89: =_xlfn.XLOOKUP(G89,Sheet1!F:F,Sheet1!G:G) -> 输尿管支架管冲洗 | G89: 003110000290000-311000029 | I89: 11 | J89: 10 | K89: 8.5 | M89: 0 | N89: 0 | O89: 0 | P89: 1 | Q89: 1 | R89: main | S89: 0 | T89: 1759 | U89: 80 | V89: 1320 | W89: -19349 | X89: -800 | Y89: -11220 | Z89: -19349 | AA89: -800 | AB89: -11220 | AC89: =Z89+AA89+AB89 -> -31369
A90: 129 | B90: =_xlfn.XLOOKUP(G90,Sheet1!E:E,Sheet1!A:A) -> 3290 | C90: 201 | D90: =_xlfn.XLOOKUP(G90,'规范整合泌尿系统医疗服务价格映射表12.11 (2)'!T:T,'规范整合泌尿系统医疗服务价格映射表12.11 (2)'!A:A) -> 51 | F90: =_xlfn.XLOOKUP(G90,Sheet1!F:F,Sheet1!G:G) -> 经膀胱镜输尿管插管术 | G90: 003110000210000-311000021 | I90: 220 | J90: 200 | K90: 170 | M90: 330 | N90: 300 | O90: 255 | P90: 1 | Q90: 1 | R90: main | S90: 0 | T90: 35 | U90: 4.5 | V90: 0 | W90: 3850 | X90: 450 | Y90: 0 | Z90: 3850 | AA90: 450 | AB90: 0 | AC90: =Z90+AA90+AB90 -> 4300
A91: 86 | B91: =_xlfn.XLOOKUP(G91,Sheet1!E:E,Sheet1!A:A) -> 3291 | C91: 201 | D91: =_xlfn.XLOOKUP(G91,'规范整合泌尿系统医疗服务价格映射表12.11 (2)'!T:T,'规范整合泌尿系统医疗服务价格映射表12.11 (2)'!A:A) -> 51 | F91: =_xlfn.XLOOKUP(G91,Sheet1!F:F,Sheet1!G:G) -> 经输尿管镜支架置入术 | G91: 003110000280000-311000028 | I91: 220 | J91: 200 | K91: 170 | M91: 330 | N91: 300 | O91: 255 | P91: 1 | Q91: 1 | R91: main | S91: 0 | T91: 762.4 | U91: 486.8 | V91: 25.5 | W91: 83864 | X91: 48680 | Y91: 2167.5 | Z91: 83864 | AA91: 61805 | AB91: 2167.5 | AC91: =Z91+AA91+AB91 -> 147836.5
A92: 106 | B92: =_xlfn.XLOOKUP(G92,Sheet1!E:E,Sheet1!A:A) -> 3292 | C92: 201 | D92: =_xlfn.XLOOKUP(G92,'规范整合泌尿系统医疗服务价格映射表12.11 (2)'!T:T,'规范整合泌尿系统医疗服务价格映射表12.11 (2)'!A:A) -> 52 | E92: 输尿管支架取出费 | F92: =_xlfn.XLOOKUP(G92,Sheet1!F:F,Sheet1!G:G) -> 经输尿管镜支架取出术 | G92: 003110000280100-31100002801 | I92: 220 | J92: 200 | K92: 170 | M92: 320 | N92: 290 | O92: 245 | P92: 1 | Q92: 1 | R92: main | S92: 0 | T92: 877.7 | U92: 249 | V92: 37 | W92: 87770 | X92: 22410 | Y92: 2775 | Z92: 87770 | AA92: 22840 | AB92: 2775 | AC92: =Z92+AA92+AB92 -> 113385
A93: 55 | B93: =_xlfn.XLOOKUP(G93,Sheet1!E:E,Sheet1!A:A) -> 3293 | C93: 201 | D93: =_xlfn.XLOOKUP(G93,'规范整合泌尿系统医疗服务价格映射表12.11 (2)'!T:T,'规范整合泌尿系统医疗服务价格映射表12.11 (2)'!A:A) -> 52 | F93: =_xlfn.XLOOKUP(G93,Sheet1!F:F,Sheet1!G:G) -> 经膀胱镜输尿管支架取出术 | G93: 003110000270100-31100002701 | I93: 275 | J93: 250 | K93: 212.5 | M93: 320 | N93: 290 | O93: 245 | P93: 1 | Q93: 1 | R93: main | S93: 0 | T93: 717 | U93: 1354 | V93: 376 | W93: 32265 | X93: 54160 | Y93: 12220 | Z93: 32265 | AA93: 54085 | AB93: 12220 | AC93: =Z93+AA93+AB93 -> 98570
A94: 96 | B94: =_xlfn.XLOOKUP(G94,Sheet1!E:E,Sheet1!A:A) -> 3294 | C94: 201 | D94: =_xlfn.XLOOKUP(G94,'规范整合泌尿系统医疗服务价格映射表12.11 (2)'!T:T,'规范整合泌尿系统医疗服务价格映射表12.11 (2)'!A:A) -> 53 | E94: 膀胱颈/尿道悬吊费 | F94: =_xlfn.XLOOKUP(G94,Sheet1!F:F,Sheet1!G:G) -> 膀胱颈悬吊术 | G94: 003311030220000-331103022 | I94: 1500 | J94: 1440 | K94: 1224 | M94: 1070 | N94: 970 | O94: 820 | P94: 1 | Q94: 1 | R94: main | S94: 0 | T94: 1.5 | U94: 13 | V94: 0 | W94: -645 | X94: -6110 | Y94: 0 | Z94: -645 | AA94: -5390 | AB94: 0 | AC94: =Z94+AA94+AB94 -> -6035
A95: 124 | B95: =_xlfn.XLOOKUP(G95,Sheet1!E:E,Sheet1!A:A) -> 3295 | C95: 201 | D95: =_xlfn.XLOOKUP(G95,'规范整合泌尿系统医疗服务价格映射表12.11 (2)'!T:T,'规范整合泌尿系统医疗服务价格映射表12.11 (2)'!A:A) -> 53 | F95: =_xlfn.XLOOKUP(G95,Sheet1!F:F,Sheet1!G:G) -> 经腹腔镜膀胱颈悬吊术 | G95: 003311030220001-33110302202 | I95: 2125 | J95: 2040 | K95: 1734 | M95: 1070 | N95: 970 | O95: 820 | P95: 1 | Q95: 1 | R95: main | S95: 0 | T95: 0 | U95: 1 | V95: 0 | W95: 0 | X95: -1070 | Y95: 0 | Z95: 0 | AA95: -1070 | AB95: 0 | AC95: =Z95+AA95+AB95 -> -1070
A96: 166 | B96: =_xlfn.XLOOKUP(G96,Sheet1!E:E,Sheet1!A:A) -> 3296 | C96: 201 | D96: =_xlfn.XLOOKUP(G96,'规范整合泌尿系统医疗服务价格映射表12.11 (2)'!T:T,'规范整合泌尿系统医疗服务价格映射表12.11 (2)'!A:A) -> 53 | F96: =_xlfn.XLOOKUP(G96,Sheet1!F:F,Sheet1!G:G) -> 尿道悬吊延长术 | G96: 003311040220000-331104022 | I96: 750 | J96: 720 | K96: 612 | M96: 1070 | N96: 970 | O96: 820 | P96: 1 | Q96: 1 | R96: main | S96: 0 | T96: 54 | U96: 28.5 | V96: 0 | W96: 17280 | X96: 7125 | Y96: 0 | Z96: 17280 | AA96: 7647 | AB96: 0 | AC96: =Z96+AA96+AB96 -> 24927
A97: 122 | B97: =_xlfn.XLOOKUP(G97,Sheet1!E:E,Sheet1!A:A) -> 3302 | C97: 201 | D97: =_xlfn.XLOOKUP(G97,'规范整合泌尿系统医疗服务价格映射表12.11 (2)'!T:T,'规范整合泌尿系统医疗服务价格映射表12.11 (2)'!A:A) -> 54 | E97: 膀胱灌注费 | F97: =_xlfn.XLOOKUP(G97,Sheet1!F:F,Sheet1!G:G) -> 膀胱灌注 | G97: 003110000310000-311000031 | I97: 22 | J97: 20 | K97: 17 | M97: 22 | N97: 20 | O97: 17 | P97: 1 | Q97: 1 | R97: main | S97: 0 | T97: 1035.3 | U97: 1198.9 | V97: 58 | W97: 0 | X97: 0 | Y97: 0 | Z97: 0 | AA97: -259.8 | AB97: 0 | AC97: =Z97+AA97+AB97 -> -259.8
A98: 150 | B98: =_xlfn.XLOOKUP(G98,Sheet1!E:E,Sheet1!A:A) -> 3303 | C98: 201 | D98: =_xlfn.XLOOKUP(G98,'规范整合泌尿系统医疗服务价格映射表12.11 (2)'!T:T,'规范整合泌尿系统医疗服务价格映射表12.11 (2)'!A:A) -> 55 | E98: 膀胱修补费 | F98: =_xlfn.XLOOKUP(G98,Sheet1!F:F,Sheet1!G:G) -> 膀胱破裂修补术 | G98: 003311030160000-331103016 | I98: 1125 | J98: 1080 | K98: 918 | M98: 1270 | N98: 1200 | O98: 1020 | P98: 1 | Q98: 1 | R98: main | S98: 0 | T98: 10.5 | U98: 3.5 | V98: 0 | W98: 1522.5 | X98: 420 | Y98: 0 | Z98: 1522.5 | AA98: 420 | AB98: 0 | AC98: =Z98+AA98+AB98 -> 1942.5
A99: 45 | B99: =_xlfn.XLOOKUP(G99,Sheet1!E:E,Sheet1!A:A) -> 3304 | C99: 201 | D99: =_xlfn.XLOOKUP(G99,'规范整合泌尿系统医疗服务价格映射表12.11 (2)'!T:T,'规范整合泌尿系统医疗服务价格映射表12.11 (2)'!A:A) -> 55 | F99: =_xlfn.XLOOKUP(G99,Sheet1!F:F,Sheet1!G:G) -> 经腹腔镜膀胱破裂修补术 | G99: 003311030160001-33110301602 | I99: 1750 | J99: 1680 | K99: 1428 | M99: 1270 | N99: 1200 | O99: 1020 | P99: 1 | Q99: 1 | R99: main | S99: 0 | T99: 3 | U99: 3 | V99: 0 | W99: -1440 | X99: -1440 | Y99: 0 | Z99: -1440 | AA99: -1440 | AB99: 0 | AC99: =Z99+AA99+AB99 -> -2880
A100: 206 | B100: =_xlfn.XLOOKUP(G100,Sheet1!E:E,Sheet1!A:A) -> 3305 | C100: 201 | D100: =_xlfn.XLOOKUP(G100,'规范整合泌尿系统医疗服务价格映射表12.11 (2)'!T:T,'规范整合泌尿系统医疗服务价格映射表12.11 (2)'!A:A) -> 55 | F100: =_xlfn.XLOOKUP(G100,Sheet1!F:F,Sheet1!G:G) -> 膀胱膨出修补术 | G100: 003311030170000-331103017 | I100: 1250 | J100: 1200 | K100: 1020 | M100: 1270 | N100: 1200 | O100: 1020 | P100: 1 | Q100: 1 | R100: main | S100: 0 | T100: 1 | U100: 1 | V100: 0 | W100: 20 | X100: 0 | Y100: 0 | Z100: 20 | AA100: 0 | AB100: 0 | AC100: =Z100+AA100+AB100 -> 20
A101: 49 | B101: =_xlfn.XLOOKUP(G101,Sheet1!E:E,Sheet1!A:A) -> 3315 | C101: 201 | D101: =_xlfn.XLOOKUP(G101,'规范整合泌尿系统医疗服务价格映射表12.11 (2)'!T:T,'规范整合泌尿系统医疗服务价格映射表12.11 (2)'!A:A) -> 56 | E101: 膀胱颈重建费 | F101: =_xlfn.XLOOKUP(G101,Sheet1!F:F,Sheet1!G:G) -> 膀胱颈重建术 | G101: 003311030210000-331103021 | I101: 2190 | J101: 1970 | K101: 1670 | M101: 2000 | N101: 1800 | O101: 1530 | P101: 1 | Q101: 1 | R101: main | S101: 0 | T101: 0 | U101: 0.5 | V101: 0 | W101: 0 | X101: -85 | Y101: 0 | Z101: 0 | AA101: -85 | AB101: 0 | AC101: =Z101+AA101+AB101 -> -85
A102: 125 | B102: =_xlfn.XLOOKUP(G102,Sheet1!E:E,Sheet1!A:A) -> 3323 | C102: 201 | D102: =_xlfn.XLOOKUP(G102,'规范整合泌尿系统医疗服务价格映射表12.11 (2)'!T:T,'规范整合泌尿系统医疗服务价格映射表12.11 (2)'!A:A) -> 57 | E102: 膀胱部分切除费 | F102: =_xlfn.XLOOKUP(G102,Sheet1!F:F,Sheet1!G:G) -> 膀胱部分切除术 | G102: 003311030030000-331103003 | I102: 2030 | J102: 1830 | K102: 1560 | M102: 2200 | N102: 2000 | O102: 1700 | P102: 1 | Q102: 1 | R102: main | S102: 0 | T102: 10.5 | U102: 3.5 | V102: 0 | W102: 1785 | X102: 595 | Y102: 0 | Z102: 1785 | AA102: 595 | AB102: 0 | AC102: =Z102+AA102+AB102 -> 2380
A103: 26 | B103: =_xlfn.XLOOKUP(G103,Sheet1!E:E,Sheet1!A:A) -> 3324 | C103: 201 | D103: =_xlfn.XLOOKUP(G103,'规范整合泌尿系统医疗服务价格映射表12.11 (2)'!T:T,'规范整合泌尿系统医疗服务价格映射表12.11 (2)'!A:A) -> 57 | F103: =_xlfn.XLOOKUP(G103,Sheet1!F:F,Sheet1!G:G) -> 经腹腔镜膀胱部分切除术 | G103: 003311030030000-33110300302 | I103: 2655 | J103: 2430 | K103: 2070 | M103: 2200 | N103: 2000 | O103: 1700 | P103: 1 | Q103: 1 | R103: main | S103: 0 | T103: 13 | U103: 0 | V103: 0 | W103: -5915 | X103: 0 | Y103: 0 | Z103: -5915 | AA103: 0 | AB103: 0 | AC103: =Z103+AA103+AB103 -> -5915
A104: 149 | B104: =_xlfn.XLOOKUP(G104,Sheet1!E:E,Sheet1!A:A) -> 3325 | C104: 201 | D104: =_xlfn.XLOOKUP(G104,'规范整合泌尿系统医疗服务价格映射表12.11 (2)'!T:T,'规范整合泌尿系统医疗服务价格映射表12.11 (2)'!A:A) -> 57 | F104: =_xlfn.XLOOKUP(G104,Sheet1!F:F,Sheet1!G:G) -> 膀胱憩室切除术 | G104: 003311030020000-331103002 | I104: 1500 | J104: 1440 | K104: 1224 | M104: 2200 | N104: 2000 | O104: 1700 | P104: 1 | Q104: 1 | R104: main | S104: 0 | T104: 0.5 | U104: 2 | V104: 0 | W104: 350 | X104: 1120 | Y104: 0 | Z104: 350 | AA104: 1120 | AB104: 0 | AC104: =Z104+AA104+AB104 -> 1470
A105: 97 | B105: =_xlfn.XLOOKUP(G105,Sheet1!E:E,Sheet1!A:A) -> 3326 | C105: 201 | D105: =_xlfn.XLOOKUP(G105,'规范整合泌尿系统医疗服务价格映射表12.11 (2)'!T:T,'规范整合泌尿系统医疗服务价格映射表12.11 (2)'!A:A) -> 57 | F105: =_xlfn.XLOOKUP(G105,Sheet1!F:F,Sheet1!G:G) -> 经腹腔镜膀胱憩室切除术 | G105: 003311030020000-33110300202 | I105: 2125 | J105: 2040 | K105: 1734 | M105: 2200 | N105: 2000 | O105: 1700 | P105: 1 | Q105: 1 | R105: main | S105: 0 | T105: 2 | U105: 2 | V105: 0 | W105: 150 | X105: -80 | Y105: 0 | Z105: 150 | AA105: -80 | AB105: 0 | AC105: =Z105+AA105+AB105 -> 70
A106: 216 | B106: =_xlfn.XLOOKUP(G106,Sheet1!E:E,Sheet1!A:A) -> 3327 | C106: 201 | D106: =_xlfn.XLOOKUP(G106,'规范整合泌尿系统医疗服务价格映射表12.11 (2)'!T:T,'规范整合泌尿系统医疗服务价格映射表12.11 (2)'!A:A) -> 57 | F106: =_xlfn.XLOOKUP(G106,Sheet1!F:F,Sheet1!G:G) -> 膀胱瘘管切除术 | G106: 003311030150000-331103015 | I106: 1000 | J106: 960 | K106: 816 | M106: 2200 | N106: 2000 | O106: 1700 | P106: 1 | Q106: 1 | R106: main | S106: 0 | T106: 0.5 | U106: 0 | V106: 0 | W106: 600 | X106: 0 | Y106: 0 | Z106: 600 | AA106: 0 | AB106: 0 | AC106: =Z106+AA106+AB106 -> 600
...
